Workbook
Name lender_paid_offset: #REF!

Sheet CONV
AJ1: PG 1 OF 12
B2: AmWest Corporate Office | T2: 45 DAYS | U2: -0.125
B3: 6 Pointe Dr. Suite 300
B4: Brea, CA 92821
B5: (714) 831-3333
B6: www.amwestwholesale.com
L7: Wholesale Rate sheet - Consumer Paid | O7: Effective: | R7: =TODAY() -> 46101
B9: FAST TRACK (FANNIE MAE & FREDDIE MAC)
B10: CONFORMING FIXED | Z10: HIGH BALANCE FIXED
B11: (FFT30) 30 YEAR | E11: (FMFT30) 30 YEAR | H11: (FFT20) 20 YEAR | K11: (FMFT20) 20 YEAR | N11: (FFT15) 15 YEAR | Q11: (FMFT15) 15 YEAR | T11: (FFT10) 10 YEAR | W11: (FMFT10) 10 YEAR | Z11: (FFT30HB) 30 YEAR | AC11: (FMFT30SC) 30 YEAR | AF11: ( FFT15HB) 15 YEAR | AI11: ( FMFT15SC) 15 YEAR
B12: RATE | C12: 30 Days | D12: 45 days | E12: RATE | F12: 30 Days | G12: 45 days | H12: RATE | I12: 30 Days | J12: 45 days | K12: RATE | L12: 30 Days | M12: 45 days | N12: RATE | O12: 30 Days | P12: 45 days | Q12: RATE | R12: 30 Days | S12: 45 days | T12: RATE | U12: 30 Days | V12: 45 days | W12: RATE | X12: 30 Days | Y12: 45 days | Z12: RATE | AA12: 30 Days | AB12: 45 days | AC12: RATE | AD12: 30 Days | AE12: 45 days | AF12: RATE | AG12: 30 Days | AH12: 45 days | AI12: RATE | AJ12: 30 Days | AK12: 45 days
B13: =LARGE('[1]Pricing '!$A$2506:$A$2531,1) -> 7.75 | C13: =100-VLOOKUP(B13,'[1]Pricing '!$A$2506:$K$2531,11,FALSE) -> -5.2391265 | D13: =C13-$U$2 -> -5.1141265 | E13: =LARGE('[1]Pricing '!$A$2677:$A$2702,1) -> 7.625 | F13: =100-VLOOKUP(E13,'[1]Pricing '!$A$2677:$K$2702,11,FALSE) -> -5.2757203 | G13: =F13-$U$2 -> -5.1507203 | H13: =LARGE('[1]Pricing '!$A$2648:$A$2673,1) -> 7.625 | I13: =100-VLOOKUP(H13,'[1]Pricing '!$A$2648:$K$2673,11,FALSE) -> -4.5407203 | J13: =I13-$U$2 -> -4.4157203 | K13: =LARGE('[1]Pricing '!$A$2733:$A$2758,1) -> 7.75 | L13: =100-VLOOKUP(K13,'[1]Pricing '!$A$2733:$K$2758,11,FALSE) -> -4.9841265 | M13: =L13-$U$2 -> -4.8591265 | N13: =LARGE('[1]Pricing '!$A$2534:$A$2558,1) -> 7.25 | O13: =100-VLOOKUP(N13,'[1]Pricing '!$A$2534:$K$2558,11,FALSE) -> -4.0152603 | P13: =O13-$U$2 -> -3.8902603 | Q13: =LARGE('[1]Pricing '!$A$2761:$A$2785,1) -> 7 | R13: =100-VLOOKUP(Q13,'[1]Pricing '!$A$2761:$K$2785,11,FALSE) -> -4.2350398 | S13: =R13-$U$2 -> -4.1100398 | T13: =LARGE('[1]Pricing '!$A$3052:$A$3077,1) -> 7.25 | U13: =100-VLOOKUP(T13,'[1]Pricing '!$A$3052:$K$3077,11,FALSE) -> -4.0712603 | V13: =U13-$U$2 -> -3.9462603 | W13: =LARGE('[1]Pricing '!$A$2788:$A$2812,1) -> 7.375 | X13: =100-VLOOKUP(W13,'[1]Pricing '!$A$2788:$K$2812,11,FALSE) -> -4.2670013 | Y13: =X13-$U$2 -> -4.1420013 | Z13: =LARGE('[1]Pricing '!$A$2561:$A$2586,1) -> 7.75 | AA13: =100-VLOOKUP(Z13,'[1]Pricing '!$A$2561:$K$2586,11,FALSE) -> -3.2067092 | AB13: =AA13-$U$2 -> -3.0817092 | AC13: =LARGE('[1]Pricing '!$A$2815:$A$2840,1) -> 7.75 | AD13: =100-VLOOKUP(AC13,'[1]Pricing '!$A$2815:$K$2840,11,FALSE) -> -3.2067092 | AE13: =AD13-$U$2 -> -3.0817092 | AF13: =LARGE('[1]Pricing '!$A$2589:$A$2614,1) -> 7.5 | AG13: =100-VLOOKUP(AF13,'[1]Pricing '!$A$2589:$K$2614,11,FALSE) -> -3.8437478 | AH13: =AG13-$U$2 -> -3.7187478 | AI13: =LARGE('[1]Pricing '!$A$2871:$A$2896,1) -> 7.25 | AJ13: =100-VLOOKUP(AI13,'[1]Pricing '!$A$2871:$K$2896,11,FALSE) -> -3.3422655 | AK13: =AJ13-$U$2 -> -3.2172655
B14: {=INDEX($A$162:$DE$162,0,MATCH(B13,$A$162:$DE$162,0)-1)} -> 7.625 | C14: =100-VLOOKUP(B14,'[1]Pricing '!$A$2506:$K$2531,11,FALSE) -> -5.2757203 | D14: =C14-$U$2 -> -5.1507203 | E14: {=INDEX($A$162:$DE$162,0,MATCH(E13,$A$162:$DE$162,0)-1)} -> 7.5 | F14: =100-VLOOKUP(E14,'[1]Pricing '!$A$2677:$K$2702,11,FALSE) -> -5.067206 | G14: =F14-$U$2 -> -4.942206 | H14: =H13-0.125 -> 7.5 | I14: =100-VLOOKUP(H14,'[1]Pricing '!$A$2648:$K$2673,11,FALSE) -> -4.149206 | J14: =I14-$U$2 -> -4.024206 | K14: =K13-0.125 -> 7.625 | L14: =100-VLOOKUP(K14,'[1]Pricing '!$A$2733:$K$2758,11,FALSE) -> -4.5407203 | M14: =L14-$U$2 -> -4.4157203 | N14: =N13-0.125 -> 7.125 | O14: =100-VLOOKUP(N14,'[1]Pricing '!$A$2534:$K$2558,11,FALSE) -> -3.7596219 | P14: =O14-$U$2 -> -3.6346219 | Q14: =Q13-0.125 -> 6.875 | R14: =100-VLOOKUP(Q14,'[1]Pricing '!$A$2761:$K$2785,11,FALSE) -> -4.0143409 | S14: =R14-$U$2 -> -3.8893409 | T14: =T13-0.125 -> 7.125 | U14: =100-VLOOKUP(T14,'[1]Pricing '!$A$3052:$K$3077,11,FALSE) -> -3.8466219 | V14: =U14-$U$2 -> -3.7216219 | W14: =W13-0.125 -> 7.25 | X14: =100-VLOOKUP(W14,'[1]Pricing '!$A$2788:$K$2812,11,FALSE) -> -4.0712603 | Y14: =X14-$U$2 -> -3.9462603 | Z14: =Z13-0.125 -> 7.625 | AA14: =100-VLOOKUP(Z14,'[1]Pricing '!$A$2561:$K$2586,11,FALSE) -> -3.6488846 | AB14: =AA14-$U$2 -> -3.5238846 | AC14: =AC13-0.125 -> 7.625 | AD14: =100-VLOOKUP(AC14,'[1]Pricing '!$A$2815:$K$2840,11,FALSE) -> -3.6488846 | AE14: =AD14-$U$2 -> -3.5238846 | AF14: =AF13-0.125 -> 7.375 | AG14: =100-VLOOKUP(AF14,'[1]Pricing '!$A$2589:$K$2614,11,FALSE) -> -3.6628836 | AH14: =AG14-$U$2 -> -3.5378836 | AI14: =AI13-0.125 -> 7.125 | AJ14: =100-VLOOKUP(AI14,'[1]Pricing '!$A$2871:$K$2896,11,FALSE) -> -3.6428149 | AK14: =AJ14-$U$2 -> -3.5178149
B15: {=INDEX($A$162:$DE$162,0,MATCH(B14,$A$162:$DE$162,0)-1)} -> 7.5 | C15: =100-VLOOKUP(B15,'[1]Pricing '!$A$2506:$K$2531,11,FALSE) -> -5.067206 | D15: =C15-$U$2 -> -4.942206 | E15: {=INDEX($A$162:$DE$162,0,MATCH(E14,$A$162:$DE$162,0)-1)} -> 7.375 | F15: =100-VLOOKUP(E15,'[1]Pricing '!$A$2677:$K$2702,11,FALSE) -> -4.7977794 | G15: =F15-$U$2 -> -4.6727794 | H15: =H14-0.125 -> 7.375 | I15: =100-VLOOKUP(H15,'[1]Pricing '!$A$2648:$K$2673,11,FALSE) -> -3.8957794 | J15: =I15-$U$2 -> -3.7707794 | K15: =K14-0.125 -> 7.5 | L15: =100-VLOOKUP(K15,'[1]Pricing '!$A$2733:$K$2758,11,FALSE) -> -4.149206 | M15: =L15-$U$2 -> -4.024206 | N15: =N14-0.125 -> 7 | O15: =100-VLOOKUP(N15,'[1]Pricing '!$A$2534:$K$2558,11,FALSE) -> -4.1100398 | P15: =O15-$U$2 -> -3.9850398 | Q15: =Q14-0.125 -> 6.75 | R15: =100-VLOOKUP(Q15,'[1]Pricing '!$A$2761:$K$2785,11,FALSE) -> -3.7662591 | S15: =R15-$U$2 -> -3.6412591 | T15: =T14-0.125 -> 7 | U15: =100-VLOOKUP(T15,'[1]Pricing '!$A$3052:$K$3077,11,FALSE) -> -4.1890398 | V15: =U15-$U$2 -> -4.0640398 | W15: =W14-0.125 -> 7.125 | X15: =100-VLOOKUP(W15,'[1]Pricing '!$A$2788:$K$2812,11,FALSE) -> -3.8466219 | Y15: =X15-$U$2 -> -3.7216219 | Z15: =Z14-0.125 -> 7.5 | AA15: =100-VLOOKUP(Z15,'[1]Pricing '!$A$2561:$K$2586,11,FALSE) -> -3.4762904 | AB15: =AA15-$U$2 -> -3.3512904 | AC15: =AC14-0.125 -> 7.5 | AD15: =100-VLOOKUP(AC15,'[1]Pricing '!$A$2815:$K$2840,11,FALSE) -> -3.4762904 | AE15: =AD15-$U$2 -> -3.3512904 | AF15: =AF14-0.125 -> 7.25 | AG15: =100-VLOOKUP(AF15,'[1]Pricing '!$A$2589:$K$2614,11,FALSE) -> -3.4672655 | AH15: =AG15-$U$2 -> -3.3422655 | AI15: =AI14-0.125 -> 7 | AJ15: =100-VLOOKUP(AI15,'[1]Pricing '!$A$2871:$K$2896,11,FALSE) -> -3.4413756 | AK15: =AJ15-$U$2 -> -3.3163756
B16: {=INDEX($A$162:$DE$162,0,MATCH(B15,$A$162:$DE$162,0)-1)} -> 7.375 | C16: =100-VLOOKUP(B16,'[1]Pricing '!$A$2506:$K$2531,11,FALSE) -> -4.7977794 | D16: =C16-$U$2 -> -4.6727794 | E16: {=INDEX($A$162:$DE$162,0,MATCH(E15,$A$162:$DE$162,0)-1)} -> 7.25 | F16: =100-VLOOKUP(E16,'[1]Pricing '!$A$2677:$K$2702,11,FALSE) -> -4.3192232 | G16: =F16-$U$2 -> -4.1942232 | H16: =H15-0.125 -> 7.25 | I16: =100-VLOOKUP(H16,'[1]Pricing '!$A$2648:$K$2673,11,FALSE) -> -3.6172232 | J16: =I16-$U$2 -> -3.4922232 | K16: =K15-0.125 -> 7.375 | L16: =100-VLOOKUP(K16,'[1]Pricing '!$A$2733:$K$2758,11,FALSE) -> -3.8957794 | M16: =L16-$U$2 -> -3.7707794 | N16: =N15-0.125 -> 6.875 | O16: =100-VLOOKUP(N16,'[1]Pricing '!$A$2534:$K$2558,11,FALSE) -> -3.8893409 | P16: =O16-$U$2 -> -3.7643409 | Q16: =Q15-0.125 -> 6.625 | R16: =100-VLOOKUP(Q16,'[1]Pricing '!$A$2761:$K$2785,11,FALSE) -> -3.5121048 | S16: =R16-$U$2 -> -3.3871048 | T16: =T15-0.125 -> 6.875 | U16: =100-VLOOKUP(T16,'[1]Pricing '!$A$3052:$K$3077,11,FALSE) -> -3.9713409 | V16: =U16-$U$2 -> -3.8463409 | W16: =W15-0.125 -> 7 | X16: =100-VLOOKUP(W16,'[1]Pricing '!$A$2788:$K$2812,11,FALSE) -> -4.1890398 | Y16: =X16-$U$2 -> -4.0640398 | Z16: =Z15-0.125 -> 7.375 | AA16: =100-VLOOKUP(Z16,'[1]Pricing '!$A$2561:$K$2586,11,FALSE) -> -3.1187664 | AB16: =AA16-$U$2 -> -2.9937664 | AC16: =AC15-0.125 -> 7.375 | AD16: =100-VLOOKUP(AC16,'[1]Pricing '!$A$2815:$K$2840,11,FALSE) -> -3.1187664 | AE16: =AD16-$U$2 -> -2.9937664 | AF16: =AF15-0.125 -> 7.125 | AG16: =100-VLOOKUP(AF16,'[1]Pricing '!$A$2589:$K$2614,11,FALSE) -> -3.7678149 | AH16: =AG16-$U$2 -> -3.6428149 | AI16: =AI15-0.125 -> 6.875 | AJ16: =100-VLOOKUP(AI16,'[1]Pricing '!$A$2871:$K$2896,11,FALSE) -> -2.8556408 | AK16: =AJ16-$U$2 -> -2.7306408
B17: {=INDEX($A$162:$DE$162,0,MATCH(B16,$A$162:$DE$162,0)-1)} -> 7.25 | C17: =100-VLOOKUP(B17,'[1]Pricing '!$A$2506:$K$2531,11,FALSE) -> -4.3192232 | D17: =C17-$U$2 -> -4.1942232 | E17: {=INDEX($A$162:$DE$162,0,MATCH(E16,$A$162:$DE$162,0)-1)} -> 7.125 | F17: =100-VLOOKUP(E17,'[1]Pricing '!$A$2677:$K$2702,11,FALSE) -> -4.1056343 | G17: =F17-$U$2 -> -3.9806343 | H17: =H16-0.125 -> 7.125 | I17: =100-VLOOKUP(H17,'[1]Pricing '!$A$2648:$K$2673,11,FALSE) -> -3.1156343 | J17: =I17-$U$2 -> -2.9906343 | K17: =K16-0.125 -> 7.25 | L17: =100-VLOOKUP(K17,'[1]Pricing '!$A$2733:$K$2758,11,FALSE) -> -3.6172232 | M17: =L17-$U$2 -> -3.4922232 | N17: =N16-0.125 -> 6.75 | O17: =100-VLOOKUP(N17,'[1]Pricing '!$A$2534:$K$2558,11,FALSE) -> -3.6412591 | P17: =O17-$U$2 -> -3.5162591 | Q17: =Q16-0.125 -> 6.5 | R17: =100-VLOOKUP(Q17,'[1]Pricing '!$A$2761:$K$2785,11,FALSE) -> -3.3369705 | S17: =R17-$U$2 -> -3.2119705 | T17: =T16-0.125 -> 6.75 | U17: =100-VLOOKUP(T17,'[1]Pricing '!$A$3052:$K$3077,11,FALSE) -> -3.7272591 | V17: =U17-$U$2 -> -3.6022591 | W17: =W16-0.125 -> 6.875 | X17: =100-VLOOKUP(W17,'[1]Pricing '!$A$2788:$K$2812,11,FALSE) -> -3.9713409 | Y17: =X17-$U$2 -> -3.8463409 | Z17: =Z16-0.125 -> 7.25 | AA17: =100-VLOOKUP(Z17,'[1]Pricing '!$A$2561:$K$2586,11,FALSE) -> -2.6460252 | AB17: =AA17-$U$2 -> -2.5210252 | AC17: =AC16-0.125 -> 7.25 | AD17: =100-VLOOKUP(AC17,'[1]Pricing '!$A$2815:$K$2840,11,FALSE) -> -2.6460252 | AE17: =AD17-$U$2 -> -2.5210252 | AF17: =AF16-0.125 -> 7 | AG17: =100-VLOOKUP(AF17,'[1]Pricing '!$A$2589:$K$2614,11,FALSE) -> -3.5663756 | AH17: =AG17-$U$2 -> -3.4413756 | AI17: =AI16-0.125 -> 6.75 | AJ17: =100-VLOOKUP(AI17,'[1]Pricing '!$A$2871:$K$2896,11,FALSE) -> -2.4802069 | AK17: =AJ17-$U$2 -> -2.3552069
B18: {=INDEX($A$162:$DE$162,0,MATCH(B17,$A$162:$DE$162,0)-1)} -> 7.125 | C18: =100-VLOOKUP(B18,'[1]Pricing '!$A$2506:$K$2531,11,FALSE) -> -4.1056343 | D18: =C18-$U$2 -> -3.9806343 | E18: {=INDEX($A$162:$DE$162,0,MATCH(E17,$A$162:$DE$162,0)-1)} -> 7 | F18: =100-VLOOKUP(E18,'[1]Pricing '!$A$2677:$K$2702,11,FALSE) -> -3.7784188 | G18: =F18-$U$2 -> -3.6534188 | H18: =H17-0.125 -> 7 | I18: =100-VLOOKUP(H18,'[1]Pricing '!$A$2648:$K$2673,11,FALSE) -> -2.7994188 | J18: =I18-$U$2 -> -2.6744188 | K18: =K17-0.125 -> 7.125 | L18: =100-VLOOKUP(K18,'[1]Pricing '!$A$2733:$K$2758,11,FALSE) -> -3.1156343 | M18: =L18-$U$2 -> -2.9906343 | N18: =N17-0.125 -> 6.625 | O18: =100-VLOOKUP(N18,'[1]Pricing '!$A$2534:$K$2558,11,FALSE) -> -3.3871048 | P18: =O18-$U$2 -> -3.2621048 | Q18: =Q17-0.125 -> 6.375 | R18: =100-VLOOKUP(Q18,'[1]Pricing '!$A$2761:$K$2785,11,FALSE) -> -3.0965438 | S18: =R18-$U$2 -> -2.9715438 | T18: =T17-0.125 -> 6.625 | U18: =100-VLOOKUP(T18,'[1]Pricing '!$A$3052:$K$3077,11,FALSE) -> -3.5101048 | V18: =U18-$U$2 -> -3.3851048 | W18: =W17-0.125 -> 6.75 | X18: =100-VLOOKUP(W18,'[1]Pricing '!$A$2788:$K$2812,11,FALSE) -> -3.7272591 | Y18: =X18-$U$2 -> -3.6022591 | Z18: =Z17-0.125 -> 7.125 | AA18: =100-VLOOKUP(Z18,'[1]Pricing '!$A$2561:$K$2586,11,FALSE) -> -2.890445 | AB18: =AA18-$U$2 -> -2.765445 | AC18: =AC17-0.125 -> 7.125 | AD18: =100-VLOOKUP(AC18,'[1]Pricing '!$A$2815:$K$2840,11,FALSE) -> -2.890445 | AE18: =AD18-$U$2 -> -2.765445 | AF18: =AF17-0.125 -> 6.875 | AG18: =100-VLOOKUP(AF18,'[1]Pricing '!$A$2589:$K$2614,11,FALSE) -> -2.9806408 | AH18: =AG18-$U$2 -> -2.8556408 | AI18: =AI17-0.125 -> 6.625 | AJ18: =100-VLOOKUP(AI18,'[1]Pricing '!$A$2871:$K$2896,11,FALSE) -> -2.3511124 | AK18: =AJ18-$U$2 -> -2.2261124
B19: {=INDEX($A$162:$DE$162,0,MATCH(B18,$A$162:$DE$162,0)-1)} -> 7 | C19: =100-VLOOKUP(B19,'[1]Pricing '!$A$2506:$K$2531,11,FALSE) -> -3.7784188 | D19: =C19-$U$2 -> -3.6534188 | E19: {=INDEX($A$162:$DE$162,0,MATCH(E18,$A$162:$DE$162,0)-1)} -> 6.875 | F19: =100-VLOOKUP(E19,'[1]Pricing '!$A$2677:$K$2702,11,FALSE) -> -3.3166371 | G19: =F19-$U$2 -> -3.1916371 | H19: =H18-0.125 -> 6.875 | I19: =100-VLOOKUP(H19,'[1]Pricing '!$A$2648:$K$2673,11,FALSE) -> -2.5436371 | J19: =I19-$U$2 -> -2.4186371 | K19: =K18-0.125 -> 7 | L19: =100-VLOOKUP(K19,'[1]Pricing '!$A$2733:$K$2758,11,FALSE) -> -2.7994188 | M19: =L19-$U$2 -> -2.6744188 | N19: =N18-0.125 -> 6.5 | O19: =100-VLOOKUP(N19,'[1]Pricing '!$A$2534:$K$2558,11,FALSE) -> -3.2119705 | P19: =O19-$U$2 -> -3.0869705 | Q19: =Q18-0.125 -> 6.25 | R19: =100-VLOOKUP(Q19,'[1]Pricing '!$A$2761:$K$2785,11,FALSE) -> -2.8050742 | S19: =R19-$U$2 -> -2.6800742 | T19: =T18-0.125 -> 6.5 | U19: =100-VLOOKUP(T19,'[1]Pricing '!$A$3052:$K$3077,11,FALSE) -> -3.2889705 | V19: =U19-$U$2 -> -3.1639705 | W19: =W18-0.125 -> 6.625 | X19: =100-VLOOKUP(W19,'[1]Pricing '!$A$2788:$K$2812,11,FALSE) -> -3.5101048 | Y19: =X19-$U$2 -> -3.3851048 | Z19: =Z18-0.125 -> 7 | AA19: =100-VLOOKUP(Z19,'[1]Pricing '!$A$2561:$K$2586,11,FALSE) -> -2.5778289 | AB19: =AA19-$U$2 -> -2.4528289 | AC19: =AC18-0.125 -> 7 | AD19: =100-VLOOKUP(AC19,'[1]Pricing '!$A$2815:$K$2840,11,FALSE) -> -2.5778289 | AE19: =AD19-$U$2 -> -2.4528289 | AF19: =AF18-0.125 -> 6.75 | AG19: =100-VLOOKUP(AF19,'[1]Pricing '!$A$2589:$K$2614,11,FALSE) -> -2.6052069 | AH19: =AG19-$U$2 -> -2.4802069 | AI19: =AI18-0.125 -> 6.5 | AJ19: =100-VLOOKUP(AI19,'[1]Pricing '!$A$2871:$K$2896,11,FALSE) -> -2.1321443 | AK19: =AJ19-$U$2 -> -2.0071443
B20: {=INDEX($A$162:$DE$162,0,MATCH(B19,$A$162:$DE$162,0)-1)} -> 6.875 | C20: =100-VLOOKUP(B20,'[1]Pricing '!$A$2506:$K$2531,11,FALSE) -> -3.3166371 | D20: =C20-$U$2 -> -3.1916371 | E20: {=INDEX($A$162:$DE$162,0,MATCH(E19,$A$162:$DE$162,0)-1)} -> 6.75 | F20: =100-VLOOKUP(E20,'[1]Pricing '!$A$2677:$K$2702,11,FALSE) -> -2.7760354 | G20: =F20-$U$2 -> -2.6510354 | H20: =H19-0.125 -> 6.75 | I20: =100-VLOOKUP(H20,'[1]Pricing '!$A$2648:$K$2673,11,FALSE) -> -2.2440354 | J20: =I20-$U$2 -> -2.1190354 | K20: =K19-0.125 -> 6.875 | L20: =100-VLOOKUP(K20,'[1]Pricing '!$A$2733:$K$2758,11,FALSE) -> -2.5436371 | M20: =L20-$U$2 -> -2.4186371 | N20: =N19-0.125 -> 6.375 | O20: =100-VLOOKUP(N20,'[1]Pricing '!$A$2534:$K$2558,11,FALSE) -> -2.9715438 | P20: =O20-$U$2 -> -2.8465438 | Q20: =Q19-0.125 -> 6.125 | R20: =100-VLOOKUP(Q20,'[1]Pricing '!$A$2761:$K$2785,11,FALSE) -> -2.4699316 | S20: =R20-$U$2 -> -2.3449316 | T20: =T19-0.125 -> 6.375 | U20: =100-VLOOKUP(T20,'[1]Pricing '!$A$3052:$K$3077,11,FALSE) -> -3.0515438 | V20: =U20-$U$2 -> -2.9265438 | W20: =W19-0.125 -> 6.5 | X20: =100-VLOOKUP(W20,'[1]Pricing '!$A$2788:$K$2812,11,FALSE) -> -3.2889705 | Y20: =X20-$U$2 -> -3.1639705 | Z20: =Z19-0.125 -> 6.875 | AA20: =100-VLOOKUP(Z20,'[1]Pricing '!$A$2561:$K$2586,11,FALSE) -> -2.3787035 | AB20: =AA20-$U$2 -> -2.2537035 | AC20: =AC19-0.125 -> 6.875 | AD20: =100-VLOOKUP(AC20,'[1]Pricing '!$A$2815:$K$2840,11,FALSE) -> -2.3787035 | AE20: =AD20-$U$2 -> -2.2537035 | AF20: =AF19-0.125 -> 6.625 | AG20: =100-VLOOKUP(AF20,'[1]Pricing '!$A$2589:$K$2614,11,FALSE) -> -2.4761124 | AH20: =AG20-$U$2 -> -2.3511124 | AI20: =AI19-0.125 -> 6.375 | AJ20: =100-VLOOKUP(AI20,'[1]Pricing '!$A$2871:$K$2896,11,FALSE) -> -1.8776478 | AK20: =AJ20-$U$2 -> -1.7526478
B21: {=INDEX($A$162:$DE$162,0,MATCH(B20,$A$162:$DE$162,0)-1)} -> 6.75 | C21: =100-VLOOKUP(B21,'[1]Pricing '!$A$2506:$K$2531,11,FALSE) -> -2.7760354 | D21: =C21-$U$2 -> -2.6510354 | E21: {=INDEX($A$162:$DE$162,0,MATCH(E20,$A$162:$DE$162,0)-1)} -> 6.625 | F21: =100-VLOOKUP(E21,'[1]Pricing '!$A$2677:$K$2702,11,FALSE) -> -2.6001419 | G21: =F21-$U$2 -> -2.4751419 | H21: =H20-0.125 -> 6.625 | I21: =100-VLOOKUP(H21,'[1]Pricing '!$A$2648:$K$2673,11,FALSE) -> -2.1781419 | J21: =I21-$U$2 -> -2.0531419 | K21: =K20-0.125 -> 6.75 | L21: =100-VLOOKUP(K21,'[1]Pricing '!$A$2733:$K$2758,11,FALSE) -> -2.2440354 | M21: =L21-$U$2 -> -2.1190354 | N21: =N20-0.125 -> 6.25 | O21: =100-VLOOKUP(N21,'[1]Pricing '!$A$2534:$K$2558,11,FALSE) -> -2.6800742 | P21: =O21-$U$2 -> -2.5550742 | Q21: =Q20-0.125 -> 6 | R21: =100-VLOOKUP(Q21,'[1]Pricing '!$A$2761:$K$2785,11,FALSE) -> -2.2045454 | S21: =R21-$U$2 -> -2.0795454 | T21: =T20-0.125 -> 6.25 | U21: =100-VLOOKUP(T21,'[1]Pricing '!$A$3052:$K$3077,11,FALSE) -> -2.7630742 | V21: =U21-$U$2 -> -2.6380742 | W21: =W20-0.125 -> 6.375 | X21: =100-VLOOKUP(W21,'[1]Pricing '!$A$2788:$K$2812,11,FALSE) -> -3.0515438 | Y21: =X21-$U$2 -> -2.9265438 | Z21: =Z20-0.125 -> 6.75 | AA21: =100-VLOOKUP(Z21,'[1]Pricing '!$A$2561:$K$2586,11,FALSE) -> -1.8256148 | AB21: =AA21-$U$2 -> -1.7006148 | AC21: =AC20-0.125 -> 6.75 | AD21: =100-VLOOKUP(AC21,'[1]Pricing '!$A$2815:$K$2840,11,FALSE) -> -1.8256148 | AE21: =AD21-$U$2 -> -1.7006148 | AF21: =AF20-0.125 -> 6.5 | AG21: =100-VLOOKUP(AF21,'[1]Pricing '!$A$2589:$K$2614,11,FALSE) -> -2.2571443 | AH21: =AG21-$U$2 -> -2.1321443 | AI21: =AI20-0.125 -> 6.25 | AJ21: =100-VLOOKUP(AI21,'[1]Pricing '!$A$2871:$K$2896,11,FALSE) -> -1.5080034 | AK21: =AJ21-$U$2 -> -1.3830034
B22: {=INDEX($A$162:$DE$162,0,MATCH(B21,$A$162:$DE$162,0)-1)} -> 6.625 | C22: =100-VLOOKUP(B22,'[1]Pricing '!$A$2506:$K$2531,11,FALSE) -> -2.6001419 | D22: =C22-$U$2 -> -2.4751419 | E22: {=INDEX($A$162:$DE$162,0,MATCH(E21,$A$162:$DE$162,0)-1)} -> 6.5 | F22: =100-VLOOKUP(E22,'[1]Pricing '!$A$2677:$K$2702,11,FALSE) -> -2.228558 | G22: =F22-$U$2 -> -2.103558 | H22: =H21-0.125 -> 6.5 | I22: =100-VLOOKUP(H22,'[1]Pricing '!$A$2648:$K$2673,11,FALSE) -> -1.854558 | J22: =I22-$U$2 -> -1.729558 | K22: =K21-0.125 -> 6.625 | L22: =100-VLOOKUP(K22,'[1]Pricing '!$A$2733:$K$2758,11,FALSE) -> -2.1781419 | M22: =L22-$U$2 -> -2.0531419 | N22: =N21-0.125 -> 6.125 | O22: =100-VLOOKUP(N22,'[1]Pricing '!$A$2534:$K$2558,11,FALSE) -> -2.3449316 | P22: =O22-$U$2 -> -2.2199316 | Q22: =Q21-0.125 -> 5.875 | R22: =100-VLOOKUP(Q22,'[1]Pricing '!$A$2761:$K$2785,11,FALSE) -> -1.9324186 | S22: =R22-$U$2 -> -1.8074186 | T22: =T21-0.125 -> 6.125 | U22: =100-VLOOKUP(T22,'[1]Pricing '!$A$3052:$K$3077,11,FALSE) -> -2.4469316 | V22: =U22-$U$2 -> -2.3219316 | W22: =W21-0.125 -> 6.25 | X22: =100-VLOOKUP(W22,'[1]Pricing '!$A$2788:$K$2812,11,FALSE) -> -2.7630742 | Y22: =X22-$U$2 -> -2.6380742 | Z22: =Z21-0.125 -> 6.625 | AA22: =100-VLOOKUP(Z22,'[1]Pricing '!$A$2561:$K$2586,11,FALSE) -> -1.8382554 | AB22: =AA22-$U$2 -> -1.7132554 | AC22: =AC21-0.125 -> 6.625 | AD22: =100-VLOOKUP(AC22,'[1]Pricing '!$A$2815:$K$2840,11,FALSE) -> -1.8382554 | AE22: =AD22-$U$2 -> -1.7132554 | AF22: =AF21-0.125 -> 6.375 | AG22: =100-VLOOKUP(AF22,'[1]Pricing '!$A$2589:$K$2614,11,FALSE) -> -2.0026478 | AH22: =AG22-$U$2 -> -1.8776478 | AI22: =AI21-0.125 -> 6.125 | AJ22: =100-VLOOKUP(AI22,'[1]Pricing '!$A$2871:$K$2896,11,FALSE) -> -1.2463059 | AK22: =AJ22-$U$2 -> -1.1213059
B23: {=INDEX($A$162:$DE$162,0,MATCH(B22,$A$162:$DE$162,0)-1)} -> 6.5 | C23: =100-VLOOKUP(B23,'[1]Pricing '!$A$2506:$K$2531,11,FALSE) -> -2.228558 | D23: =C23-$U$2 -> -2.103558 | E23: {=INDEX($A$162:$DE$162,0,MATCH(E22,$A$162:$DE$162,0)-1)} -> 6.375 | F23: =100-VLOOKUP(E23,'[1]Pricing '!$A$2677:$K$2702,11,FALSE) -> -1.8965731 | G23: =F23-$U$2 -> -1.7715731 | H23: =H22-0.125 -> 6.375 | I23: =100-VLOOKUP(H23,'[1]Pricing '!$A$2648:$K$2673,11,FALSE) -> -1.4895731 | J23: =I23-$U$2 -> -1.3645731 | K23: =K22-0.125 -> 6.5 | L23: =100-VLOOKUP(K23,'[1]Pricing '!$A$2733:$K$2758,11,FALSE) -> -1.854558 | M23: =L23-$U$2 -> -1.729558 | N23: =N22-0.125 -> 6 | O23: =100-VLOOKUP(N23,'[1]Pricing '!$A$2534:$K$2558,11,FALSE) -> -2.0795454 | P23: =O23-$U$2 -> -1.9545454 | Q23: =Q22-0.125 -> 5.75 | R23: =100-VLOOKUP(Q23,'[1]Pricing '!$A$2761:$K$2785,11,FALSE) -> -1.5290574 | S23: =R23-$U$2 -> -1.4040574 | T23: =T22-0.125 -> 6 | U23: =100-VLOOKUP(T23,'[1]Pricing '!$A$3052:$K$3077,11,FALSE) -> -2.1825454 | V23: =U23-$U$2 -> -2.0575454 | W23: =W22-0.125 -> 6.125 | X23: =100-VLOOKUP(W23,'[1]Pricing '!$A$2788:$K$2812,11,FALSE) -> -2.4469316 | Y23: =X23-$U$2 -> -2.3219316 | Z23: =Z22-0.125 -> 6.5 | AA23: =100-VLOOKUP(Z23,'[1]Pricing '!$A$2561:$K$2586,11,FALSE) -> -1.5711154 | AB23: =AA23-$U$2 -> -1.4461154 | AC23: =AC22-0.125 -> 6.5 | AD23: =100-VLOOKUP(AC23,'[1]Pricing '!$A$2815:$K$2840,11,FALSE) -> -1.5711154 | AE23: =AD23-$U$2 -> -1.4461154 | AF23: =AF22-0.125 -> 6.25 | AG23: =100-VLOOKUP(AF23,'[1]Pricing '!$A$2589:$K$2614,11,FALSE) -> -1.6330034 | AH23: =AG23-$U$2 -> -1.5080034 | AI23: =AI22-0.125 -> 6 | AJ23: =100-VLOOKUP(AI23,'[1]Pricing '!$A$2871:$K$2896,11,FALSE) -> -0.92586102 | AK23: =AJ23-$U$2 -> -0.80086102
B24: {=INDEX($A$162:$DE$162,0,MATCH(B23,$A$162:$DE$162,0)-1)} -> 6.375 | C24: =100-VLOOKUP(B24,'[1]Pricing '!$A$2506:$K$2531,11,FALSE) -> -1.8965731 | D24: =C24-$U$2 -> -1.7715731 | E24: {=INDEX($A$162:$DE$162,0,MATCH(E23,$A$162:$DE$162,0)-1)} -> 6.25 | F24: =100-VLOOKUP(E24,'[1]Pricing '!$A$2677:$K$2702,11,FALSE) -> -1.4479342 | G24: =F24-$U$2 -> -1.3229342 | H24: =H23-0.125 -> 6.25 | I24: =100-VLOOKUP(H24,'[1]Pricing '!$A$2648:$K$2673,11,FALSE) -> -1.0939342 | J24: =I24-$U$2 -> -0.96893415 | K24: =K23-0.125 -> 6.375 | L24: =100-VLOOKUP(K24,'[1]Pricing '!$A$2733:$K$2758,11,FALSE) -> -1.4895731 | M24: =L24-$U$2 -> -1.3645731 | N24: =N23-0.125 -> 5.875 | O24: =100-VLOOKUP(N24,'[1]Pricing '!$A$2534:$K$2558,11,FALSE) -> -1.8074186 | P24: =O24-$U$2 -> -1.6824186 | Q24: =Q23-0.125 -> 5.625 | R24: =100-VLOOKUP(Q24,'[1]Pricing '!$A$2761:$K$2785,11,FALSE) -> -1.1915764 | S24: =R24-$U$2 -> -1.0665764 | T24: =T23-0.125 -> 5.875 | U24: =100-VLOOKUP(T24,'[1]Pricing '!$A$3052:$K$3077,11,FALSE) -> -1.9144186 | V24: =U24-$U$2 -> -1.7894186 | W24: =W23-0.125 -> 6 | X24: =100-VLOOKUP(W24,'[1]Pricing '!$A$2788:$K$2812,11,FALSE) -> -2.1825454 | Y24: =X24-$U$2 -> -2.0575454 | Z24: =Z23-0.125 -> 6.375 | AA24: =100-VLOOKUP(Z24,'[1]Pricing '!$A$2561:$K$2586,11,FALSE) -> -1.3176457 | AB24: =AA24-$U$2 -> -1.1926457 | AC24: =AC23-0.125 -> 6.375 | AD24: =100-VLOOKUP(AC24,'[1]Pricing '!$A$2815:$K$2840,11,FALSE) -> -1.3176457 | AE24: =AD24-$U$2 -> -1.1926457 | AF24: =AF23-0.125 -> 6.125 | AG24: =100-VLOOKUP(AF24,'[1]Pricing '!$A$2589:$K$2614,11,FALSE) -> -1.3713059 | AH24: =AG24-$U$2 -> -1.2463059 | AI24: =AI23-0.125 -> 5.875 | AJ24: =100-VLOOKUP(AI24,'[1]Pricing '!$A$2871:$K$2896,11,FALSE) -> -0.63290801 | AK24: =AJ24-$U$2 -> -0.50790801
B25: {=INDEX($A$162:$DE$162,0,MATCH(B24,$A$162:$DE$162,0)-1)} -> 6.25 | C25: =100-VLOOKUP(B25,'[1]Pricing '!$A$2506:$K$2531,11,FALSE) -> -1.4479342 | D25: =C25-$U$2 -> -1.3229342 | E25: {=INDEX($A$162:$DE$162,0,MATCH(E24,$A$162:$DE$162,0)-1)} -> 6.125 | F25: =100-VLOOKUP(E25,'[1]Pricing '!$A$2677:$K$2702,11,FALSE) -> -1.0084619 | G25: =F25-$U$2 -> -0.88346194 | H25: =H24-0.125 -> 6.125 | I25: =100-VLOOKUP(H25,'[1]Pricing '!$A$2648:$K$2673,11,FALSE) -> -0.94046194 | J25: =I25-$U$2 -> -0.81546194 | K25: =K24-0.125 -> 6.25 | L25: =100-VLOOKUP(K25,'[1]Pricing '!$A$2733:$K$2758,11,FALSE) -> -1.0939342 | M25: =L25-$U$2 -> -0.96893415 | N25: =N24-0.125 -> 5.75 | O25: =100-VLOOKUP(N25,'[1]Pricing '!$A$2534:$K$2558,11,FALSE) -> -1.4040574 | P25: =O25-$U$2 -> -1.2790574 | Q25: =Q24-0.125 -> 5.5 | R25: =100-VLOOKUP(Q25,'[1]Pricing '!$A$2761:$K$2785,11,FALSE) -> -0.86875712 | S25: =R25-$U$2 -> -0.74375712 | T25: =T24-0.125 -> 5.75 | U25: =100-VLOOKUP(T25,'[1]Pricing '!$A$3052:$K$3077,11,FALSE) -> -1.5130574 | V25: =U25-$U$2 -> -1.3880574 | W25: =W24-0.125 -> 5.875 | X25: =100-VLOOKUP(W25,'[1]Pricing '!$A$2788:$K$2812,11,FALSE) -> -1.9144186 | Y25: =X25-$U$2 -> -1.7894186 | Z25: =Z24-0.125 -> 6.25 | AA25: =100-VLOOKUP(Z25,'[1]Pricing '!$A$2561:$K$2586,11,FALSE) -> -0.9273983 | AB25: =AA25-$U$2 -> -0.8023983 | AC25: =AC24-0.125 -> 6.25 | AD25: =100-VLOOKUP(AC25,'[1]Pricing '!$A$2815:$K$2840,11,FALSE) -> -0.9273983 | AE25: =AD25-$U$2 -> -0.8023983 | AF25: =AF24-0.125 -> 6 | AG25: =100-VLOOKUP(AF25,'[1]Pricing '!$A$2589:$K$2614,11,FALSE) -> -1.050861 | AH25: =AG25-$U$2 -> -0.92586102 | AI25: =AI24-0.125 -> 5.75 | AJ25: =100-VLOOKUP(AI25,'[1]Pricing '!$A$2871:$K$2896,11,FALSE) -> -0.15871406 | AK25: =AJ25-$U$2 -> -0.033714064
... B37: {=INDEX($A$162:$DE$162,0,MATCH(B36,$A$162:$DE$162,0)-1)} -> 4.875 | C37: =100-VLOOKUP(B37,'[1]Pricing '!$A$2506:$K$2531,11,FALSE) -> 4.6669012 | D37: =C37-$U$2 -> 4.7919012 | E37: {=INDEX($A$162:$DE$162,0,MATCH(E36,$A$162:$DE$162,0)-1)} -> 4.75 | F37: =100-VLOOKUP(E37,'[1]Pricing '!$A$2677:$K$2702,11,FALSE) -> 5.5315774 | G37: =F37-$U$2 -> 5.6565774 | H37: =H36-0.125 -> 4.625 | I37: =100-VLOOKUP(H37,'[1]Pricing '!$A$2648:$K$2673,11,FALSE) -> 5.2745101 | J37: =I37-$U$2 -> 5.3995101 | K37: =K36-0.125 -> 4.75 | L37: =100-VLOOKUP(K37,'[1]Pricing '!$A$2733:$K$2758,11,FALSE) -> 4.4765774 | M37: =L37-$U$2 -> 4.6015774 | N37: =N36-0.125 -> 4.25 | O37: =100-VLOOKUP(N37,'[1]Pricing '!$A$2534:$K$2558,11,FALSE) -> 3.1147495 | P37: =O37-$U$2 -> 3.2397495 | Q37: =Q36-0.125 -> 4 | R37: =100-VLOOKUP(Q37,'[1]Pricing '!$A$2761:$K$2785,11,FALSE) -> 2.5834823 | S37: =R37-$U$2 -> 2.7084823 | T37: =T36-0.125 -> 4.25 | U37: =100-VLOOKUP(T37,'[1]Pricing '!$A$3052:$K$3077,11,FALSE) -> 2.8177495 | V37: =U37-$U$2 -> 2.9427495 | W37: =W36-0.125 -> 4.375 | X37: =100-VLOOKUP(W37,'[1]Pricing '!$A$2788:$K$2812,11,FALSE) -> 2.2743055 | Y37: =X37-$U$2 -> 2.3993055 | Z37: =Z36-0.125 -> 4.75 | AA37: =100-VLOOKUP(Z37,'[1]Pricing '!$A$2561:$K$2586,11,FALSE) -> 6.5086638 | AB37: =AA37-$U$2 -> 6.6336638 | AC37: =AC36-0.125 -> 4.75 | AD37: =100-VLOOKUP(AC37,'[1]Pricing '!$A$2815:$K$2840,11,FALSE) -> 6.5086638 | AE37: =AD37-$U$2 -> 6.6336638 | AF37: =AF36-0.125 -> 4.5 | AG37: =100-VLOOKUP(AF37,'[1]Pricing '!$A$2589:$K$2614,11,FALSE) -> 3.7635388 | AH37: =AG37-$U$2 -> 3.8885388 | AI37: =AI36-0.125 -> 4.25 | AJ37: =100-VLOOKUP(AI37,'[1]Pricing '!$A$2871:$K$2896,11,FALSE) -> 4.8893076 | AK37: =AJ37-$U$2 -> 5.0143076
B39: FIXED PROGRAMS (FANNIE MAE & FREDDIE MAC)
B40: CONFORMING FIXED | Z40: HIGH BALANCE FIXED
B41: (FCF30) 30 YEAR | E41: (FM30) / (FM30 RP) 30 YEAR | H41: (FCF20) 20 YEAR | K41: (FM20) 20 YEAR | N41: (FCF15) 15 YEAR | Q41: (FM15) / (FM15 RP) 15 YEAR | T41: (FCF10) 10 YEAR | W41: (FM10) 10 YEAR | Z41: (FCF30HB) 30 YEAR | AC41: (FMSC30) 30 YEAR | AF41: ( FCF15HB) 15 YEAR | AI41: (FMSC15) 15 YEAR
B42: RATE | C42: 30 Days | D42: 45 days | E42: RATE | F42: 30 Days | G42: 45 days | H42: RATE | I42: 30 Days | J42: 45 days | K42: RATE | L42: 30 Days | M42: 45 days | N42: RATE | O42: 30 Days | P42: 45 days | Q42: RATE | R42: 30 Days | S42: 45 days | T42: RATE | U42: 30 Days | V42: 45 days | W42: RATE | X42: 30 Days | Y42: 45 days | Z42: RATE | AA42: 30 Days | AB42: 45 days | AC42: RATE | AD42: 30 Days | AE42: 45 days | AF42: RATE | AG42: 30 Days | AH42: 45 days | AI42: RATE | AJ42: 30 Days | AK42: 45 days
B43: =LARGE('[1]Pricing '!$A$6:$A$30,1) -> 7.625 | C43: =100-VLOOKUP(B43,'[1]Pricing '!$A$6:$K$30,11,FALSE) -> -4.2757203 | D43: =C43-$U$2 -> -4.1507203 | E43: =LARGE('[1]Pricing '!$A$566:$A$590,1) -> 7.875 | F43: =100-VLOOKUP(E43,'[1]Pricing '!$A$566:$K$590,11,FALSE) -> -4.500331 | G43: =F43-$U$2 -> -4.375331 | H43: =LARGE('[1]Pricing '!$A$59:$A$83,1) -> 7.5 | I43: =100-VLOOKUP(H43,'[1]Pricing '!$A$59:$K$83,11,FALSE) -> -3.274206 | J43: =I43-$U$2 -> -3.149206 | K43: =LARGE('[1]Pricing '!$A$593:$A$617,1) -> 7.5 | L43: =100-VLOOKUP(K43,'[1]Pricing '!$A$593:$K$617,11,FALSE) -> -3.274206 | M43: =L43-$U$2 -> -3.149206 | N43: =LARGE('[1]Pricing '!$A$86:$A$110,1) -> 7 | O43: =100-VLOOKUP(N43,'[1]Pricing '!$A$86:$K$110,11,FALSE) -> -3.2350398 | P43: =O43-$U$2 -> -3.1100398 | Q43: =LARGE('[1]Pricing '!$A$620:$A$644,1) -> 7 | R43: =100-VLOOKUP(Q43,'[1]Pricing '!$A$620:$K$644,11,FALSE) -> -3.2350398 | S43: =R43-$U$2 -> -3.1100398 | T43: =LARGE('[1]Pricing '!$A$113:$A$137,1) -> 7.125 | U43: =100-VLOOKUP(T43,'[1]Pricing '!$A$113:$K$137,11,FALSE) -> -2.8466219 | V43: =U43-$U$2 -> -2.7216219 | W43: =LARGE('[1]Pricing '!$A$647:$A$671,1) -> 7.375 | X43: =100-VLOOKUP(W43,'[1]Pricing '!$A$647:$K$671,11,FALSE) -> -3.2670013 | Y43: =X43-$U$2 -> -3.1420013 | Z43: =LARGE('[1]Pricing '!$A$167:$A$191,1) -> 7.75 | AA43: =100-VLOOKUP(Z43,'[1]Pricing '!$A$167:$K$191,11,FALSE) -> -2.3317092 | AB43: =AA43-$U$2 -> -2.2067092 | AC43: =LARGE('[1]Pricing '!$A$674:$A$698,1) -> 7.875 | AD43: =100-VLOOKUP(AC43,'[1]Pricing '!$A$674:$K$698,11,FALSE) -> -2.7171899 | AE43: =AD43-$U$2 -> -2.5921899 | AF43: =LARGE('[1]Pricing '!$A$194:$A$218,1) -> 7.5 | AG43: =100-VLOOKUP(AF43,'[1]Pricing '!$A$194:$K$218,11,FALSE) -> -2.9687478 | AH43: =AG43-$U$2 -> -2.8437478 | AI43: =LARGE('[1]Pricing '!$A$701:$A$725,1) -> 7.5 | AJ43: =100-VLOOKUP(AI43,'[1]Pricing '!$A$701:$K$725,11,FALSE) -> -2.9687478 | AK43: =AJ43-$U$2 -> -2.8437478
B44: {=INDEX($A$162:$DE$162,0,MATCH(B43,$A$162:$DE$162,0)-1)} -> 7.5 | C44: =100-VLOOKUP(B44,'[1]Pricing '!$A$6:$K$30,11,FALSE) -> -4.067206 | D44: =C44-$U$2 -> -3.942206 | E44: {=INDEX($A$162:$DE$162,0,MATCH(E43,$A$162:$DE$162,0)-1)} -> 7.75 | F44: =100-VLOOKUP(E44,'[1]Pricing '!$A$566:$K$590,11,FALSE) -> -4.2391265 | G44: =F44-$U$2 -> -4.1141265 | H44: =H43-0.125 -> 7.375 | I44: =100-VLOOKUP(H44,'[1]Pricing '!$A$59:$K$83,11,FALSE) -> -3.0207794 | J44: =I44-$U$2 -> -2.8957794 | K44: =K43-0.125 -> 7.375 | L44: =100-VLOOKUP(K44,'[1]Pricing '!$A$593:$K$617,11,FALSE) -> -3.0207794 | M44: =L44-$U$2 -> -2.8957794 | N44: =N43-0.125 -> 6.875 | O44: =100-VLOOKUP(N44,'[1]Pricing '!$A$86:$K$110,11,FALSE) -> -3.0143409 | P44: =O44-$U$2 -> -2.8893409 | Q44: =Q43-0.125 -> 6.875 | R44: =100-VLOOKUP(Q44,'[1]Pricing '!$A$620:$K$644,11,FALSE) -> -3.0143409 | S44: =R44-$U$2 -> -2.8893409 | T44: =T43-0.125 -> 7 | U44: =100-VLOOKUP(T44,'[1]Pricing '!$A$113:$K$137,11,FALSE) -> -3.1890398 | V44: =U44-$U$2 -> -3.0640398 | W44: =W43-0.125 -> 7.25 | X44: =100-VLOOKUP(W44,'[1]Pricing '!$A$647:$K$671,11,FALSE) -> -3.0712603 | Y44: =X44-$U$2 -> -2.9462603 | Z44: =Z43-0.125 -> 7.625 | AA44: =100-VLOOKUP(Z44,'[1]Pricing '!$A$167:$K$191,11,FALSE) -> -2.7738846 | AB44: =AA44-$U$2 -> -2.6488846 | AC44: =AC43-0.125 -> 7.75 | AD44: =100-VLOOKUP(AC44,'[1]Pricing '!$A$674:$K$698,11,FALSE) -> -2.3317092 | AE44: =AD44-$U$2 -> -2.2067092 | AF44: =AF43-0.125 -> 7.375 | AG44: =100-VLOOKUP(AF44,'[1]Pricing '!$A$194:$K$218,11,FALSE) -> -2.7878836 | AH44: =AG44-$U$2 -> -2.6628836 | AI44: =AI43-0.125 -> 7.375 | AJ44: =100-VLOOKUP(AI44,'[1]Pricing '!$A$701:$K$725,11,FALSE) -> -2.7878836 | AK44: =AJ44-$U$2 -> -2.6628836
B45: {=INDEX($A$162:$DE$162,0,MATCH(B44,$A$162:$DE$162,0)-1)} -> 7.375 | C45: =100-VLOOKUP(B45,'[1]Pricing '!$A$6:$K$30,11,FALSE) -> -3.7977794 | D45: =C45-$U$2 -> -3.6727794 | E45: {=INDEX($A$162:$DE$162,0,MATCH(E44,$A$162:$DE$162,0)-1)} -> 7.625 | F45: =100-VLOOKUP(E45,'[1]Pricing '!$A$566:$K$590,11,FALSE) -> -4.2757203 | G45: =F45-$U$2 -> -4.1507203 | H45: =H44-0.125 -> 7.25 | I45: =100-VLOOKUP(H45,'[1]Pricing '!$A$59:$K$83,11,FALSE) -> -2.7422232 | J45: =I45-$U$2 -> -2.6172232 | K45: =K44-0.125 -> 7.25 | L45: =100-VLOOKUP(K45,'[1]Pricing '!$A$593:$K$617,11,FALSE) -> -2.7422232 | M45: =L45-$U$2 -> -2.6172232 | N45: =N44-0.125 -> 6.75 | O45: =100-VLOOKUP(N45,'[1]Pricing '!$A$86:$K$110,11,FALSE) -> -2.7662591 | P45: =O45-$U$2 -> -2.6412591 | Q45: =Q44-0.125 -> 6.75 | R45: =100-VLOOKUP(Q45,'[1]Pricing '!$A$620:$K$644,11,FALSE) -> -2.7662591 | S45: =R45-$U$2 -> -2.6412591 | T45: =T44-0.125 -> 6.875 | U45: =100-VLOOKUP(T45,'[1]Pricing '!$A$113:$K$137,11,FALSE) -> -2.9713409 | V45: =U45-$U$2 -> -2.8463409 | W45: =W44-0.125 -> 7.125 | X45: =100-VLOOKUP(W45,'[1]Pricing '!$A$647:$K$671,11,FALSE) -> -2.8466219 | Y45: =X45-$U$2 -> -2.7216219 | Z45: =Z44-0.125 -> 7.5 | AA45: =100-VLOOKUP(Z45,'[1]Pricing '!$A$167:$K$191,11,FALSE) -> -2.6012904 | AB45: =AA45-$U$2 -> -2.4762904 | AC45: =AC44-0.125 -> 7.625 | AD45: =100-VLOOKUP(AC45,'[1]Pricing '!$A$674:$K$698,11,FALSE) -> -2.7738846 | AE45: =AD45-$U$2 -> -2.6488846 | AF45: =AF44-0.125 -> 7.25 | AG45: =100-VLOOKUP(AF45,'[1]Pricing '!$A$194:$K$218,11,FALSE) -> -2.5922655 | AH45: =AG45-$U$2 -> -2.4672655 | AI45: =AI44-0.125 -> 7.25 | AJ45: =100-VLOOKUP(AI45,'[1]Pricing '!$A$701:$K$725,11,FALSE) -> -2.5922655 | AK45: =AJ45-$U$2 -> -2.4672655
B46: {=INDEX($A$162:$DE$162,0,MATCH(B45,$A$162:$DE$162,0)-1)} -> 7.25 | C46: =100-VLOOKUP(B46,'[1]Pricing '!$A$6:$K$30,11,FALSE) -> -3.3192232 | D46: =C46-$U$2 -> -3.1942232 | E46: {=INDEX($A$162:$DE$162,0,MATCH(E45,$A$162:$DE$162,0)-1)} -> 7.5 | F46: =100-VLOOKUP(E46,'[1]Pricing '!$A$566:$K$590,11,FALSE) -> -4.067206 | G46: =F46-$U$2 -> -3.942206 | H46: =H45-0.125 -> 7.125 | I46: =100-VLOOKUP(H46,'[1]Pricing '!$A$59:$K$83,11,FALSE) -> -2.2406343 | J46: =I46-$U$2 -> -2.1156343 | K46: =K45-0.125 -> 7.125 | L46: =100-VLOOKUP(K46,'[1]Pricing '!$A$593:$K$617,11,FALSE) -> -2.2406343 | M46: =L46-$U$2 -> -2.1156343 | N46: =N45-0.125 -> 6.625 | O46: =100-VLOOKUP(N46,'[1]Pricing '!$A$86:$K$110,11,FALSE) -> -2.5121048 | P46: =O46-$U$2 -> -2.3871048 | Q46: =Q45-0.125 -> 6.625 | R46: =100-VLOOKUP(Q46,'[1]Pricing '!$A$620:$K$644,11,FALSE) -> -2.5121048 | S46: =R46-$U$2 -> -2.3871048 | T46: =T45-0.125 -> 6.75 | U46: =100-VLOOKUP(T46,'[1]Pricing '!$A$113:$K$137,11,FALSE) -> -2.7272591 | V46: =U46-$U$2 -> -2.6022591 | W46: =W45-0.125 -> 7 | X46: =100-VLOOKUP(W46,'[1]Pricing '!$A$647:$K$671,11,FALSE) -> -3.1890398 | Y46: =X46-$U$2 -> -3.0640398 | Z46: =Z45-0.125 -> 7.375 | AA46: =100-VLOOKUP(Z46,'[1]Pricing '!$A$167:$K$191,11,FALSE) -> -2.2437664 | AB46: =AA46-$U$2 -> -2.1187664 | AC46: =AC45-0.125 -> 7.5 | AD46: =100-VLOOKUP(AC46,'[1]Pricing '!$A$674:$K$698,11,FALSE) -> -2.6012904 | AE46: =AD46-$U$2 -> -2.4762904 | AF46: =AF45-0.125 -> 7.125 | AG46: =100-VLOOKUP(AF46,'[1]Pricing '!$A$194:$K$218,11,FALSE) -> -2.8928149 | AH46: =AG46-$U$2 -> -2.7678149 | AI46: =AI45-0.125 -> 7.125 | AJ46: =100-VLOOKUP(AI46,'[1]Pricing '!$A$701:$K$725,11,FALSE) -> -2.8928149 | AK46: =AJ46-$U$2 -> -2.7678149
B47: {=INDEX($A$162:$DE$162,0,MATCH(B46,$A$162:$DE$162,0)-1)} -> 7.125 | C47: =100-VLOOKUP(B47,'[1]Pricing '!$A$6:$K$30,11,FALSE) -> -3.1056343 | D47: =C47-$U$2 -> -2.9806343 | E47: {=INDEX($A$162:$DE$162,0,MATCH(E46,$A$162:$DE$162,0)-1)} -> 7.375 | F47: =100-VLOOKUP(E47,'[1]Pricing '!$A$566:$K$590,11,FALSE) -> -3.7977794 | G47: =F47-$U$2 -> -3.6727794 | H47: =H46-0.125 -> 7 | I47: =100-VLOOKUP(H47,'[1]Pricing '!$A$59:$K$83,11,FALSE) -> -1.9244188 | J47: =I47-$U$2 -> -1.7994188 | K47: =K46-0.125 -> 7 | L47: =100-VLOOKUP(K47,'[1]Pricing '!$A$593:$K$617,11,FALSE) -> -1.9244188 | M47: =L47-$U$2 -> -1.7994188 | N47: =N46-0.125 -> 6.5 | O47: =100-VLOOKUP(N47,'[1]Pricing '!$A$86:$K$110,11,FALSE) -> -2.3369705 | P47: =O47-$U$2 -> -2.2119705 | Q47: =Q46-0.125 -> 6.5 | R47: =100-VLOOKUP(Q47,'[1]Pricing '!$A$620:$K$644,11,FALSE) -> -2.3369705 | S47: =R47-$U$2 -> -2.2119705 | T47: =T46-0.125 -> 6.625 | U47: =100-VLOOKUP(T47,'[1]Pricing '!$A$113:$K$137,11,FALSE) -> -2.5101048 | V47: =U47-$U$2 -> -2.3851048 | W47: =W46-0.125 -> 6.875 | X47: =100-VLOOKUP(W47,'[1]Pricing '!$A$647:$K$671,11,FALSE) -> -2.9713409 | Y47: =X47-$U$2 -> -2.8463409 | Z47: =Z46-0.125 -> 7.25 | AA47: =100-VLOOKUP(Z47,'[1]Pricing '!$A$167:$K$191,11,FALSE) -> -1.7710252 | AB47: =AA47-$U$2 -> -1.6460252 | AC47: =AC46-0.125 -> 7.375 | AD47: =100-VLOOKUP(AC47,'[1]Pricing '!$A$674:$K$698,11,FALSE) -> -2.2437664 | AE47: =AD47-$U$2 -> -2.1187664 | AF47: =AF46-0.125 -> 7 | AG47: =100-VLOOKUP(AF47,'[1]Pricing '!$A$194:$K$218,11,FALSE) -> -2.6913756 | AH47: =AG47-$U$2 -> -2.5663756 | AI47: =AI46-0.125 -> 7 | AJ47: =100-VLOOKUP(AI47,'[1]Pricing '!$A$701:$K$725,11,FALSE) -> -2.6913756 | AK47: =AJ47-$U$2 -> -2.5663756
B48: {=INDEX($A$162:$DE$162,0,MATCH(B47,$A$162:$DE$162,0)-1)} -> 7 | C48: =100-VLOOKUP(B48,'[1]Pricing '!$A$6:$K$30,11,FALSE) -> -2.7784188 | D48: =C48-$U$2 -> -2.6534188 | E48: {=INDEX($A$162:$DE$162,0,MATCH(E47,$A$162:$DE$162,0)-1)} -> 7.25 | F48: =100-VLOOKUP(E48,'[1]Pricing '!$A$566:$K$590,11,FALSE) -> -3.3192232 | G48: =F48-$U$2 -> -3.1942232 | H48: =H47-0.125 -> 6.875 | I48: =100-VLOOKUP(H48,'[1]Pricing '!$A$59:$K$83,11,FALSE) -> -1.6686371 | J48: =I48-$U$2 -> -1.5436371 | K48: =K47-0.125 -> 6.875 | L48: =100-VLOOKUP(K48,'[1]Pricing '!$A$593:$K$617,11,FALSE) -> -1.6686371 | M48: =L48-$U$2 -> -1.5436371 | N48: =N47-0.125 -> 6.375 | O48: =100-VLOOKUP(N48,'[1]Pricing '!$A$86:$K$110,11,FALSE) -> -2.0965438 | P48: =O48-$U$2 -> -1.9715438 | Q48: =Q47-0.125 -> 6.375 | R48: =100-VLOOKUP(Q48,'[1]Pricing '!$A$620:$K$644,11,FALSE) -> -2.0965438 | S48: =R48-$U$2 -> -1.9715438 | T48: =T47-0.125 -> 6.5 | U48: =100-VLOOKUP(T48,'[1]Pricing '!$A$113:$K$137,11,FALSE) -> -2.2889705 | V48: =U48-$U$2 -> -2.1639705 | W48: =W47-0.125 -> 6.75 | X48: =100-VLOOKUP(W48,'[1]Pricing '!$A$647:$K$671,11,FALSE) -> -2.7272591 | Y48: =X48-$U$2 -> -2.6022591 | Z48: =Z47-0.125 -> 7.125 | AA48: =100-VLOOKUP(Z48,'[1]Pricing '!$A$167:$K$191,11,FALSE) -> -2.015445 | AB48: =AA48-$U$2 -> -1.890445 | AC48: =AC47-0.125 -> 7.25 | AD48: =100-VLOOKUP(AC48,'[1]Pricing '!$A$674:$K$698,11,FALSE) -> -1.7710252 | AE48: =AD48-$U$2 -> -1.6460252 | AF48: =AF47-0.125 -> 6.875 | AG48: =100-VLOOKUP(AF48,'[1]Pricing '!$A$194:$K$218,11,FALSE) -> -2.1056408 | AH48: =AG48-$U$2 -> -1.9806408 | AI48: =AI47-0.125 -> 6.875 | AJ48: =100-VLOOKUP(AI48,'[1]Pricing '!$A$701:$K$725,11,FALSE) -> -2.1056408 | AK48: =AJ48-$U$2 -> -1.9806408
B49: {=INDEX($A$162:$DE$162,0,MATCH(B48,$A$162:$DE$162,0)-1)} -> 6.875 | C49: =100-VLOOKUP(B49,'[1]Pricing '!$A$6:$K$30,11,FALSE) -> -2.3166371 | D49: =C49-$U$2 -> -2.1916371 | E49: {=INDEX($A$162:$DE$162,0,MATCH(E48,$A$162:$DE$162,0)-1)} -> 7.125 | F49: =100-VLOOKUP(E49,'[1]Pricing '!$A$566:$K$590,11,FALSE) -> -3.1056343 | G49: =F49-$U$2 -> -2.9806343 | H49: =H48-0.125 -> 6.75 | I49: =100-VLOOKUP(H49,'[1]Pricing '!$A$59:$K$83,11,FALSE) -> -1.3690354 | J49: =I49-$U$2 -> -1.2440354 | K49: =K48-0.125 -> 6.75 | L49: =100-VLOOKUP(K49,'[1]Pricing '!$A$593:$K$617,11,FALSE) -> -1.3690354 | M49: =L49-$U$2 -> -1.2440354 | N49: =N48-0.125 -> 6.25 | O49: =100-VLOOKUP(N49,'[1]Pricing '!$A$86:$K$110,11,FALSE) -> -1.8050742 | P49: =O49-$U$2 -> -1.6800742 | Q49: =Q48-0.125 -> 6.25 | R49: =100-VLOOKUP(Q49,'[1]Pricing '!$A$620:$K$644,11,FALSE) -> -1.8050742 | S49: =R49-$U$2 -> -1.6800742 | T49: =T48-0.125 -> 6.375 | U49: =100-VLOOKUP(T49,'[1]Pricing '!$A$113:$K$137,11,FALSE) -> -2.0515438 | V49: =U49-$U$2 -> -1.9265438 | W49: =W48-0.125 -> 6.625 | X49: =100-VLOOKUP(W49,'[1]Pricing '!$A$647:$K$671,11,FALSE) -> -2.5101048 | Y49: =X49-$U$2 -> -2.3851048 | Z49: =Z48-0.125 -> 7 | AA49: =100-VLOOKUP(Z49,'[1]Pricing '!$A$167:$K$191,11,FALSE) -> -1.7028289 | AB49: =AA49-$U$2 -> -1.5778289 | AC49: =AC48-0.125 -> 7.125 | AD49: =100-VLOOKUP(AC49,'[1]Pricing '!$A$674:$K$698,11,FALSE) -> -2.015445 | AE49: =AD49-$U$2 -> -1.890445 | AF49: =AF48-0.125 -> 6.75 | AG49: =100-VLOOKUP(AF49,'[1]Pricing '!$A$194:$K$218,11,FALSE) -> -1.7302069 | AH49: =AG49-$U$2 -> -1.6052069 | AI49: =AI48-0.125 -> 6.75 | AJ49: =100-VLOOKUP(AI49,'[1]Pricing '!$A$701:$K$725,11,FALSE) -> -1.7302069 | AK49: =AJ49-$U$2 -> -1.6052069
B50: {=INDEX($A$162:$DE$162,0,MATCH(B49,$A$162:$DE$162,0)-1)} -> 6.75 | C50: =100-VLOOKUP(B50,'[1]Pricing '!$A$6:$K$30,11,FALSE) -> -1.7760354 | D50: =C50-$U$2 -> -1.6510354 | E50: {=INDEX($A$162:$DE$162,0,MATCH(E49,$A$162:$DE$162,0)-1)} -> 7 | F50: =100-VLOOKUP(E50,'[1]Pricing '!$A$566:$K$590,11,FALSE) -> -2.7784188 | G50: =F50-$U$2 -> -2.6534188 | H50: =H49-0.125 -> 6.625 | I50: =100-VLOOKUP(H50,'[1]Pricing '!$A$59:$K$83,11,FALSE) -> -1.3031419 | J50: =I50-$U$2 -> -1.1781419 | K50: =K49-0.125 -> 6.625 | L50: =100-VLOOKUP(K50,'[1]Pricing '!$A$593:$K$617,11,FALSE) -> -1.3031419 | M50: =L50-$U$2 -> -1.1781419 | N50: =N49-0.125 -> 6.125 | O50: =100-VLOOKUP(N50,'[1]Pricing '!$A$86:$K$110,11,FALSE) -> -1.4699316 | P50: =O50-$U$2 -> -1.3449316 | Q50: =Q49-0.125 -> 6.125 | R50: =100-VLOOKUP(Q50,'[1]Pricing '!$A$620:$K$644,11,FALSE) -> -1.4699316 | S50: =R50-$U$2 -> -1.3449316 | T50: =T49-0.125 -> 6.25 | U50: =100-VLOOKUP(T50,'[1]Pricing '!$A$113:$K$137,11,FALSE) -> -1.7630742 | V50: =U50-$U$2 -> -1.6380742 | W50: =W49-0.125 -> 6.5 | X50: =100-VLOOKUP(W50,'[1]Pricing '!$A$647:$K$671,11,FALSE) -> -2.2889705 | Y50: =X50-$U$2 -> -2.1639705 | Z50: =Z49-0.125 -> 6.875 | AA50: =100-VLOOKUP(Z50,'[1]Pricing '!$A$167:$K$191,11,FALSE) -> -1.5037035 | AB50: =AA50-$U$2 -> -1.3787035 | AC50: =AC49-0.125 -> 7 | AD50: =100-VLOOKUP(AC50,'[1]Pricing '!$A$674:$K$698,11,FALSE) -> -1.7028289 | AE50: =AD50-$U$2 -> -1.5778289 | AF50: =AF49-0.125 -> 6.625 | AG50: =100-VLOOKUP(AF50,'[1]Pricing '!$A$194:$K$218,11,FALSE) -> -1.6011124 | AH50: =AG50-$U$2 -> -1.4761124 | AI50: =AI49-0.125 -> 6.625 | AJ50: =100-VLOOKUP(AI50,'[1]Pricing '!$A$701:$K$725,11,FALSE) -> -1.6011124 | AK50: =AJ50-$U$2 -> -1.4761124
B51: {=INDEX($A$162:$DE$162,0,MATCH(B50,$A$162:$DE$162,0)-1)} -> 6.625 | C51: =100-VLOOKUP(B51,'[1]Pricing '!$A$6:$K$30,11,FALSE) -> -1.6001419 | D51: =C51-$U$2 -> -1.4751419 | E51: {=INDEX($A$162:$DE$162,0,MATCH(E50,$A$162:$DE$162,0)-1)} -> 6.875 | F51: =100-VLOOKUP(E51,'[1]Pricing '!$A$566:$K$590,11,FALSE) -> -2.3166371 | G51: =F51-$U$2 -> -2.1916371 | H51: =H50-0.125 -> 6.5 | I51: =100-VLOOKUP(H51,'[1]Pricing '!$A$59:$K$83,11,FALSE) -> -0.97955797 | J51: =I51-$U$2 -> -0.85455797 | K51: =K50-0.125 -> 6.5 | L51: =100-VLOOKUP(K51,'[1]Pricing '!$A$593:$K$617,11,FALSE) -> -0.97955797 | M51: =L51-$U$2 -> -0.85455797 | N51: =N50-0.125 -> 6 | O51: =100-VLOOKUP(N51,'[1]Pricing '!$A$86:$K$110,11,FALSE) -> -1.2045454 | P51: =O51-$U$2 -> -1.0795454 | Q51: =Q50-0.125 -> 6 | R51: =100-VLOOKUP(Q51,'[1]Pricing '!$A$620:$K$644,11,FALSE) -> -1.2045454 | S51: =R51-$U$2 -> -1.0795454 | T51: =T50-0.125 -> 6.125 | U51: =100-VLOOKUP(T51,'[1]Pricing '!$A$113:$K$137,11,FALSE) -> -1.4469316 | V51: =U51-$U$2 -> -1.3219316 | W51: =W50-0.125 -> 6.375 | X51: =100-VLOOKUP(W51,'[1]Pricing '!$A$647:$K$671,11,FALSE) -> -2.0515438 | Y51: =X51-$U$2 -> -1.9265438 | Z51: =Z50-0.125 -> 6.75 | AA51: =100-VLOOKUP(Z51,'[1]Pricing '!$A$167:$K$191,11,FALSE) -> -0.95061475 | AB51: =AA51-$U$2 -> -0.82561475 | AC51: =AC50-0.125 -> 6.875 | AD51: =100-VLOOKUP(AC51,'[1]Pricing '!$A$674:$K$698,11,FALSE) -> -1.5037035 | AE51: =AD51-$U$2 -> -1.3787035 | AF51: =AF50-0.125 -> 6.5 | AG51: =100-VLOOKUP(AF51,'[1]Pricing '!$A$194:$K$218,11,FALSE) -> -1.3821443 | AH51: =AG51-$U$2 -> -1.2571443 | AI51: =AI50-0.125 -> 6.5 | AJ51: =100-VLOOKUP(AI51,'[1]Pricing '!$A$701:$K$725,11,FALSE) -> -1.3821443 | AK51: =AJ51-$U$2 -> -1.2571443
B52: {=INDEX($A$162:$DE$162,0,MATCH(B51,$A$162:$DE$162,0)-1)} -> 6.5 | C52: =100-VLOOKUP(B52,'[1]Pricing '!$A$6:$K$30,11,FALSE) -> -1.228558 | D52: =C52-$U$2 -> -1.103558 | E52: {=INDEX($A$162:$DE$162,0,MATCH(E51,$A$162:$DE$162,0)-1)} -> 6.75 | F52: =100-VLOOKUP(E52,'[1]Pricing '!$A$566:$K$590,11,FALSE) -> -1.7760354 | G52: =F52-$U$2 -> -1.6510354 | H52: =H51-0.125 -> 6.375 | I52: =100-VLOOKUP(H52,'[1]Pricing '!$A$59:$K$83,11,FALSE) -> -0.61457311 | J52: =I52-$U$2 -> -0.48957311 | K52: =K51-0.125 -> 6.375 | L52: =100-VLOOKUP(K52,'[1]Pricing '!$A$593:$K$617,11,FALSE) -> -0.61457311 | M52: =L52-$U$2 -> -0.48957311 | N52: =N51-0.125 -> 5.875 | O52: =100-VLOOKUP(N52,'[1]Pricing '!$A$86:$K$110,11,FALSE) -> -0.93241865 | P52: =O52-$U$2 -> -0.80741865 | Q52: =Q51-0.125 -> 5.875 | R52: =100-VLOOKUP(Q52,'[1]Pricing '!$A$620:$K$644,11,FALSE) -> -0.93241865 | S52: =R52-$U$2 -> -0.80741865 | T52: =T51-0.125 -> 6 | U52: =100-VLOOKUP(T52,'[1]Pricing '!$A$113:$K$137,11,FALSE) -> -1.1825454 | V52: =U52-$U$2 -> -1.0575454 | W52: =W51-0.125 -> 6.25 | X52: =100-VLOOKUP(W52,'[1]Pricing '!$A$647:$K$671,11,FALSE) -> -1.7630742 | Y52: =X52-$U$2 -> -1.6380742 | Z52: =Z51-0.125 -> 6.625 | AA52: =100-VLOOKUP(Z52,'[1]Pricing '!$A$167:$K$191,11,FALSE) -> -0.96325543 | AB52: =AA52-$U$2 -> -0.83825543 | AC52: =AC51-0.125 -> 6.75 | AD52: =100-VLOOKUP(AC52,'[1]Pricing '!$A$674:$K$698,11,FALSE) -> -0.95061475 | AE52: =AD52-$U$2 -> -0.82561475 | AF52: =AF51-0.125 -> 6.375 | AG52: =100-VLOOKUP(AF52,'[1]Pricing '!$A$194:$K$218,11,FALSE) -> -1.1276478 | AH52: =AG52-$U$2 -> -1.0026478 | AI52: =AI51-0.125 -> 6.375 | AJ52: =100-VLOOKUP(AI52,'[1]Pricing '!$A$701:$K$725,11,FALSE) -> -1.1276478 | AK52: =AJ52-$U$2 -> -1.0026478
B53: {=INDEX($A$162:$DE$162,0,MATCH(B52,$A$162:$DE$162,0)-1)} -> 6.375 | C53: =100-VLOOKUP(B53,'[1]Pricing '!$A$6:$K$30,11,FALSE) -> -0.89657311 | D53: =C53-$U$2 -> -0.77157311 | E53: {=INDEX($A$162:$DE$162,0,MATCH(E52,$A$162:$DE$162,0)-1)} -> 6.625 | F53: =100-VLOOKUP(E53,'[1]Pricing '!$A$566:$K$590,11,FALSE) -> -1.6001419 | G53: =F53-$U$2 -> -1.4751419 | H53: =H52-0.125 -> 6.25 | I53: =100-VLOOKUP(H53,'[1]Pricing '!$A$59:$K$83,11,FALSE) -> -0.21893415 | J53: =I53-$U$2 -> -0.093934154 | K53: =K52-0.125 -> 6.25 | L53: =100-VLOOKUP(K53,'[1]Pricing '!$A$593:$K$617,11,FALSE) -> -0.21893415 | M53: =L53-$U$2 -> -0.093934154 | N53: =N52-0.125 -> 5.75 | O53: =100-VLOOKUP(N53,'[1]Pricing '!$A$86:$K$110,11,FALSE) -> -0.5290574 | P53: =O53-$U$2 -> -0.4040574 | Q53: =Q52-0.125 -> 5.75 | R53: =100-VLOOKUP(Q53,'[1]Pricing '!$A$620:$K$644,11,FALSE) -> -0.5290574 | S53: =R53-$U$2 -> -0.4040574 | T53: =T52-0.125 -> 5.875 | U53: =100-VLOOKUP(T53,'[1]Pricing '!$A$113:$K$137,11,FALSE) -> -0.91441865 | V53: =U53-$U$2 -> -0.78941865 | W53: =W52-0.125 -> 6.125 | X53: =100-VLOOKUP(W53,'[1]Pricing '!$A$647:$K$671,11,FALSE) -> -1.4469316 | Y53: =X53-$U$2 -> -1.3219316 | Z53: =Z52-0.125 -> 6.5 | AA53: =100-VLOOKUP(Z53,'[1]Pricing '!$A$167:$K$191,11,FALSE) -> -0.69611537 | AB53: =AA53-$U$2 -> -0.57111537 | AC53: =AC52-0.125 -> 6.625 | AD53: =100-VLOOKUP(AC53,'[1]Pricing '!$A$674:$K$698,11,FALSE) -> -0.96325543 | AE53: =AD53-$U$2 -> -0.83825543 | AF53: =AF52-0.125 -> 6.25 | AG53: =100-VLOOKUP(AF53,'[1]Pricing '!$A$194:$K$218,11,FALSE) -> -0.75800343 | AH53: =AG53-$U$2 -> -0.63300343 | AI53: =AI52-0.125 -> 6.25 | AJ53: =100-VLOOKUP(AI53,'[1]Pricing '!$A$701:$K$725,11,FALSE) -> -0.75800343 | AK53: =AJ53-$U$2 -> -0.63300343
B54: {=INDEX($A$162:$DE$162,0,MATCH(B53,$A$162:$DE$162,0)-1)} -> 6.25 | C54: =100-VLOOKUP(B54,'[1]Pricing '!$A$6:$K$30,11,FALSE) -> -0.44793415 | D54: =C54-$U$2 -> -0.32293415 | E54: {=INDEX($A$162:$DE$162,0,MATCH(E53,$A$162:$DE$162,0)-1)} -> 6.5 | F54: =100-VLOOKUP(E54,'[1]Pricing '!$A$566:$K$590,11,FALSE) -> -1.228558 | G54: =F54-$U$2 -> -1.103558 | H54: =H53-0.125 -> 6.125 | I54: =100-VLOOKUP(H54,'[1]Pricing '!$A$59:$K$83,11,FALSE) -> -0.16546194 | J54: =I54-$U$2 -> -0.040461938 | K54: =K53-0.125 -> 6.125 | L54: =100-VLOOKUP(K54,'[1]Pricing '!$A$593:$K$617,11,FALSE) -> -0.16546194 | M54: =L54-$U$2 -> -0.040461938 | N54: =N53-0.125 -> 5.625 | O54: =100-VLOOKUP(N54,'[1]Pricing '!$A$86:$K$110,11,FALSE) -> -0.19157641 | P54: =O54-$U$2 -> -0.066576413 | Q54: =Q53-0.125 -> 5.625 | R54: =100-VLOOKUP(Q54,'[1]Pricing '!$A$620:$K$644,11,FALSE) -> -0.19157641 | S54: =R54-$U$2 -> -0.066576413 | T54: =T53-0.125 -> 5.75 | U54: =100-VLOOKUP(T54,'[1]Pricing '!$A$113:$K$137,11,FALSE) -> -0.5130574 | V54: =U54-$U$2 -> -0.3880574 | W54: =W53-0.125 -> 6 | X54: =100-VLOOKUP(W54,'[1]Pricing '!$A$647:$K$671,11,FALSE) -> -1.1825454 | Y54: =X54-$U$2 -> -1.0575454 | Z54: =Z53-0.125 -> 6.375 | AA54: =100-VLOOKUP(Z54,'[1]Pricing '!$A$167:$K$191,11,FALSE) -> -0.44264573 | AB54: =AA54-$U$2 -> -0.31764573 | AC54: =AC53-0.125 -> 6.5 | AD54: =100-VLOOKUP(AC54,'[1]Pricing '!$A$674:$K$698,11,FALSE) -> -0.69611537 | AE54: =AD54-$U$2 -> -0.57111537 | AF54: =AF53-0.125 -> 6.125 | AG54: =100-VLOOKUP(AF54,'[1]Pricing '!$A$194:$K$218,11,FALSE) -> -0.49630595 | AH54: =AG54-$U$2 -> -0.37130595 | AI54: =AI53-0.125 -> 6.125 | AJ54: =100-VLOOKUP(AI54,'[1]Pricing '!$A$701:$K$725,11,FALSE) -> -0.49630595 | AK54: =AJ54-$U$2 -> -0.37130595
B55: {=INDEX($A$162:$DE$162,0,MATCH(B54,$A$162:$DE$162,0)-1)} -> 6.125 | C55: =100-VLOOKUP(B55,'[1]Pricing '!$A$6:$K$30,11,FALSE) -> -0.0084619383 | D55: =C55-$U$2 -> 0.11653806 | E55: {=INDEX($A$162:$DE$162,0,MATCH(E54,$A$162:$DE$162,0)-1)} -> 6.375 | F55: =100-VLOOKUP(E55,'[1]Pricing '!$A$566:$K$590,11,FALSE) -> -0.89657311 | G55: =F55-$U$2 -> -0.77157311 | H55: =H54-0.125 -> 6 | I55: =100-VLOOKUP(H55,'[1]Pricing '!$A$59:$K$83,11,FALSE) -> 0.2708967 | J55: =I55-$U$2 -> 0.3958967 | K55: =K54-0.125 -> 6 | L55: =100-VLOOKUP(K55,'[1]Pricing '!$A$593:$K$617,11,FALSE) -> 0.2708967 | M55: =L55-$U$2 -> 0.3958967 | N55: =N54-0.125 -> 5.5 | O55: =100-VLOOKUP(N55,'[1]Pricing '!$A$86:$K$110,11,FALSE) -> 0.13124288 | P55: =O55-$U$2 -> 0.25624288 | Q55: =Q54-0.125 -> 5.5 | R55: =100-VLOOKUP(Q55,'[1]Pricing '!$A$620:$K$644,11,FALSE) -> 0.13124288 | S55: =R55-$U$2 -> 0.25624288 | T55: =T54-0.125 -> 5.625 | U55: =100-VLOOKUP(T55,'[1]Pricing '!$A$113:$K$137,11,FALSE) -> -0.19057641 | V55: =U55-$U$2 -> -0.065576413 | W55: =W54-0.125 -> 5.875 | X55: =100-VLOOKUP(W55,'[1]Pricing '!$A$647:$K$671,11,FALSE) -> -0.91441865 | Y55: =X55-$U$2 -> -0.78941865 | Z55: =Z54-0.125 -> 6.25 | AA55: =100-VLOOKUP(Z55,'[1]Pricing '!$A$167:$K$191,11,FALSE) -> -0.052398303 | AB55: =AA55-$U$2 -> 0.072601697 | AC55: =AC54-0.125 -> 6.375 | AD55: =100-VLOOKUP(AC55,'[1]Pricing '!$A$674:$K$698,11,FALSE) -> -0.44264573 | AE55: =AD55-$U$2 -> -0.31764573 | AF55: =AF54-0.125 -> 6 | AG55: =100-VLOOKUP(AF55,'[1]Pricing '!$A$194:$K$218,11,FALSE) -> -0.17586102 | AH55: =AG55-$U$2 -> -0.050861019 | AI55: =AI54-0.125 -> 6 | AJ55: =100-VLOOKUP(AI55,'[1]Pricing '!$A$701:$K$725,11,FALSE) -> -0.17586102 | AK55: =AJ55-$U$2 -> -0.050861019
... B61: {=INDEX($A$162:$DE$162,0,MATCH(B60,$A$162:$DE$162,0)-1)} -> 5.5 | C61: =100-VLOOKUP(B61,'[1]Pricing '!$A$6:$K$30,11,FALSE) -> 2.6369002 | D61: =C61-$U$2 -> 2.7619002 | E61: {=INDEX($A$162:$DE$162,0,MATCH(E60,$A$162:$DE$162,0)-1)} -> 5.75 | F61: =100-VLOOKUP(E61,'[1]Pricing '!$A$566:$K$590,11,FALSE) -> 1.5245396 | G61: =F61-$U$2 -> 1.6495396 | H61: =H60-0.125 -> 5.25 | I61: =100-VLOOKUP(H61,'[1]Pricing '!$A$59:$K$83,11,FALSE) -> 3.290068 | J61: =I61-$U$2 -> 3.415068 | K61: =K60-0.125 -> 5.25 | L61: =100-VLOOKUP(K61,'[1]Pricing '!$A$593:$K$617,11,FALSE) -> 3.290068 | M61: =L61-$U$2 -> 3.415068 | N61: =N60-0.125 -> 4.75 | O61: =100-VLOOKUP(N61,'[1]Pricing '!$A$86:$K$110,11,FALSE) -> 2.4388164 | P61: =O61-$U$2 -> 2.5638164 | Q61: =Q60-0.125 -> 4.75 | R61: =100-VLOOKUP(Q61,'[1]Pricing '!$A$620:$K$644,11,FALSE) -> 2.4388164 | S61: =R61-$U$2 -> 2.5638164 | T61: =T60-0.125 -> 4.875 | U61: =100-VLOOKUP(T61,'[1]Pricing '!$A$113:$K$137,11,FALSE) -> 1.05236 | V61: =U61-$U$2 -> 1.17736 | W61: =W60-0.125 -> 5.125 | X61: =100-VLOOKUP(W61,'[1]Pricing '!$A$647:$K$671,11,FALSE) -> 0.52802587 | Y61: =X61-$U$2 -> 0.65302587 | Z61: =Z60-0.125 -> 5.5 | AA61: =100-VLOOKUP(Z61,'[1]Pricing '!$A$167:$K$191,11,FALSE) -> 3.0148427 | AB61: =AA61-$U$2 -> 3.1398427 | AC61: =AC60-0.125 -> 5.625 | AD61: =100-VLOOKUP(AC61,'[1]Pricing '!$A$674:$K$698,11,FALSE) -> 2.4235853 | AE61: =AD61-$U$2 -> 2.5485853 | AF61: =AF60-0.125 -> 5.25 | AG61: =100-VLOOKUP(AF61,'[1]Pricing '!$A$194:$K$218,11,FALSE) -> 2.0172316 | AH61: =AG61-$U$2 -> 2.1422316 | AI61: =AI60-0.125 -> 5.25 | AJ61: =100-VLOOKUP(AI61,'[1]Pricing '!$A$701:$K$725,11,FALSE) -> 2.0172316 | AK61: =AJ61-$U$2 -> 2.1422316
B62: {=INDEX($A$162:$DE$162,0,MATCH(B61,$A$162:$DE$162,0)-1)} -> 5.375 | C62: =IFERROR(100-VLOOKUP(B62,'[1]Pricing '!$A$6:$K$30,11,FALSE),"NA") -> 3.2056035 | D62: =C62-$U$2 -> 3.3306035 | E62: {=INDEX($A$162:$DE$162,0,MATCH(E61,$A$162:$DE$162,0)-1)} -> 5.625 | F62: =100-VLOOKUP(E62,'[1]Pricing '!$A$566:$K$590,11,FALSE) -> 2.0566477 | G62: =F62-$U$2 -> 2.1816477 | H62: =H61-0.125 -> 5.125 | I62: =100-VLOOKUP(H62,'[1]Pricing '!$A$59:$K$83,11,FALSE) -> 3.618032 | J62: =I62-$U$2 -> 3.743032 | K62: =K61-0.125 -> 5.125 | L62: =100-VLOOKUP(K62,'[1]Pricing '!$A$593:$K$617,11,FALSE) -> 3.618032 | M62: =L62-$U$2 -> 3.743032 | N62: =N61-0.125 -> 4.625 | O62: =100-VLOOKUP(N62,'[1]Pricing '!$A$86:$K$110,11,FALSE) -> 2.8945452 | P62: =O62-$U$2 -> 3.0195452 | Q62: =Q61-0.125 -> 4.625 | R62: =100-VLOOKUP(Q62,'[1]Pricing '!$A$620:$K$644,11,FALSE) -> 2.8945452 | S62: =R62-$U$2 -> 3.0195452 | T62: =T61-0.125 -> 4.75 | U62: =100-VLOOKUP(T62,'[1]Pricing '!$A$113:$K$137,11,FALSE) -> 1.4398164 | V62: =U62-$U$2 -> 1.5648164 | W62: =W61-0.125 -> 5 | X62: =100-VLOOKUP(W62,'[1]Pricing '!$A$647:$K$671,11,FALSE) -> 0.68621885 | Y62: =X62-$U$2 -> 0.81121885 | Z62: =Z61-0.125 -> 5.375 | AA62: =100-VLOOKUP(Z62,'[1]Pricing '!$A$167:$K$191,11,FALSE) -> 3.5867835 | AB62: =AA62-$U$2 -> 3.7117835 | AC62: =AC61-0.125 -> 5.5 | AD62: =100-VLOOKUP(AC62,'[1]Pricing '!$A$674:$K$698,11,FALSE) -> 3.0148427 | AE62: =AD62-$U$2 -> 3.1398427 | AF62: =AF61-0.125 -> 5.125 | AG62: =100-VLOOKUP(AF62,'[1]Pricing '!$A$194:$K$218,11,FALSE) -> 2.2103841 | AH62: =AG62-$U$2 -> 2.3353841 | AI62: =AI61-0.125 -> 5.125 | AJ62: =100-VLOOKUP(AI62,'[1]Pricing '!$A$701:$K$725,11,FALSE) -> 2.2103841 | AK62: =AJ62-$U$2 -> 2.3353841
B63: {=INDEX($A$162:$DE$162,0,MATCH(B62,$A$162:$DE$162,0)-1)} -> 5.25 | C63: =IFERROR(100-VLOOKUP(B63,'[1]Pricing '!$A$6:$K$30,11,FALSE),"NA") -> 4.197068 | D63: =C63-$U$2 -> 4.322068 | E63: {=INDEX($A$162:$DE$162,0,MATCH(E62,$A$162:$DE$162,0)-1)} -> 5.5 | F63: =100-VLOOKUP(E63,'[1]Pricing '!$A$566:$K$590,11,FALSE) -> 2.6369002 | G63: =F63-$U$2 -> 2.7619002 | H63: =H62-0.125 -> 5 | I63: =100-VLOOKUP(H63,'[1]Pricing '!$A$59:$K$83,11,FALSE) -> 4.1210553 | J63: =I63-$U$2 -> 4.2460553 | K63: =K62-0.125 -> 5 | L63: =100-VLOOKUP(K63,'[1]Pricing '!$A$593:$K$617,11,FALSE) -> 4.1210553 | M63: =L63-$U$2 -> 4.2460553 | N63: =N62-0.125 -> 4.5 | O63: =100-VLOOKUP(N63,'[1]Pricing '!$A$86:$K$110,11,FALSE) -> 3.0965591 | P63: =O63-$U$2 -> 3.2215591 | Q63: =Q62-0.125 -> 4.5 | R63: =100-VLOOKUP(Q63,'[1]Pricing '!$A$620:$K$644,11,FALSE) -> 3.0965591 | S63: =R63-$U$2 -> 3.2215591 | T63: =T62-0.125 -> 4.625 | U63: =100-VLOOKUP(T63,'[1]Pricing '!$A$113:$K$137,11,FALSE) -> 1.8775452 | V63: =U63-$U$2 -> 2.0025452 | W63: =W62-0.125 -> 4.875 | X63: =100-VLOOKUP(W63,'[1]Pricing '!$A$647:$K$671,11,FALSE) -> 1.05236 | Y63: =X63-$U$2 -> 1.17736 | Z63: =Z62-0.125 -> 5.25 | AA63: =100-VLOOKUP(Z63,'[1]Pricing '!$A$167:$K$191,11,FALSE) -> 4.506967 | AB63: =AA63-$U$2 -> 4.631967 | AC63: =AC62-0.125 -> 5.375 | AD63: =100-VLOOKUP(AC63,'[1]Pricing '!$A$674:$K$698,11,FALSE) -> 3.5867835 | AE63: =AD63-$U$2 -> 3.7117835 | AF63: =AF62-0.125 -> 5 | AG63: =100-VLOOKUP(AF63,'[1]Pricing '!$A$194:$K$218,11,FALSE) -> 2.9187311 | AH63: =AG63-$U$2 -> 3.0437311 | AI63: =AI62-0.125 -> 5 | AJ63: =100-VLOOKUP(AI63,'[1]Pricing '!$A$701:$K$725,11,FALSE) -> 2.9187311 | AK63: =AJ63-$U$2 -> 3.0437311
B64: {=INDEX($A$162:$DE$162,0,MATCH(B63,$A$162:$DE$162,0)-1)} -> 5.125 | C64: =IFERROR(100-VLOOKUP(B64,'[1]Pricing '!$A$6:$K$30,11,FALSE),"NA") -> 4.204032 | D64: =C64-$U$2 -> 4.329032 | E64: {=INDEX($A$162:$DE$162,0,MATCH(E63,$A$162:$DE$162,0)-1)} -> 5.375 | F64: =100-VLOOKUP(E64,'[1]Pricing '!$A$566:$K$590,11,FALSE) -> 3.2056035 | G64: =F64-$U$2 -> 3.3306035 | H64: =H63-0.125 -> 4.875 | I64: =100-VLOOKUP(H64,'[1]Pricing '!$A$59:$K$83,11,FALSE) -> 4.7359012 | J64: =I64-$U$2 -> 4.8609012 | K64: =K63-0.125 -> 4.875 | L64: =100-VLOOKUP(K64,'[1]Pricing '!$A$593:$K$617,11,FALSE) -> 4.7359012 | M64: =L64-$U$2 -> 4.8609012 | N64: =N63-0.125 -> 4.375 | O64: =100-VLOOKUP(N64,'[1]Pricing '!$A$86:$K$110,11,FALSE) -> 3.5423055 | P64: =O64-$U$2 -> 3.6673055 | Q64: =Q63-0.125 -> 4.375 | R64: =100-VLOOKUP(Q64,'[1]Pricing '!$A$620:$K$644,11,FALSE) -> 3.5423055 | S64: =R64-$U$2 -> 3.6673055 | T64: =T63-0.125 -> 4.5 | U64: =100-VLOOKUP(T64,'[1]Pricing '!$A$113:$K$137,11,FALSE) -> 2.7325591 | V64: =U64-$U$2 -> 2.8575591 | W64: =W63-0.125 -> 4.75 | X64: =100-VLOOKUP(W64,'[1]Pricing '!$A$647:$K$671,11,FALSE) -> 1.4398164 | Y64: =X64-$U$2 -> 1.5648164 | Z64: =Z63-0.125 -> 5.125 | AA64: =100-VLOOKUP(Z64,'[1]Pricing '!$A$167:$K$191,11,FALSE) -> 5.6274668 | AB64: =AA64-$U$2 -> 5.7524668 | AC64: =AC63-0.125 -> 5.25 | AD64: =100-VLOOKUP(AC64,'[1]Pricing '!$A$674:$K$698,11,FALSE) -> 4.506967 | AE64: =AD64-$U$2 -> 4.631967 | AF64: =AF63-0.125 -> 4.875 | AG64: =100-VLOOKUP(AF64,'[1]Pricing '!$A$194:$K$218,11,FALSE) -> 3.2982717 | AH64: =AG64-$U$2 -> 3.4232717 | AI64: =AI63-0.125 -> 4.875 | AJ64: =100-VLOOKUP(AI64,'[1]Pricing '!$A$701:$K$725,11,FALSE) -> 3.2982717 | AK64: =AJ64-$U$2 -> 3.4232717
B65: {=INDEX($A$162:$DE$162,0,MATCH(B64,$A$162:$DE$162,0)-1)} -> 5 | C65: =IFERROR(100-VLOOKUP(B65,'[1]Pricing '!$A$6:$K$30,11,FALSE),"NA") -> 4.9040553 | D65: =C65-$U$2 -> 5.0290553 | E65: {=INDEX($A$162:$DE$162,0,MATCH(E64,$A$162:$DE$162,0)-1)} -> 5.25 | F65: =100-VLOOKUP(E65,'[1]Pricing '!$A$566:$K$590,11,FALSE) -> 4.197068 | G65: =F65-$U$2 -> 4.322068 | H65: =H64-0.125 -> 4.75 | I65: =100-VLOOKUP(H65,'[1]Pricing '!$A$59:$K$83,11,FALSE) -> 5.3515774 | J65: =I65-$U$2 -> 5.4765774 | K65: =K64-0.125 -> 4.75 | L65: =100-VLOOKUP(K65,'[1]Pricing '!$A$593:$K$617,11,FALSE) -> 5.3515774 | M65: =L65-$U$2 -> 5.4765774 | N65: =N64-0.125 -> 4.25 | O65: =100-VLOOKUP(N65,'[1]Pricing '!$A$86:$K$110,11,FALSE) -> 3.9897495 | P65: =O65-$U$2 -> 4.1147495 | Q65: =Q64-0.125 -> 4.25 | R65: =100-VLOOKUP(Q65,'[1]Pricing '!$A$620:$K$644,11,FALSE) -> 3.9897495 | S65: =R65-$U$2 -> 4.1147495 | T65: =T64-0.125 -> 4.375 | U65: =100-VLOOKUP(T65,'[1]Pricing '!$A$113:$K$137,11,FALSE) -> 3.2743055 | V65: =U65-$U$2 -> 3.3993055 | W65: =W64-0.125 -> 4.625 | X65: =100-VLOOKUP(W65,'[1]Pricing '!$A$647:$K$671,11,FALSE) -> 1.8775452 | Y65: =X65-$U$2 -> 2.0025452 | Z65: =Z64-0.125 -> 5 | AA65: =100-VLOOKUP(Z65,'[1]Pricing '!$A$167:$K$191,11,FALSE) -> 6.3340383 | AB65: =AA65-$U$2 -> 6.4590383 | AC65: =AC64-0.125 -> 5.125 | AD65: =100-VLOOKUP(AC65,'[1]Pricing '!$A$674:$K$698,11,FALSE) -> 5.6274668 | AE65: =AD65-$U$2 -> 5.7524668 | AF65: =AF64-0.125 -> 4.75 | AG65: =100-VLOOKUP(AF65,'[1]Pricing '!$A$194:$K$218,11,FALSE) -> 3.939277 | AH65: =AG65-$U$2 -> 4.064277 | AI65: =AI64-0.125 -> 4.75 | AJ65: =100-VLOOKUP(AI65,'[1]Pricing '!$A$701:$K$725,11,FALSE) -> 3.939277 | AK65: =AJ65-$U$2 -> 4.064277
B66: {=INDEX($A$162:$DE$162,0,MATCH(B65,$A$162:$DE$162,0)-1)} -> 4.875 | C66: =IFERROR(100-VLOOKUP(B66,'[1]Pricing '!$A$6:$K$30,11,FALSE),"NA") -> 5.6669012 | D66: =C66-$U$2 -> 5.7919012 | E66: {=INDEX($A$162:$DE$162,0,MATCH(E65,$A$162:$DE$162,0)-1)} -> 5.125 | F66: =100-VLOOKUP(E66,'[1]Pricing '!$A$566:$K$590,11,FALSE) -> 4.204032 | G66: =F66-$U$2 -> 4.329032 | H66: =H65-0.125 -> 4.625 | I66: =100-VLOOKUP(H66,'[1]Pricing '!$A$59:$K$83,11,FALSE) -> 6.1495101 | J66: =I66-$U$2 -> 6.2745101 | K66: =K65-0.125 -> 4.625 | L66: =100-VLOOKUP(K66,'[1]Pricing '!$A$593:$K$617,11,FALSE) -> 6.1495101 | M66: =L66-$U$2 -> 6.2745101 | N66: =N65-0.125 -> 4.125 | O66: =100-VLOOKUP(N66,'[1]Pricing '!$A$86:$K$110,11,FALSE) -> 4.3512278 | P66: =O66-$U$2 -> 4.4762278 | Q66: =Q65-0.125 -> 4.125 | R66: =100-VLOOKUP(Q66,'[1]Pricing '!$A$620:$K$644,11,FALSE) -> 4.3512278 | S66: =R66-$U$2 -> 4.4762278 | T66: =T65-0.125 -> 4.25 | U66: =100-VLOOKUP(T66,'[1]Pricing '!$A$113:$K$137,11,FALSE) -> 3.8177495 | V66: =U66-$U$2 -> 3.9427495 | W66: =W65-0.125 -> 4.5 | X66: =100-VLOOKUP(W66,'[1]Pricing '!$A$647:$K$671,11,FALSE) -> 2.7325591 | Y66: =X66-$U$2 -> 2.8575591 | Z66: =Z65-0.125 -> 4.875 | AA66: =100-VLOOKUP(Z66,'[1]Pricing '!$A$167:$K$191,11,FALSE) -> 6.6016623 | AB66: =AA66-$U$2 -> 6.7266623 | AC66: =AC65-0.125 -> 5 | AD66: =100-VLOOKUP(AC66,'[1]Pricing '!$A$674:$K$698,11,FALSE) -> 6.3340383 | AE66: =AD66-$U$2 -> 6.4590383 | AF66: =AF65-0.125 -> 4.625 | AG66: =100-VLOOKUP(AF66,'[1]Pricing '!$A$194:$K$218,11,FALSE) -> 3.9184098 | AH66: =AG66-$U$2 -> 4.0434098 | AI66: =AI65-0.125 -> 4.625 | AJ66: =100-VLOOKUP(AI66,'[1]Pricing '!$A$701:$K$725,11,FALSE) -> 3.9184098 | AK66: =AJ66-$U$2 -> 4.0434098
B67: {=INDEX($A$162:$DE$162,0,MATCH(B66,$A$162:$DE$162,0)-1)} -> 4.75 | C67: =IFERROR(100-VLOOKUP(B67,'[1]Pricing '!$A$6:$K$30,11,FALSE),"NA") -> 6.5315774 | D67: =C67-$U$2 -> 6.6565774 | E67: {=INDEX($A$162:$DE$162,0,MATCH(E66,$A$162:$DE$162,0)-1)} -> 5 | F67: =100-VLOOKUP(E67,'[1]Pricing '!$A$566:$K$590,11,FALSE) -> 4.9040553 | G67: =F67-$U$2 -> 5.0290553 | H67: =H66-0.125 -> 4.5 | I67: =100-VLOOKUP(H67,'[1]Pricing '!$A$59:$K$83,11,FALSE) -> 6.7494108 | J67: =I67-$U$2 -> 6.8744108 | K67: =K66-0.125 -> 4.5 | L67: =100-VLOOKUP(K67,'[1]Pricing '!$A$593:$K$617,11,FALSE) -> 6.7494108 | M67: =L67-$U$2 -> 6.8744108 | N67: =N66-0.125 -> 4 | O67: =100-VLOOKUP(N67,'[1]Pricing '!$A$86:$K$110,11,FALSE) -> 3.5834823 | P67: =O67-$U$2 -> 3.7084823 | Q67: =Q66-0.125 -> 4 | R67: =100-VLOOKUP(Q67,'[1]Pricing '!$A$620:$K$644,11,FALSE) -> 3.5834823 | S67: =R67-$U$2 -> 3.7084823 | T67: =T66-0.125 -> 4.125 | U67: =100-VLOOKUP(T67,'[1]Pricing '!$A$113:$K$137,11,FALSE) -> 4.3612278 | V67: =U67-$U$2 -> 4.4862278 | W67: =W66-0.125 -> 4.375 | X67: =100-VLOOKUP(W67,'[1]Pricing '!$A$647:$K$671,11,FALSE) -> 3.2743055 | Y67: =X67-$U$2 -> 3.3993055 | Z67: =Z66-0.125 -> 4.75 | AA67: =100-VLOOKUP(Z67,'[1]Pricing '!$A$167:$K$191,11,FALSE) -> 7.3836638 | AB67: =AA67-$U$2 -> 7.5086638 | AC67: =AC66-0.125 -> 4.875 | AD67: =100-VLOOKUP(AC67,'[1]Pricing '!$A$674:$K$698,11,FALSE) -> 6.6016623 | AE67: =AD67-$U$2 -> 6.7266623 | AF67: =AF66-0.125 -> 4.5 | AG67: =100-VLOOKUP(AF67,'[1]Pricing '!$A$194:$K$218,11,FALSE) -> 4.6385388 | AH67: =AG67-$U$2 -> 4.7635388 | AI67: =AI66-0.125 -> 4.5 | AJ67: =100-VLOOKUP(AI67,'[1]Pricing '!$A$701:$K$725,11,FALSE) -> 4.6385388 | AK67: =AJ67-$U$2 -> 4.7635388
N69: AFFORDABLE PRODUCTS (FANNIE MAE & FREDDIE MAC)
B70: REFINOW | K70: HOMEONE
B71: (FCF30 RN) 30 YEAR | E71: (FCF15 RN) 15 YEAR | K71: (FM30HO) 30 YEAR | N71: (FM15HO) 15 YEAR
B72: RATE | C72: 30 Days | D72: 45 days | E72: RATE | F72: 30 Days | G72: 45 days | K72: RATE | L72: 30 Days | M72: 45 days | N72: RATE | O72: 30 Days | P72: 45 days
B73: =LARGE('[1]Pricing '!$A$3347:$A$3371,1) -> 7.75 | C73: =100-VLOOKUP(B73,'[1]Pricing '!$A$3347:$K$3371,11,FALSE) -> -4.3010265 | D73: =C73-$U$2 -> -4.1760265 | E73: =LARGE('[1]Pricing '!$A$86:$A$110,1) -> 7 | F73: =100-VLOOKUP(E73,'[1]Pricing '!$A$86:$K$110,11,FALSE) -> -3.2350398 | G73: =F73-$U$2 -> -3.1100398 | K73: =LARGE('[1]Pricing '!$A$3404:$A$3428,1) -> 7.875 | L73: =100-VLOOKUP(K73,'[1]Pricing '!$A$3404:$K$3428,11,FALSE) -> -4.250331 | M73: =L73-$U$2 -> -4.125331 | N73: =LARGE('[1]Pricing '!$A$3431:$A$3456,1) -> 7 | O73: =100-VLOOKUP(N73,'[1]Pricing '!$A$3431:$K$3456,11,FALSE) -> -2.9850398 | P73: =O73-$U$2 -> -2.8600398
B74: =B73-0.125 -> 7.625 | C74: =100-VLOOKUP(B74,'[1]Pricing '!$A$3347:$K$3371,11,FALSE) -> -4.3356203 | D74: =C74-$U$2 -> -4.2106203 | E74: =E73-0.125 -> 6.875 | F74: =100-VLOOKUP(E74,'[1]Pricing '!$A$86:$K$110,11,FALSE) -> -3.0143409 | G74: =F74-$U$2 -> -2.8893409 | K74: =K73-0.125 -> 7.75 | L74: =100-VLOOKUP(K74,'[1]Pricing '!$A$3404:$K$3428,11,FALSE) -> -3.9891265 | M74: =L74-$U$2 -> -3.8641265 | N74: =N73-0.125 -> 6.875 | O74: =100-VLOOKUP(N74,'[1]Pricing '!$A$3431:$K$3456,11,FALSE) -> -2.7643409 | P74: =O74-$U$2 -> -2.6393409
B75: =B74-0.125 -> 7.5 | C75: =100-VLOOKUP(B75,'[1]Pricing '!$A$3347:$K$3371,11,FALSE) -> -4.109106 | D75: =C75-$U$2 -> -3.984106 | E75: =E74-0.125 -> 6.75 | F75: =100-VLOOKUP(E75,'[1]Pricing '!$A$86:$K$110,11,FALSE) -> -2.7662591 | G75: =F75-$U$2 -> -2.6412591 | K75: =K74-0.125 -> 7.625 | L75: =100-VLOOKUP(K75,'[1]Pricing '!$A$3404:$K$3428,11,FALSE) -> -4.0257203 | M75: =L75-$U$2 -> -3.9007203 | N75: =N74-0.125 -> 6.75 | O75: =100-VLOOKUP(N75,'[1]Pricing '!$A$3431:$K$3456,11,FALSE) -> -2.5162591 | P75: =O75-$U$2 -> -2.3912591
B76: =B75-0.125 -> 7.375 | C76: =100-VLOOKUP(B76,'[1]Pricing '!$A$3347:$K$3371,11,FALSE) -> -3.8406794 | D76: =C76-$U$2 -> -3.7156794 | E76: =E75-0.125 -> 6.625 | F76: =100-VLOOKUP(E76,'[1]Pricing '!$A$86:$K$110,11,FALSE) -> -2.5121048 | G76: =F76-$U$2 -> -2.3871048 | K76: =K75-0.125 -> 7.5 | L76: =100-VLOOKUP(K76,'[1]Pricing '!$A$3404:$K$3428,11,FALSE) -> -3.817206 | M76: =L76-$U$2 -> -3.692206 | N76: =N75-0.125 -> 6.625 | O76: =100-VLOOKUP(N76,'[1]Pricing '!$A$3431:$K$3456,11,FALSE) -> -2.2621048 | P76: =O76-$U$2 -> -2.1371048
B77: =B76-0.125 -> 7.25 | C77: =100-VLOOKUP(B77,'[1]Pricing '!$A$3347:$K$3371,11,FALSE) -> -3.6941232 | D77: =C77-$U$2 -> -3.5691232 | E77: =E76-0.125 -> 6.5 | F77: =100-VLOOKUP(E77,'[1]Pricing '!$A$86:$K$110,11,FALSE) -> -2.3369705 | G77: =F77-$U$2 -> -2.2119705 | K77: =K76-0.125 -> 7.375 | L77: =100-VLOOKUP(K77,'[1]Pricing '!$A$3404:$K$3428,11,FALSE) -> -3.5477794 | M77: =L77-$U$2 -> -3.4227794 | N77: =N76-0.125 -> 6.5 | O77: =100-VLOOKUP(N77,'[1]Pricing '!$A$3431:$K$3456,11,FALSE) -> -2.0869705 | P77: =O77-$U$2 -> -1.9619705
B78: =B77-0.125 -> 7.125 | C78: =100-VLOOKUP(B78,'[1]Pricing '!$A$3347:$K$3371,11,FALSE) -> -3.3120343 | D78: =C78-$U$2 -> -3.1870343 | E78: =E77-0.125 -> 6.375 | F78: =100-VLOOKUP(E78,'[1]Pricing '!$A$86:$K$110,11,FALSE) -> -2.0965438 | G78: =F78-$U$2 -> -1.9715438 | K78: =K77-0.125 -> 7.25 | L78: =100-VLOOKUP(K78,'[1]Pricing '!$A$3404:$K$3428,11,FALSE) -> -3.0692232 | M78: =L78-$U$2 -> -2.9442232 | N78: =N77-0.125 -> 6.375 | O78: =100-VLOOKUP(N78,'[1]Pricing '!$A$3431:$K$3456,11,FALSE) -> -1.8465438 | P78: =O78-$U$2 -> -1.7215438
B79: =B78-0.125 -> 7 | C79: =100-VLOOKUP(B79,'[1]Pricing '!$A$3347:$K$3371,11,FALSE) -> -3.0116188 | D79: =C79-$U$2 -> -2.8866188 | E79: =E78-0.125 -> 6.25 | F79: =100-VLOOKUP(E79,'[1]Pricing '!$A$86:$K$110,11,FALSE) -> -1.8050742 | G79: =F79-$U$2 -> -1.6800742 | K79: =K78-0.125 -> 7.125 | L79: =100-VLOOKUP(K79,'[1]Pricing '!$A$3404:$K$3428,11,FALSE) -> -2.8556343 | M79: =L79-$U$2 -> -2.7306343 | N79: =N78-0.125 -> 6.25 | O79: =100-VLOOKUP(N79,'[1]Pricing '!$A$3431:$K$3456,11,FALSE) -> -1.5550742 | P79: =O79-$U$2 -> -1.4300742
B80: =B79-0.125 -> 6.875 | C80: =100-VLOOKUP(B80,'[1]Pricing '!$A$3347:$K$3371,11,FALSE) -> -2.6455371 | D80: =C80-$U$2 -> -2.5205371 | E80: =E79-0.125 -> 6.125 | F80: =100-VLOOKUP(E80,'[1]Pricing '!$A$86:$K$110,11,FALSE) -> -1.4699316 | G80: =F80-$U$2 -> -1.3449316 | K80: =K79-0.125 -> 7 | L80: =100-VLOOKUP(K80,'[1]Pricing '!$A$3404:$K$3428,11,FALSE) -> -2.5284188 | M80: =L80-$U$2 -> -2.4034188 | N80: =N79-0.125 -> 6.125 | O80: =100-VLOOKUP(N80,'[1]Pricing '!$A$3431:$K$3456,11,FALSE) -> -1.2199316 | P80: =O80-$U$2 -> -1.0949316
B81: =B80-0.125 -> 6.75 | C81: =100-VLOOKUP(B81,'[1]Pricing '!$A$3347:$K$3371,11,FALSE) -> -2.2252354 | D81: =C81-$U$2 -> -2.1002354 | E81: =E80-0.125 -> 6 | F81: =100-VLOOKUP(E81,'[1]Pricing '!$A$86:$K$110,11,FALSE) -> -1.2045454 | G81: =F81-$U$2 -> -1.0795454 | K81: =K80-0.125 -> 6.875 | L81: =100-VLOOKUP(K81,'[1]Pricing '!$A$3404:$K$3428,11,FALSE) -> -2.0666371 | M81: =L81-$U$2 -> -1.9416371 | N81: =N80-0.125 -> 6 | O81: =100-VLOOKUP(N81,'[1]Pricing '!$A$3431:$K$3456,11,FALSE) -> -0.95454537 | P81: =O81-$U$2 -> -0.82954537
B82: =B81-0.125 -> 6.625 | C82: =100-VLOOKUP(B82,'[1]Pricing '!$A$3347:$K$3371,11,FALSE) -> -1.7969419 | D82: =C82-$U$2 -> -1.6719419 | E82: =E81-0.125 -> 5.875 | F82: =100-VLOOKUP(E82,'[1]Pricing '!$A$86:$K$110,11,FALSE) -> -0.93241865 | G82: =F82-$U$2 -> -0.80741865 | K82: =K81-0.125 -> 6.75 | L82: =100-VLOOKUP(K82,'[1]Pricing '!$A$3404:$K$3428,11,FALSE) -> -1.5260354 | M82: =L82-$U$2 -> -1.4010354 | N82: =N81-0.125 -> 5.875 | O82: =100-VLOOKUP(N82,'[1]Pricing '!$A$3431:$K$3456,11,FALSE) -> -0.68241865 | P82: =O82-$U$2 -> -0.55741865
B83: =B82-0.125 -> 6.5 | C83: =100-VLOOKUP(B83,'[1]Pricing '!$A$3347:$K$3371,11,FALSE) -> -1.366058 | D83: =C83-$U$2 -> -1.241058 | E83: =E82-0.125 -> 5.75 | F83: =100-VLOOKUP(E83,'[1]Pricing '!$A$86:$K$110,11,FALSE) -> -0.5290574 | G83: =F83-$U$2 -> -0.4040574 | K83: =K82-0.125 -> 6.625 | L83: =100-VLOOKUP(K83,'[1]Pricing '!$A$3404:$K$3428,11,FALSE) -> -1.3501419 | M83: =L83-$U$2 -> -1.2251419 | N83: =N82-0.125 -> 5.75 | O83: =100-VLOOKUP(N83,'[1]Pricing '!$A$3431:$K$3456,11,FALSE) -> -0.2790574 | P83: =O83-$U$2 -> -0.1540574
B84: =B83-0.125 -> 6.375 | C84: =100-VLOOKUP(B84,'[1]Pricing '!$A$3347:$K$3371,11,FALSE) -> -0.94347311 | D84: =C84-$U$2 -> -0.81847311 | E84: =E83-0.125 -> 5.625 | F84: =100-VLOOKUP(E84,'[1]Pricing '!$A$86:$K$110,11,FALSE) -> -0.19157641 | G84: =F84-$U$2 -> -0.066576413 | K84: =K83-0.125 -> 6.5 | L84: =100-VLOOKUP(K84,'[1]Pricing '!$A$3404:$K$3428,11,FALSE) -> -0.97855797 | M84: =L84-$U$2 -> -0.85355797 | N84: =N83-0.125 -> 5.625 | O84: =100-VLOOKUP(N84,'[1]Pricing '!$A$3431:$K$3456,11,FALSE) -> 0.058423587 | P84: =O84-$U$2 -> 0.18342359
B85: =B84-0.125 -> 6.25 | C85: =100-VLOOKUP(B85,'[1]Pricing '!$A$3347:$K$3371,11,FALSE) -> -0.50613415 | D85: =C85-$U$2 -> -0.38113415 | E85: =E84-0.125 -> 5.5 | F85: =100-VLOOKUP(E85,'[1]Pricing '!$A$86:$K$110,11,FALSE) -> 0.13124288 | G85: =F85-$U$2 -> 0.25624288 | K85: =K84-0.125 -> 6.375 | L85: =100-VLOOKUP(K85,'[1]Pricing '!$A$3404:$K$3428,11,FALSE) -> -0.64657311 | M85: =L85-$U$2 -> -0.52157311 | N85: =N84-0.125 -> 5.5 | O85: =100-VLOOKUP(N85,'[1]Pricing '!$A$3431:$K$3456,11,FALSE) -> 0.38124288 | P85: =O85-$U$2 -> 0.50624288
... B97: =B96-0.125 -> 4.75 | C97: =100-VLOOKUP(B97,'[1]Pricing '!$A$3347:$K$3371,11,FALSE) -> 6.1001774 | D97: =C97-$U$2 -> 6.2251774 | E97: =E96-0.125 -> 4 | F97: =100-VLOOKUP(E97,'[1]Pricing '!$A$86:$K$110,11,FALSE) -> 3.5834823 | G97: =F97-$U$2 -> 3.7084823 | K97: =K96-0.125 -> 4.875 | L97: =100-VLOOKUP(K97,'[1]Pricing '!$A$3404:$K$3428,11,FALSE) -> 5.9169012 | M97: =L97-$U$2 -> 6.0419012 | N97: =N96-0.125 -> 4 | O97: =100-VLOOKUP(N97,'[1]Pricing '!$A$3431:$K$3456,11,FALSE) -> 3.8334823 | P97: =O97-$U$2 -> 3.9584823
B100: ARMS
B101: CONFORMING ARMS | O101: CONFORMING ARMS | AC101: HB ARMS
B102: (FM5/6) 5YR ARM | E102: (FM7/6) 7YR ARM | H102: (FM10/6) 10YR ARM | O102: (CA5/6) 5YR ARM | R102: (CA7/6) 7YR ARM | U102: (CA10/6) 10YR ARM | AC102: (CA5/6HB) HB 5YR ARM | AF102: (CA7/6HB) HB 7YR ARM | AI102: (CA10/6HB) HB 10YR ARM
B103: RATE | C103: 30 Days | D103: 45 days | E103: RATE | F103: 30 Days | G103: 45 days | H103: RATE | I103: 30 Days | J103: 45 days | O103: RATE | P103: 30 Days | Q103: 45 days | R103: RATE | S103: 30 Days | T103: 45 days | U103: RATE | V103: 30 Days | W103: 45 days | AC103: RATE | AD103: 30 Days | AE103: 45 days | AF103: RATE | AG103: 30 Days | AH103: 45 days | AI103: RATE | AJ103: 30 Days | AK103: 45 days
B104: =LARGE('[1]Pricing '!$A$419:$A$438,1) -> 7.5 | C104: =100-VLOOKUP(B104,'[1]Pricing '!$A$419:$K$438,11,FALSE) -> -1.8771161 | D104: =C104-$U$2 -> -1.7521161 | E104: =LARGE('[1]Pricing '!$A$441:$A$460,1) -> 7.5 | F104: =100-VLOOKUP(E104,'[1]Pricing '!$A$441:$K$460,11,FALSE) -> -1.421829 | G104: =F104-$U$2 -> -1.296829 | H104: =LARGE('[1]Pricing '!$A$463:$A$482,1) -> 7.5 | I104: =100-VLOOKUP(H104,'[1]Pricing '!$A$463:$K$482,11,FALSE) -> -0.10092871 | J104: =I104-$U$2 -> 0.024071289 | O104: =LARGE('[1]Pricing '!$A$221:$A$240,1) -> 7.5 | P104: =100-VLOOKUP(O104,'[1]Pricing '!$A$221:$K$240,11,FALSE) -> -1.3693032 | Q104: =P104-$U$2 -> -1.2443032 | R104: =LARGE('[1]Pricing '!$A$243:$A$262,1) -> 7.5 | S104: =100-VLOOKUP(R104,'[1]Pricing '!$A$243:$K$262,11,FALSE) -> -1.873018 | T104: =S104-$U$2 -> -1.748018 | U104: =LARGE('[1]Pricing '!$A$265:$A$284,1) -> 7.5 | V104: =100-VLOOKUP(U104,'[1]Pricing '!$A$265:$K$284,11,FALSE) -> -1.4578674 | W104: =V104-$U$2 -> -1.3328674 | AC104: =LARGE('[1]Pricing '!$A$287:$A$306,1) -> 7.625 | AD104: =100-VLOOKUP(AC104,'[1]Pricing '!$A$287:$K$306,11,FALSE) -> -1.0323449 | AE104: =AD104-$U$2 -> -0.90734493 | AF104: =LARGE('[1]Pricing '!$A$309:$A$328,1) -> 7.625 | AG104: =100-VLOOKUP(AF104,'[1]Pricing '!$A$309:$K$328,11,FALSE) -> -1.5795413 | AH104: =AG104-$U$2 -> -1.4545413 | AI104: =LARGE('[1]Pricing '!$A$331:$A$350,1) -> 7.5 | AJ104: =100-VLOOKUP(AI104,'[1]Pricing '!$A$331:$K$350,11,FALSE) -> -1.0382798 | AK104: =AJ104-$U$2 -> -0.91327978
B105: =B104-0.125 -> 7.375 | C105: =100-VLOOKUP(B105,'[1]Pricing '!$A$419:$K$438,11,FALSE) -> -1.680801 | D105: =C105-$U$2 -> -1.555801 | E105: =E104-0.125 -> 7.375 | F105: =100-VLOOKUP(E105,'[1]Pricing '!$A$441:$K$460,11,FALSE) -> -1.470218 | G105: =F105-$U$2 -> -1.345218 | H105: =H104-0.125 -> 7.375 | I105: =100-VLOOKUP(H105,'[1]Pricing '!$A$463:$K$482,11,FALSE) -> -0.086067352 | J105: =I105-$U$2 -> 0.038932648 | O105: =O104-0.125 -> 7.375 | P105: =100-VLOOKUP(O105,'[1]Pricing '!$A$221:$K$240,11,FALSE) -> -1.380415 | Q105: =P105-$U$2 -> -1.255415 | R105: =R104-0.125 -> 7.375 | S105: =100-VLOOKUP(R105,'[1]Pricing '!$A$243:$K$262,11,FALSE) -> -1.8052883 | T105: =S105-$U$2 -> -1.6802883 | U105: =U104-0.125 -> 7.375 | V105: =100-VLOOKUP(U105,'[1]Pricing '!$A$265:$K$284,11,FALSE) -> -1.4367517 | W105: =V105-$U$2 -> -1.3117517 | AC105: =AC104-0.125 -> 7.5 | AD105: =100-VLOOKUP(AC105,'[1]Pricing '!$A$287:$K$306,11,FALSE) -> -1.0429017 | AE105: =AD105-$U$2 -> -0.91790166 | AF105: =AF104-0.125 -> 7.5 | AG105: =100-VLOOKUP(AF105,'[1]Pricing '!$A$309:$K$328,11,FALSE) -> -1.5429834 | AH105: =AG105-$U$2 -> -1.4179834 | AI105: =AI104-0.125 -> 7.375 | AJ105: =100-VLOOKUP(AI105,'[1]Pricing '!$A$331:$K$350,11,FALSE) -> -1.0172082 | AK105: =AJ105-$U$2 -> -0.89220818
B106: =B105-0.125 -> 7.25 | C106: =100-VLOOKUP(B106,'[1]Pricing '!$A$419:$K$438,11,FALSE) -> -1.4979032 | D106: =C106-$U$2 -> -1.3729032 | E106: =E105-0.125 -> 7.25 | F106: =100-VLOOKUP(E106,'[1]Pricing '!$A$441:$K$460,11,FALSE) -> -1.4998883 | G106: =F106-$U$2 -> -1.3748883 | H106: =H105-0.125 -> 7.25 | I106: =100-VLOOKUP(H106,'[1]Pricing '!$A$463:$K$482,11,FALSE) -> -0.057851724 | J106: =I106-$U$2 -> 0.067148276 | O106: =O105-0.125 -> 7.25 | P106: =100-VLOOKUP(O106,'[1]Pricing '!$A$221:$K$240,11,FALSE) -> -1.4004055 | Q106: =P106-$U$2 -> -1.2754055 | R106: =R105-0.125 -> 7.25 | S106: =100-VLOOKUP(R106,'[1]Pricing '!$A$243:$K$262,11,FALSE) -> -1.7272829 | T106: =S106-$U$2 -> -1.6022829 | U106: =U105-0.125 -> 7.25 | V106: =100-VLOOKUP(U106,'[1]Pricing '!$A$265:$K$284,11,FALSE) -> -1.4087359 | W106: =V106-$U$2 -> -1.2837359 | AC106: =AC105-0.125 -> 7.375 | AD106: =100-VLOOKUP(AC106,'[1]Pricing '!$A$287:$K$306,11,FALSE) -> -1.0537067 | AE106: =AD106-$U$2 -> -0.9287067 | AF106: =AF105-0.125 -> 7.375 | AG106: =100-VLOOKUP(AF106,'[1]Pricing '!$A$309:$K$328,11,FALSE) -> -1.4746818 | AH106: =AG106-$U$2 -> -1.3496818 | AI106: =AI105-0.125 -> 7.25 | AJ106: =100-VLOOKUP(AI106,'[1]Pricing '!$A$331:$K$350,11,FALSE) -> -0.98915242 | AK106: =AJ106-$U$2 -> -0.86415242
B107: =B106-0.125 -> 7.125 | C107: =100-VLOOKUP(B107,'[1]Pricing '!$A$419:$K$438,11,FALSE) -> -1.468615 | D107: =C107-$U$2 -> -1.343615 | E107: =E106-0.125 -> 7.125 | F107: =100-VLOOKUP(E107,'[1]Pricing '!$A$441:$K$460,11,FALSE) -> -1.5966829 | G107: =F107-$U$2 -> -1.4716829 | H107: =H106-0.125 -> 7.125 | I107: =100-VLOOKUP(H107,'[1]Pricing '!$A$463:$K$482,11,FALSE) -> -0.30783593 | J107: =I107-$U$2 -> -0.18283593 | O107: =O106-0.125 -> 7.125 | P107: =100-VLOOKUP(O107,'[1]Pricing '!$A$221:$K$240,11,FALSE) -> -1.4058097 | Q107: =P107-$U$2 -> -1.2808097 | R107: =R106-0.125 -> 7.125 | S107: =100-VLOOKUP(R107,'[1]Pricing '!$A$243:$K$262,11,FALSE) -> -1.5782491 | T107: =S107-$U$2 -> -1.4532491 | U107: =U106-0.125 -> 7.125 | V107: =100-VLOOKUP(U107,'[1]Pricing '!$A$265:$K$284,11,FALSE) -> -1.3939609 | W107: =V107-$U$2 -> -1.2689609 | AC107: =AC106-0.125 -> 7.25 | AD107: =100-VLOOKUP(AC107,'[1]Pricing '!$A$287:$K$306,11,FALSE) -> -1.0734562 | AE107: =AD107-$U$2 -> -0.94845621 | AF107: =AF106-0.125 -> 7.25 | AG107: =100-VLOOKUP(AF107,'[1]Pricing '!$A$309:$K$328,11,FALSE) -> -1.3962604 | AH107: =AG107-$U$2 -> -1.2712604 | AI107: =AI106-0.125 -> 7.125 | AJ107: =100-VLOOKUP(AI107,'[1]Pricing '!$A$331:$K$350,11,FALSE) -> -0.97442351 | AK107: =AJ107-$U$2 -> -0.84942351
B108: =B107-0.125 -> 7 | C108: =100-VLOOKUP(B108,'[1]Pricing '!$A$419:$K$438,11,FALSE) -> -1.5338055 | D108: =C108-$U$2 -> -1.4088055 | E108: =E107-0.125 -> 7 | F108: =100-VLOOKUP(E108,'[1]Pricing '!$A$441:$K$460,11,FALSE) -> -1.7296491 | G108: =F108-$U$2 -> -1.6046491 | H108: =H107-0.125 -> 7 | I108: =100-VLOOKUP(H108,'[1]Pricing '!$A$463:$K$482,11,FALSE) -> -0.71406086 | J108: =I108-$U$2 -> -0.58906086 | O108: =O107-0.125 -> 7 | P108: =100-VLOOKUP(O108,'[1]Pricing '!$A$221:$K$240,11,FALSE) -> -1.412409 | Q108: =P108-$U$2 -> -1.287409 | R108: =R107-0.125 -> 7 | S108: =100-VLOOKUP(R108,'[1]Pricing '!$A$243:$K$262,11,FALSE) -> -1.3954257 | T108: =S108-$U$2 -> -1.2704257 | U108: =U107-0.125 -> 7 | V108: =100-VLOOKUP(U108,'[1]Pricing '!$A$265:$K$284,11,FALSE) -> -1.3978822 | W108: =V108-$U$2 -> -1.2728822 | AC108: =AC107-0.125 -> 7.125 | AD108: =100-VLOOKUP(AC108,'[1]Pricing '!$A$287:$K$306,11,FALSE) -> -1.0787099 | AE108: =AD108-$U$2 -> -0.95370991 | AF108: =AF107-0.125 -> 7.125 | AG108: =100-VLOOKUP(AF108,'[1]Pricing '!$A$309:$K$328,11,FALSE) -> -1.246981 | AH108: =AG108-$U$2 -> -1.121981 | AI108: =AI107-0.125 -> 7 | AJ108: =100-VLOOKUP(AI108,'[1]Pricing '!$A$331:$K$350,11,FALSE) -> -0.97841525 | AK108: =AJ108-$U$2 -> -0.85341525
B109: =B108-0.125 -> 6.875 | C109: =100-VLOOKUP(B109,'[1]Pricing '!$A$419:$K$438,11,FALSE) -> -1.5994097 | D109: =C109-$U$2 -> -1.4744097 | E109: =E108-0.125 -> 6.875 | F109: =100-VLOOKUP(E109,'[1]Pricing '!$A$441:$K$460,11,FALSE) -> -1.9048257 | G109: =F109-$U$2 -> -1.7798257 | H109: =H108-0.125 -> 6.875 | I109: =100-VLOOKUP(H109,'[1]Pricing '!$A$463:$K$482,11,FALSE) -> -1.1295822 | J109: =I109-$U$2 -> -1.0045822 | O109: =O108-0.125 -> 6.875 | P109: =100-VLOOKUP(O109,'[1]Pricing '!$A$221:$K$240,11,FALSE) -> -1.4112903 | Q109: =P109-$U$2 -> -1.2862903 | R109: =R108-0.125 -> 6.875 | S109: =100-VLOOKUP(R109,'[1]Pricing '!$A$243:$K$262,11,FALSE) -> -1.272 | T109: =S109-$U$2 -> -1.147 | U109: =U108-0.125 -> 6.875 | V109: =100-VLOOKUP(U109,'[1]Pricing '!$A$265:$K$284,11,FALSE) -> -1.386047 | W109: =V109-$U$2 -> -1.261047 | AC109: =AC108-0.125 -> 7 | AD109: =100-VLOOKUP(AC109,'[1]Pricing '!$A$287:$K$306,11,FALSE) -> -1.0850755 | AE109: =AD109-$U$2 -> -0.96007552 | AF109: =AF108-0.125 -> 7 | AG109: =100-VLOOKUP(AF109,'[1]Pricing '!$A$309:$K$328,11,FALSE) -> -1.0636496 | AH109: =AG109-$U$2 -> -0.93864957 | AI109: =AI108-0.125 -> 6.875 | AJ109: =100-VLOOKUP(AI109,'[1]Pricing '!$A$331:$K$350,11,FALSE) -> -0.96682045 | AK109: =AJ109-$U$2 -> -0.84182045
B110: =B109-0.125 -> 6.75 | C110: =100-VLOOKUP(B110,'[1]Pricing '!$A$419:$K$438,11,FALSE) -> -1.674609 | D110: =C110-$U$2 -> -1.549609 | E110: =E109-0.125 -> 6.75 | F110: =100-VLOOKUP(E110,'[1]Pricing '!$A$441:$K$460,11,FALSE) -> -2.0443 | G110: =F110-$U$2 -> -1.9193 | H110: =H109-0.125 -> 6.75 | I110: =100-VLOOKUP(H110,'[1]Pricing '!$A$463:$K$482,11,FALSE) -> -1.534147 | J110: =I110-$U$2 -> -1.409147 | O110: =O109-0.125 -> 6.75 | P110: =100-VLOOKUP(O110,'[1]Pricing '!$A$221:$K$240,11,FALSE) -> -1.412735 | Q110: =P110-$U$2 -> -1.287735 | R110: =R109-0.125 -> 6.75 | S110: =100-VLOOKUP(R110,'[1]Pricing '!$A$243:$K$262,11,FALSE) -> -1.1978748 | T110: =S110-$U$2 -> -1.0728748 | U110: =U109-0.125 -> 6.75 | V110: =100-VLOOKUP(U110,'[1]Pricing '!$A$265:$K$284,11,FALSE) -> -1.3708509 | W110: =V110-$U$2 -> -1.2458509 | AC110: =AC109-0.125 -> 6.875 | AD110: =100-VLOOKUP(AC110,'[1]Pricing '!$A$287:$K$306,11,FALSE) -> -1.0839711 | AE110: =AD110-$U$2 -> -0.95897109 | AF110: =AF109-0.125 -> 6.875 | AG110: =100-VLOOKUP(AF110,'[1]Pricing '!$A$309:$K$328,11,FALSE) -> -0.94025016 | AH110: =AG110-$U$2 -> -0.81525016 | AI110: =AI109-0.125 -> 6.75 | AJ110: =100-VLOOKUP(AI110,'[1]Pricing '!$A$331:$K$350,11,FALSE) -> -0.95190066 | AK110: =AJ110-$U$2 -> -0.82690066
B111: =B110-0.125 -> 6.625 | C111: =100-VLOOKUP(B111,'[1]Pricing '!$A$419:$K$438,11,FALSE) -> -1.6744903 | D111: =C111-$U$2 -> -1.5494903 | E111: =E110-0.125 -> 6.625 | F111: =100-VLOOKUP(E111,'[1]Pricing '!$A$441:$K$460,11,FALSE) -> -1.8910748 | G111: =F111-$U$2 -> -1.7660748 | H111: =H110-0.125 -> 6.625 | I111: =100-VLOOKUP(H111,'[1]Pricing '!$A$463:$K$482,11,FALSE) -> -1.6103509 | J111: =I111-$U$2 -> -1.4853509 | O111: =O110-0.125 -> 6.625 | P111: =100-VLOOKUP(O111,'[1]Pricing '!$A$221:$K$240,11,FALSE) -> -1.3667035 | Q111: =P111-$U$2 -> -1.2417035 | R111: =R110-0.125 -> 6.625 | S111: =100-VLOOKUP(R111,'[1]Pricing '!$A$243:$K$262,11,FALSE) -> -1.085459 | T111: =S111-$U$2 -> -0.96045899 | U111: =U110-0.125 -> 6.625 | V111: =100-VLOOKUP(U111,'[1]Pricing '!$A$265:$K$284,11,FALSE) -> -1.2664158 | W111: =V111-$U$2 -> -1.1414158 | AC111: =AC110-0.125 -> 6.75 | AD111: =100-VLOOKUP(AC111,'[1]Pricing '!$A$287:$K$306,11,FALSE) -> -1.0855362 | AE111: =AD111-$U$2 -> -0.96053621 | AF111: =AF110-0.125 -> 6.75 | AG111: =100-VLOOKUP(AF111,'[1]Pricing '!$A$309:$K$328,11,FALSE) -> -0.86613766 | AH111: =AG111-$U$2 -> -0.74113766 | AI111: =AI110-0.125 -> 6.625 | AJ111: =100-VLOOKUP(AI111,'[1]Pricing '!$A$331:$K$350,11,FALSE) -> -0.84775116 | AK111: =AJ111-$U$2 -> -0.72275116
B112: =B111-0.125 -> 6.5 | C112: =100-VLOOKUP(B112,'[1]Pricing '!$A$419:$K$438,11,FALSE) -> -1.638735 | D112: =C112-$U$2 -> -1.513735 | E112: =E111-0.125 -> 6.5 | F112: =100-VLOOKUP(E112,'[1]Pricing '!$A$441:$K$460,11,FALSE) -> -1.725159 | G112: =F112-$U$2 -> -1.600159 | H112: =H111-0.125 -> 6.5 | I112: =100-VLOOKUP(H112,'[1]Pricing '!$A$463:$K$482,11,FALSE) -> -1.5024158 | J112: =I112-$U$2 -> -1.3774158 | O112: =O111-0.125 -> 6.5 | P112: =100-VLOOKUP(O112,'[1]Pricing '!$A$221:$K$240,11,FALSE) -> -1.2970811 | Q112: =P112-$U$2 -> -1.1720811 | R112: =R111-0.125 -> 6.5 | S112: =100-VLOOKUP(R112,'[1]Pricing '!$A$243:$K$262,11,FALSE) -> -0.95866036 | T112: =S112-$U$2 -> -0.83366036 | U112: =U111-0.125 -> 6.5 | V112: =100-VLOOKUP(U112,'[1]Pricing '!$A$265:$K$284,11,FALSE) -> -1.1118526 | W112: =V112-$U$2 -> -0.98685261 | AC112: =AC111-0.125 -> 6.625 | AD112: =100-VLOOKUP(AC112,'[1]Pricing '!$A$287:$K$306,11,FALSE) -> -1.0395955 | AE112: =AD112-$U$2 -> -0.91459549 | AF112: =AF111-0.125 -> 6.625 | AG112: =100-VLOOKUP(AF112,'[1]Pricing '!$A$309:$K$328,11,FALSE) -> -0.75388691 | AH112: =AG112-$U$2 -> -0.62888691 | AI112: =AI111-0.125 -> 6.5 | AJ112: =100-VLOOKUP(AI112,'[1]Pricing '!$A$331:$K$350,11,FALSE) -> -0.69357534 | AK112: =AJ112-$U$2 -> -0.56857534
B113: =B112-0.125 -> 6.375 | C113: =100-VLOOKUP(B113,'[1]Pricing '!$A$419:$K$438,11,FALSE) -> -1.6024035 | D113: =C113-$U$2 -> -1.4774035 | E113: =E112-0.125 -> 6.375 | F113: =100-VLOOKUP(E113,'[1]Pricing '!$A$441:$K$460,11,FALSE) -> -1.5617604 | G113: =F113-$U$2 -> -1.4367604 | H113: =H112-0.125 -> 6.375 | I113: =100-VLOOKUP(H113,'[1]Pricing '!$A$463:$K$482,11,FALSE) -> -1.4027526 | J113: =I113-$U$2 -> -1.2777526 | O113: =O112-0.125 -> 6.375 | P113: =100-VLOOKUP(O113,'[1]Pricing '!$A$221:$K$240,11,FALSE) -> -1.1988541 | Q113: =P113-$U$2 -> -1.0738541 | R113: =R112-0.125 -> 6.375 | S113: =100-VLOOKUP(R113,'[1]Pricing '!$A$243:$K$262,11,FALSE) -> -0.85669182 | T113: =S113-$U$2 -> -0.73169182 | U113: =U112-0.125 -> 6.375 | V113: =100-VLOOKUP(U113,'[1]Pricing '!$A$265:$K$284,11,FALSE) -> -0.93405185 | W113: =V113-$U$2 -> -0.80905185 | AC113: =AC112-0.125 -> 6.5 | AD113: =100-VLOOKUP(AC113,'[1]Pricing '!$A$287:$K$306,11,FALSE) -> -0.9701749 | AE113: =AD113-$U$2 -> -0.8451749 | AF113: =AF112-0.125 -> 6.5 | AG113: =100-VLOOKUP(AF113,'[1]Pricing '!$A$309:$K$328,11,FALSE) -> -0.62729334 | AH113: =AG113-$U$2 -> -0.50229334 | AI113: =AI112-0.125 -> 6.375 | AJ113: =100-VLOOKUP(AI113,'[1]Pricing '!$A$331:$K$350,11,FALSE) -> -0.51610943 | AK113: =AJ113-$U$2 -> -0.39110943
B114: =B113-0.125 -> 6.25 | C114: =100-VLOOKUP(B114,'[1]Pricing '!$A$419:$K$438,11,FALSE) -> -1.5736811 | D114: =C114-$U$2 -> -1.4486811 | E114: =E113-0.125 -> 6.25 | F114: =100-VLOOKUP(E114,'[1]Pricing '!$A$441:$K$460,11,FALSE) -> -1.3707918 | G114: =F114-$U$2 -> -1.2457918 | H114: =H113-0.125 -> 6.25 | I114: =100-VLOOKUP(H114,'[1]Pricing '!$A$463:$K$482,11,FALSE) -> -1.2938519 | J114: =I114-$U$2 -> -1.1688519 | O114: =O113-0.125 -> 6.25 | P114: =100-VLOOKUP(O114,'[1]Pricing '!$A$221:$K$240,11,FALSE) -> -1.086758 | Q114: =P114-$U$2 -> -0.96175803 | R114: =R113-0.125 -> 6.25 | S114: =100-VLOOKUP(R114,'[1]Pricing '!$A$243:$K$262,11,FALSE) -> -0.77818396 | T114: =S114-$U$2 -> -0.65318396 | U114: =U113-0.125 -> 6.25 | V114: =100-VLOOKUP(U114,'[1]Pricing '!$A$265:$K$284,11,FALSE) -> -0.74634108 | W114: =V114-$U$2 -> -0.62134108 | AC114: =AC113-0.125 -> 6.375 | AD114: =100-VLOOKUP(AC114,'[1]Pricing '!$A$287:$K$306,11,FALSE) -> -0.87219466 | AE114: =AD114-$U$2 -> -0.74719466 | AF114: =AF113-0.125 -> 6.375 | AG114: =100-VLOOKUP(AF114,'[1]Pricing '!$A$309:$K$328,11,FALSE) -> -0.52561103 | AH114: =AG114-$U$2 -> -0.40061103 | AI114: =AI113-0.125 -> 6.25 | AJ114: =100-VLOOKUP(AI114,'[1]Pricing '!$A$331:$K$350,11,FALSE) -> -0.32875042 | AK114: =AJ114-$U$2 -> -0.20375042
B115: =B114-0.125 -> 6.125 | C115: =100-VLOOKUP(B115,'[1]Pricing '!$A$419:$K$438,11,FALSE) -> -1.3731541 | D115: =C115-$U$2 -> -1.2481541 | E115: =E114-0.125 -> 6.125 | F115: =100-VLOOKUP(E115,'[1]Pricing '!$A$441:$K$460,11,FALSE) -> -1.146184 | G115: =F115-$U$2 -> -1.021184 | H115: =H114-0.125 -> 6.125 | I115: =100-VLOOKUP(H115,'[1]Pricing '!$A$463:$K$482,11,FALSE) -> -1.0134411 | J115: =I115-$U$2 -> -0.88844108 | O115: =O114-0.125 -> 6.125 | P115: =100-VLOOKUP(O115,'[1]Pricing '!$A$221:$K$240,11,FALSE) -> -0.9454631 | Q115: =P115-$U$2 -> -0.8204631 | R115: =R114-0.125 -> 6.125 | S115: =100-VLOOKUP(R115,'[1]Pricing '!$A$243:$K$262,11,FALSE) -> -0.71690183 | T115: =S115-$U$2 -> -0.59190183 | U115: =U114-0.125 -> 6.125 | V115: =100-VLOOKUP(U115,'[1]Pricing '!$A$265:$K$284,11,FALSE) -> -0.59107427 | W115: =V115-$U$2 -> -0.46607427 | AC115: =AC114-0.125 -> 6.25 | AD115: =100-VLOOKUP(AC115,'[1]Pricing '!$A$287:$K$306,11,FALSE) -> -0.76036625 | AE115: =AD115-$U$2 -> -0.63536625 | AF115: =AF114-0.125 -> 6.25 | AG115: =100-VLOOKUP(AF115,'[1]Pricing '!$A$309:$K$328,11,FALSE) -> -0.44737206 | AH115: =AG115-$U$2 -> -0.32237206 | AI115: =AI114-0.125 -> 6.125 | AJ115: =100-VLOOKUP(AI115,'[1]Pricing '!$A$331:$K$350,11,FALSE) -> -0.17383685 | AK115: =AJ115-$U$2 -> -0.048836848
B116: =B115-0.125 -> 6 | C116: =100-VLOOKUP(B116,'[1]Pricing '!$A$419:$K$438,11,FALSE) -> -1.080258 | D116: =C116-$U$2 -> -0.95525803 | E116: =E115-0.125 -> 6 | F116: =100-VLOOKUP(E116,'[1]Pricing '!$A$441:$K$460,11,FALSE) -> -0.86010183 | G116: =F116-$U$2 -> -0.73510183 | H116: =H115-0.125 -> 6 | I116: =100-VLOOKUP(H116,'[1]Pricing '!$A$463:$K$482,11,FALSE) -> -0.63567427 | J116: =I116-$U$2 -> -0.51067427 | O116: =O115-0.125 -> 6 | P116: =100-VLOOKUP(O116,'[1]Pricing '!$A$221:$K$240,11,FALSE) -> -0.78523005 | Q116: =P116-$U$2 -> -0.66023005 | R116: =R115-0.125 -> 6 | S116: =100-VLOOKUP(R116,'[1]Pricing '!$A$243:$K$262,11,FALSE) -> -0.66935656 | T116: =S116-$U$2 -> -0.54435656 | U116: =U115-0.125 -> 6 | V116: =100-VLOOKUP(U116,'[1]Pricing '!$A$265:$K$284,11,FALSE) -> -0.46250463 | W116: =V116-$U$2 -> -0.33750463 | AC116: =AC115-0.125 -> 6.125 | AD116: =100-VLOOKUP(AC116,'[1]Pricing '!$A$287:$K$306,11,FALSE) -> -0.61926818 | AE116: =AD116-$U$2 -> -0.49426818 | AF116: =AF115-0.125 -> 6.125 | AG116: =100-VLOOKUP(AF116,'[1]Pricing '!$A$309:$K$328,11,FALSE) -> -0.38645279 | AH116: =AG116-$U$2 -> -0.26145279 | AI116: =AI115-0.125 -> 6 | AJ116: =100-VLOOKUP(AI116,'[1]Pricing '!$A$331:$K$350,11,FALSE) -> -0.045952036 | AK116: =AJ116-$U$2 -> 0.079047964
... B123: =B122-0.125 -> 5.125 | C123: =100-VLOOKUP(B123,'[1]Pricing '!$A$419:$K$438,11,FALSE) -> 1.1325309 | D123: =C123-$U$2 -> 1.2575309 | E123: =E122-0.125 -> 5.125 | F123: =100-VLOOKUP(E123,'[1]Pricing '!$A$441:$K$460,11,FALSE) -> 1.1253252 | G123: =F123-$U$2 -> 1.2503252 | H123: =H122-0.125 -> 5.125 | I123: =100-VLOOKUP(H123,'[1]Pricing '!$A$463:$K$482,11,FALSE) -> 2.0735459 | J123: =I123-$U$2 -> 2.1985459 | O123: =O122-0.125 -> 5.125 | P123: =100-VLOOKUP(O123,'[1]Pricing '!$A$221:$K$240,11,FALSE) -> 0.65085543 | Q123: =P123-$U$2 -> 0.77585543 | R123: =R122-0.125 -> 5.125 | S123: =100-VLOOKUP(R123,'[1]Pricing '!$A$243:$K$262,11,FALSE) -> 0.96793671 | T123: =S123-$U$2 -> 1.0929367 | U123: =U122-0.125 -> 5.125 | V123: =100-VLOOKUP(U123,'[1]Pricing '!$A$265:$K$284,11,FALSE) -> 1.6686049 | W123: =V123-$U$2 -> 1.7936049 | AC123: =AC122-0.125 -> 5.25 | AD123: =100-VLOOKUP(AC123,'[1]Pricing '!$A$287:$K$306,11,FALSE) -> 0.73607145 | AE123: =AD123-$U$2 -> 0.86107145 | AF123: =AF122-0.125 -> 5.25 | AG123: =100-VLOOKUP(AF123,'[1]Pricing '!$A$309:$K$328,11,FALSE) -> 1.0099516 | AH123: =AG123-$U$2 -> 1.1349516 | AI123: =AI122-0.125 -> 5.125 | AJ123: =100-VLOOKUP(AI123,'[1]Pricing '!$A$331:$K$350,11,FALSE) -> 2.0807989 | AK123: =AJ123-$U$2 -> 2.2057989
B127: MAX PRICE ON FIXED PROG
B128: 0.04
B130: MAX PRICE ON ARM PROG
B131: 0.03
B143: Lender Fees: CONVENTIONAL $1,295 Lock Extensions: 2 bps per Day (Max of 30 Days) Redraw Fee $150.00
B144: Lock Hours until 5:00 PM PST
B145: Rates and fees are subject to change without notice.
A162: 1 | B162: 1.125 | C162: 1.25 | D162: 1.375 | E162: 1.5 | F162: 1.625 | G162: 1.75 | H162: 1.875 | I162: 2 | J162: 2.125 | K162: 2.25 | L162: 2.375 | M162: 2.5 | N162: 2.625 | O162: 2.75 | P162: 2.875 | Q162: 3 | R162: 3.125 | S162: 3.25 | T162: 3.375 | U162: 3.5 | V162: 3.625 | W162: 3.75 | X162: 3.875 | Y162: 4 | Z162: 4.125 | AA162: 4.25 | AB162: 4.375 | AC162: 4.5 | AD162: 4.625 | AE162: 4.75 | AF162: 4.875 | AG162: 5 | AH162: 5.125 | AI162: 5.25 | AJ162: 5.375 | AK162: 5.5 | AL162: 5.625 | AM162: 5.75 | AN162: 5.875 | AO162: 5.99 | AP162: 6 | AQ162: 6.125 | AR162: 6.25 | AS162: 6.375 | AT162: 6.5 | AU162: 6.625 | AV162: 6.75 | AW162: 6.875 | AX162: 7 | AY162: 7.125 | AZ162: 7.25 | BA162: 7.375 | BB162: 7.5 | BC162: 7.625 | BD162: 7.75 | BE162: 7.875 | BF162: 8 | BG162: 8.125 | BH162: 8.25 | BI162: 8.375 | BJ162: 8.5 | BK162: 8.625 | BL162: 8.75 | BM162: 8.875 | BN162: 9 | BO162: 9.125 | BP162: 9.25 | BQ162: 9.375 | BR162: 9.5 | BS162: 9.625 | BT162: 9.75 | BU162: 9.875 | BV162: 10 | BW162: 10.125 | BX162: 10.25 | BY162: 10.375 | BZ162: 10.5 | CA162: 10.625 | CB162: 10.75 | CC162: 10.875 | CD162: 11 | CE162: 11.125 | CF162: 11.25 | CG162: 11.375 | CH162: 11.5 | CI162: 11.625 | CJ162: 11.75 | CK162: 11.875 | CL162: 12 | CM162: 12.125 | CN162: 12.25 | CO162: 12.375 | CP162: 12.5 | CQ162: 12.625 | CR162: 12.75 | CS162: 12.875 | CT162: 13 | CU162: 13.125 | CV162: 13.25 | CW162: 13.375 | CX162: 13.5 | CY162: 13.625 | CZ162: 13.75 | DA162: 13.875 | DB162: 14 | DC162: 14.125 | DD162: 14.25 | DE162: 14.375

Sheet FT_LLPAS
T1: 2 of 12
B2: AmWest Corporate Office
B3: 6 Pointe Dr. Suite 300
B4: Brea, CA 92821
B5: (714) 831-3333
B6: www.amwestwholesale.com
E7: Wholesale Rate sheet - Consumer Paid | J7: Effective: | L7: =CONV!R7 -> 46101 | O7: =CONV!W7 -> 0
B8: LOAN LOCK INFO
B9: Lock Desk : Email: Lockdesk@amwestfunding.com | H9: Phone: (714) 831-3299 | L9: eFax: (714) 905-5620 | Q9: Lock Hours: 8:30AM-5:00 PM PST
B10: ANNOUNCEMENT
B15: FAST TRACK LLPA's (FFT & FMFT)
B17: Purchase(Loan terms > 15 years) | N17: >4 Owned properties including Financed LLPA
B18: FICO/LTV | C18: ≤30 | D18: 30.01-60 | E18: 60.01-70 | F18: 70.01-75 | G18: 75.01-80 | H18: 80.01-85 | I18: 85.01-90 | J18: 90.01-95 | K18: >95 | N18: 15 MAX owned properties on CONVENTIONAL
B19: ≥800 | C19: 0 | D19: 0 | E19: 0 | F19: 0 | G19: 0.375 | H19: 0.75 | I19: 0.75 | J19: 0.875 | K19: 0.875 | N19: 5-7 properties | T19: 0
B20: 780-799 | C20: 0 | D20: 0 | E20: 0 | F20: 0 | G20: 0.375 | H20: 0.75 | I20: 0.75 | J20: 0.875 | K20: 0.875 | N20: 8-10 properties | T20: 0.25
B21: 760-779 | C21: 0 | D21: 0 | E21: 0 | F21: 0.25 | G21: 0.625 | H21: 1 | I21: 1 | J21: 1.125 | K21: 1 | N21: 11-15 properties | T21: 0.5
B22: 740-759 | C22: 0 | D22: 0 | E22: 0.125 | F22: 0.375 | G22: 0.875 | H22: 1.375 | I22: 1.25 | J22: 1.25 | K22: 1.25
B23: 720-739 | C23: 0 | D23: 0 | E23: 0.25 | F23: 0.75 | G23: 1.25 | H23: 1.625 | I23: 1.5 | J23: 1.5 | K23: 1.5
B24: 700-719 | C24: 0 | D24: 0 | E24: 0.375 | F24: 0.875 | G24: 1.375 | H24: 1.875 | I24: 1.75 | J24: 1.75 | K24: 1.625
B25: 680-699 | C25: 0 | D25: 0 | E25: 0.625 | F25: 1.125 | G25: 1.75 | H25: 2.25 | I25: 2 | J25: 2 | K25: 1.875
B26: 660-679 | C26: 0.375 | D26: 0.375 | E26: 1.125 | F26: 1.75 | G26: 2.25 | H26: 2.5 | I26: 2.25 | J26: 2.25 | K26: 2
B27: 640-659 | C27: 0.5 | D27: 0.5 | E27: 1.625 | F27: 2 | G27: 2.75 | H27: 3 | I27: 2.5 | J27: 2.5 | K27: 2.25
B28: 620-639 | C28: 0.625 | D28: 0.75 | E28: 2.125 | F28: 2.75 | G28: 3.375 | H28: 3.5 | I28: 3.25 | J28: 2.875 | K28: 2.5
B29: Purchase Loan Additional (all amortization terms) | N29: OTHER PRICE ADJUSTMENTS
B30: LTV | C30: ≤30 | D30: 30.01-60 | E30: 60.01-70 | F30: 70.01-75 | G30: 75.01-80 | H30: 80.01-85 | I30: 85.01-90 | J30: 90.01-95 | K30: >95 | N30: Loan Amt $50,000- $74,999 | T30: 1.5
B31: ARMs | C31: 0 | D31: 0 | E31: 0 | F31: 0 | G31: 0 | H31: 0 | I31: 0 | J31: 0.25 | K31: N/A | N31: Loan Amt $75,000 to $99,999 | T31: 0.75
B32: Attached Condo | C32: 0 | D32: 0 | E32: 0.125 | F32: 0.125 | G32: 0.75 | H32: 0.75 | I32: 0.75 | J32: 0.75 | K32: 0.75 | N32: Loan Amt $100,000 to $149,999 | T32: 0.125
B33: Sub Financing | C33: 0.625 | D33: 0.625 | E33: 0.625 | F33: 0.875 | G33: 1.125 | H33: 1.125 | I33: 1.125 | J33: 1.875 | K33: 1.875 | N33: Texas 50 A (6) | T33: 0.125
B34: HighBal Fixed | C34: 0.5 | D34: 0.5 | E34: 0.75 | F34: 0.75 | G34: 1 | H34: 1 | I34: 1 | J34: 1 | K34: 1 | N34: 60 DAYS LOCK (based on 30 days price) | T34: 0.25
B35: HighBal ARM | C35: 1.25 | D35: 1.25 | E35: 1.5 | F35: 1.5 | G35: 2.5 | H35: 2.5 | I35: 2.5 | J35: 2.75 | K35: N/A
B36: Baltimore County-MD | C36: 0.25 | D36: 0.25 | E36: 0.25 | F36: 0.375 | G36: 0.375 | H36: 0.5 | I36: 0.5 | J36: 0.5 | K36: 0.5
B37: Rate&Term (Loan terms > 15 years)
B38: FICO/LTV | C38: ≤30 | D38: 30.01-60 | E38: 60.01-70 | F38: 70.01-75 | G38: 75.01-80 | H38: 80.01-85 | I38: 85.01-90 | J38: 90.01-95 | K38: >95
B39: ≥800 | C39: 0 | D39: 0 | E39: 0 | F39: 0.125 | G39: 0.5 | H39: 1 | I39: 1 | J39: 1 | K39: 1.125 | N39: State Adjuster (FIXED Program) | S39: 30/20Y | T39: 15/10Y
B40: 780-799 | C40: 0 | D40: 0 | E40: 0 | F40: 0.125 | G40: 0.5 | H40: 1 | I40: 1 | J40: 1 | K40: 1.125 | N40: Group 1 | O40: TX | S40: -0.125 | T40: -0.125
B41: 760-779 | C41: 0 | D41: 0 | E41: 0.125 | F41: 0.375 | G41: 0.875 | H41: 1.375 | I41: 1.25 | J41: 1.25 | K41: 1.375
B42: 740-759 | C42: 0 | D42: 0 | E42: 0.25 | F42: 0.75 | G42: 1.125 | H42: 1.75 | I42: 1.625 | J42: 1.625 | K42: 1.75
B43: 720-739 | C43: 0 | D43: 0 | E43: 0.5 | F43: 1 | G43: 1.625 | H43: 2.125 | I43: 2 | J43: 1.875 | K43: 2
B44: 700-719 | C44: 0 | D44: 0 | E44: 0.625 | F44: 1.25 | G44: 1.875 | H44: 2.5 | I44: 2.25 | J44: 2.25 | K44: 2.375
B45: 680-699 | C45: 0 | D45: 0 | E45: 0.875 | F45: 1.625 | G45: 2.25 | H45: 2.875 | I45: 2.625 | J45: 2.375 | K45: 2.5
B46: 660-679 | C46: 0.375 | D46: 0.5 | E46: 1.5 | F46: 2.25 | G46: 2.875 | H46: 3.375 | I46: 2.875 | J46: 2.75 | K46: 2.875
B47: 640-659 | C47: 0.5 | D47: 0.75 | E47: 1.875 | F47: 2.625 | G47: 3.375 | H47: 3.875 | I47: 3.375 | J47: 3.125 | K47: 3.25 | N47: FANNIE MAE & FREDDIE MAC
B48: 620-639 | C48: 0.625 | D48: 1 | E48: 2.375 | F48: 3.125 | G48: 4.125 | H48: 4.5 | I48: 4.25 | J48: 3.125 | K48: 3.25 | N48: LLPA WAIVER
B49: Rate&Term Additional (all amortization terms) | N49: Must be first-time home buyer with
B50: LTV | C50: ≤30 | D50: 30.01-60 | E50: 60.01-70 | F50: 70.01-75 | G50: 75.01-80 | H50: 80.01-85 | I50: 85.01-90 | J50: 90.01-95 | K50: >95 | N50: Applicable AMI (Area Median Income )
B51: ARMs | C51: 0 | D51: 0 | E51: 0 | F51: 0 | G51: 0 | H51: 0 | I51: 0 | J51: 0.25 | K51: N/A
B52: Attached Condo | C52: 0 | D52: 0 | E52: 0.125 | F52: 0.125 | G52: 0.75 | H52: 0.75 | I52: 0.75 | J52: 0.75 | K52: 0.75
B53: Sub Financing | C53: 0.625 | D53: 0.625 | E53: 0.625 | F53: 0.875 | G53: 1.125 | H53: 1.125 | I53: 1.125 | J53: 1.875 | K53: 1.875
B54: HighBal Fixed | C54: 0.5 | D54: 0.5 | E54: 0.75 | F54: 0.75 | G54: 1 | H54: 1 | I54: 1 | J54: 1 | K54: N/A
B55: HighBal ARM | C55: 1.25 | D55: 1.25 | E55: 1.5 | F55: 1.5 | G55: 2.5 | H55: 2.5 | I55: 2.5 | J55: 2.75 | K55: N/A
B56: Baltimore County-MD | C56: 0.25 | D56: 0.25 | E56: 0.25 | F56: 0.375 | G56: 0.375 | H56: 0.5 | I56: 0.5 | J56: 0.5 | K56: 0.5
B57: Cash Out (all amortization terms) | N57: Cumulative LLPA Caps
B58: FICO/LTV | C58: ≤30 | D58: 30.01-60 | E58: 60.01-70 | F58: 70.01-75 | G58: 75.01-80 | S58: ALL LTV's
B59: ≥800 | C59: 0.375 | D59: 0.375 | E59: 0.625 | F59: 0.875 | G59: 1.375
B60: 780-799 | C60: 0.375 | D60: 0.375 | E60: 0.625 | F60: 0.875 | G60: 1.375 | N60: AMI & FTHB | S60: 0
B61: 760-779 | C61: 0.375 | D61: 0.375 | E61: 0.875 | F61: 1.25 | G61: 1.875 | N61: **(Excluded from Cumulative Cap- Loan amts ,lock term, state Adj)
B62: 740-759 | C62: 0.375 | D62: 0.375 | E62: 1 | F62: 1.625 | G62: 2.375
B63: 720-739 | C63: 0.375 | D63: 0.5 | E63: 1.375 | F63: 2 | G63: 2.75
B64: 700-719 | C64: 0.375 | D64: 0.5 | E64: 1.625 | F64: 2.625 | G64: 3.25
B65: 680-699 | C65: 0.375 | D65: 0.625 | E65: 2 | F65: 2.875 | G65: 3.75 | N65: IMPOUNDS/ ESCROW
B66: 660-679 | C66: 0.75 | D66: 1.25 | E66: 3.125 | F66: 4.375 | G66: 5.125 | N66: • Impounds/Escrows may be waived per state law
B67: 640-659 | C67: 0.875 | D67: 1.875 | E67: 3.625 | F67: 5.125 | G67: 5.625 | N67: • HPML loans must be impounded
B68: 620-639 | C68: 1 | D68: 2 | E68: 4 | F68: 5.5 | G68: 5.75 | N68: • Any loans requiring flood insurance must include flood
B69: Cash Out Additional (all amortization terms) | N69: insurance must include in the borrower(s)’ escrow account
B70: LTV | C70: ≤30 | D70: 30.01-60 | E70: 60.01-70 | F70: 70.01-75 | G70: 75.01-80 | N70: even if no other escrows are collected or escrows have been
B71: ARMs | C71: 0 | D71: 0 | E71: 0 | F71: 0 | G71: 0 | N71: waived
B72: Attached Condo | C72: 0 | D72: 0 | E72: 0.125 | F72: 0.125 | G72: 0.75
B73: Sub Financing | C73: 0.625 | D73: 0.625 | E73: 0.625 | F73: 0.875 | G73: 1.125
B74: HighBal Fixed | C74: 1.25 | D74: 1.25 | E74: 1.5 | F74: 1.5 | G74: 1.75
B75: HighBal ARM | C75: 2 | D75: 2 | E75: 2.25 | F75: 2.25 | G75: 3.25 | N75: MAX LOAN AMOUNT
B76: Baltimore County-MD | C76: 0.25 | D76: 0.25 | E76: 0.25 | F76: 0.375 | G76: 0.375 | N76: All States Except Alaska / Hawaii
B77: LPMI ADJUSTER's APPLIED TO FANNIE MAE & FREDDIE MAC (Fixed & Arm's) | N77: 1 UNIT | S77: 832750
B78: LPMI ADJUSTMENTS FOR 30 & 25 YEAR & ALL ARMS
B79: LTV | C79: Coverage | D79: >=760 | E79: 740-759 | F79: 720-739 | G79: 700-719 | H79: 680-699 | I79: 660-679 | J79: 640-659 | K79: 620-639 | N79: STATE RESTRICTIONS
B80: 95.01-97% | C80: 0.35 | D80: 2.3 | E80: 3.32 | F80: 4.23 | G80: 5.05 | H80: 6.27 | I80: 8.42 | J80: 9.13 | K80: 10 | N80: Please refer to our website for list of Eligible States:
B81: 90.01-95% | C81: 0.3 | D81: 1.89 | E81: 2.65 | F81: 3.32 | G81: 3.93 | H81: 4.85 | I81: 6.43 | J81: 6.99 | K81: 7.75 | N81: CLICK HERE
B82: 85.01-90% | C82: 0.25 | D82: 1.43 | E82: 2.04 | F82: 2.5 | G82: 3.01 | H82: 3.67 | I82: 5.05 | J82: 5.36 | K82: 5.87
B83: 80.01-85% | C83: 0.12 | D83: 0.71 | E83: 0.87 | F83: 1.02 | G83: 1.17 | H83: 1.38 | I83: 1.84 | J83: 2.04 | K83: 2.19
B84: LPMI ADJUSTMENTS FOR 20 YEAR & UNDER | N84: MORTGAGE INSURANCE
B85: 90.01-95% | C85: 0.25 | D85: 1.45 | E85: 2.12 | F85: 2.68 | G85: 3.09 | H85: 3.9 | I85: 5.12 | J85: 5.63 | K85: 6.24 | N85: LTV | R85: 10,15, 20 Year | T85: 30 Year
B86: 85.01-90% | C86: 0.12 | D86: 0.79 | E86: 1.04 | F86: 1.3 | G86: 1.45 | H86: 1.76 | I86: 2.31 | J86: 2.52 | K86: 2.77 | N86: 95.01- 97.00%* HomeReady | R86: N/A | T86: 0.25
B87: 80.01-85% | C87: 0.06 | D87: 0.55 | E87: 0.55 | F87: 0.55 | G87: 0.55 | H87: 0.59 | I87: 0.73 | J87: 0.78 | K87: 0.89 | N87: 95.01-97.00% *Standard | R87: N/A | T87: 0.35
B88: LPMI ADDITIONAL ADJUSTMENTS (FIXED & ARM'S) | N88: 90.01-95.00% | R88: 0.25 | T88: 0.3
B89: Rate&term | D89: 0 | E89: 0 | F89: 0 | G89: 0.53 | H89: 0.53 | I89: 1.05 | J89: 1.05 | K89: 1.05 | N89: 85.01-90.00% | R89: 0.12 | T89: 0.25
B90: LPMI ADDITIONAL ADJUSTMENTS (FIXED & ARM'S) >45.00% DTI | N90: 80.01-85.00% | R90: 0.06 | T90: 0.12
B91: 95.01-97% | D91: 0.38 | E91: 0.62 | F91: 0.76 | G91: 1.06 | H91: 1.24 | I91: 1.42 | J91: 1.6 | K91: 1.82 | N91: All loans with LTV > 80% are subject to MI approval
B92: 90.01-95% | D92: 0.35 | E92: 0.44 | F92: 0.57 | G92: 0.72 | H92: 1 | I92: 1.12 | J92: 1.27 | K92: 1.53
B93: 85.01-90% | D93: 0.28 | E93: 0.39 | F93: 0.5 | G93: 0.62 | H93: 0.75 | I93: 0.89 | J93: 1.01 | K93: 1.25
B94: 80.01-85% | D94: 0.11 | E94: 0.17 | F94: 0.22 | G94: 0.3 | H94: 0.38 | I94: 0.42 | J94: 0.44 | K94: 0.49
B107: Lender Fees: CONVENTIONAL $1,295 Lock Extensions: 2 bps per Day (Max of 30 Days) Redraw Fee $150.00
B108: Lock Hours until 5:00 PM PST
B109: Rates and fees are subject to change without notice.

Sheet LLPAS
T1: 4 of 11
B2: AmWest Corporate Office | R2: Lock Expiration Dates
B3: 6 Pointe Dr. Suite 300
B4: Brea, CA 92821 | R4: 30 Day Lock | T4: =[2]FNMA!P4 -> 45980
B5: (714) 831-3333 | R5: 45 Day Lock | T5: =[2]FNMA!P5 -> 45995
B6: www.amwestwholesale.com | R6: 60 Day Lock | T6: =[2]FNMA!P6 -> 46010
F7: Wholesale Rate sheet - Consumer Paid | J7: Effective: | L7: =TODAY() -> 46101 | O7: =[2]FNMA!M7 -> 8:00 AM PST
B8: LOAN LOCK INFO
B9: Lock Desk : Email: Lockdesk@amwestfunding.com | H9: Phone: (714) 831-3299 | L9: eFax: (714) 905-5620 | Q9: Lock Hours: 8:30AM-5:00 PM PST
B10: ANNOUNCEMENT
B15: AGENCY LLPAs (DU/LP) - FIXED & ARM (Incl. HomeOne, RefiNow)
B17: Purchase(Loan terms > 15 years) | N17: NOO Additional Adjustments (30YR FIXED ONLY)
B18: FICO/LTV | C18: ≤30 | D18: 30.01-60 | E18: 60.01-70 | F18: 70.01-75 | G18: 75.01-80 | H18: 80.01-85 | I18: 85.01-90 | J18: 90.01-95 | K18: >95 | N18: LTV | O18: ≤30 | P18: 30.01-60 | Q18: 60.01-70 | R18: 70.01-75 | S18: 75.01-80 | T18: 80.01-85
B19: ≥800 | C19: 0 | D19: 0 | E19: 0 | F19: 0 | G19: 0.375 | H19: 0.75 | I19: 0.75 | J19: 0.875 | K19: 0.875 | N19: Purchase | O19: -0.375 | P19: -0.375 | Q19: -1 | R19: -1.125 | S19: -1.25 | T19: -0.75
B20: 780-799 | C20: 0 | D20: 0 | E20: 0 | F20: 0 | G20: 0.375 | H20: 0.75 | I20: 0.75 | J20: 0.875 | K20: 0.875 | N20: Rate&Term | O20: -0.875 | P20: -0.875 | Q20: -1.125 | R20: -1.25 | S20: -1.75 | T20: -0.625
B21: 760-779 | C21: 0 | D21: 0 | E21: 0 | F21: 0.25 | G21: 0.625 | H21: 1 | I21: 1 | J21: 1.125 | K21: 1 | N21: Cash Out | O21: -1.125 | P21: -1.125 | Q21: -1.25 | R21: -1.25 | S21: -0.25 | T21: -0.25
B22: 740-759 | C22: 0 | D22: 0 | E22: 0.125 | F22: 0.375 | G22: 0.875 | H22: 1.375 | I22: 1.25 | J22: 1.25 | K22: 1.25 | N22: High Balance | O22: 1.25 | P22: 1.25 | Q22: 1.25 | R22: 1.25 | S22: 1.25 | T22: 1.25
B23: 720-739 | C23: 0 | D23: 0 | E23: 0.25 | F23: 0.75 | G23: 1.25 | H23: 1.625 | I23: 1.5 | J23: 1.5 | K23: 1.5 | N23: Fico 680-719 | O23: 0.25 | P23: 0.25 | Q23: -0.25 | R23: 0.25 | S23: -0.25 | T23: 0.25
B24: 700-719 | C24: 0 | D24: 0 | E24: 0.375 | F24: 0.875 | G24: 1.375 | H24: 1.875 | I24: 1.75 | J24: 1.75 | K24: 1.625
B25: 680-699 | C25: 0 | D25: 0 | E25: 0.625 | F25: 1.125 | G25: 1.75 | H25: 2.25 | I25: 2 | J25: 2 | K25: 1.875 | N25: 2nd Home Additional Adjustments (30YR FIXED ONLY)
B26: 660-679 | C26: 0.375 | D26: 0.375 | E26: 1.125 | F26: 1.75 | G26: 2.25 | H26: 2.5 | I26: 2.25 | J26: 2.25 | K26: 2 | N26: LTV | O26: ≤30 | P26: 30.01-60 | Q26: 60.01-70 | R26: 70.01-75 | S26: 75.01-80 | T26: 80.01-85
B27: 640-659 | C27: 0.5 | D27: 0.5 | E27: 1.625 | F27: 2 | G27: 2.75 | H27: 3 | I27: 2.5 | J27: 2.5 | K27: 2.25 | N27: Purchase / R&T | O27: -0.375 | P27: -0.375 | Q27: -0.375 | R27: 0 | S27: 0 | T27: 0
B28: 620-639 | C28: 0.625 | D28: 0.75 | E28: 2.125 | F28: 2.75 | G28: 3.375 | H28: 3.5 | I28: 3.25 | J28: 2.875 | K28: 2.5 | N28: Cash Out | O28: -0.375 | P28: -0.375 | Q28: 0 | R28: 0 | S28: 0 | T28: 0
B29: Purchase Loan Additional (all amortization terms)
B30: LTV | C30: ≤30 | D30: 30.01-60 | E30: 60.01-70 | F30: 70.01-75 | G30: 75.01-80 | H30: 80.01-85 | I30: 85.01-90 | J30: 90.01-95 | K30: >95
B31: ARMs | C31: 0 | D31: 0 | E31: 0 | F31: 0 | G31: 0 | H31: 0 | I31: 0 | J31: 0.25 | K31: N/A
B32: Attached Condo | C32: 0 | D32: 0 | E32: 0.125 | F32: 0.125 | G32: 0.75 | H32: 0.75 | I32: 0.75 | J32: 0.75 | K32: 0.75
B33: 2-4 Units | C33: 0 | D33: 0 | E33: 0.375 | F33: 0.375 | G33: 0.625 | H33: 0.625 | I33: 0.875 | J33: 0.875 | K33: N/A | O33: >4 Owned properties including Financed LLPA
B34: N/O/O | C34: 1.125 | D34: 1.125 | E34: 1.625 | F34: 2.125 | G34: 3.375 | H34: 4.125 | I34: N/A | J34: N/A | K34: N/A | O34: 15 MAX owned properties on CONVENTIONAL
B35: Second Homes | C35: 1.125 | D35: 1.125 | E35: 1.625 | F35: 2.125 | G35: 3.375 | H35: 4.125 | I35: 4.125 | J35: N/A | K35: N/A | O35: 5-7 properties | S35: 0
B36: Sub Financing | C36: 0.625 | D36: 0.625 | E36: 0.625 | F36: 0.875 | G36: 1.125 | H36: 1.125 | I36: 1.125 | J36: 1.875 | K36: 1.875 | O36: 8-10 properties | S36: 0.25
B37: HighBal Fixed | C37: 0.5 | D37: 0.5 | E37: 0.75 | F37: 0.75 | G37: 1 | H37: 1 | I37: 1 | J37: 1 | K37: 1 | O37: 11-15 properties | S37: 0.5
B38: HighBal ARM | C38: 1.25 | D38: 1.25 | E38: 1.5 | F38: 1.5 | G38: 2.5 | H38: 2.5 | I38: 2.5 | J38: 2.75 | K38: N/A
B39: Baltimore County-MD | C39: 0.25 | D39: 0.25 | E39: 0.25 | F39: 0.375 | G39: 0.375 | H39: 0.5 | I39: 0.5 | J39: 0.5 | K39: 0.5
B40: Rate&Term (Loan terms > 15 years) | N40: OTHER PRICE ADJUSTMENTS
B41: FICO/LTV | C41: ≤30 | D41: 30.01-60 | E41: 60.01-70 | F41: 70.01-75 | G41: 75.01-80 | H41: 80.01-85 | I41: 85.01-90 | J41: 90.01-95 | K41: >95 | N41: Loan Amt $50,000- $74,999 | T41: 1.5
B42: ≥800 | C42: 0 | D42: 0 | E42: 0 | F42: 0.125 | G42: 0.5 | H42: 1 | I42: 1 | J42: 1 | K42: 1.125 | N42: Loan Amt $75,000 to $99,999 | T42: 0.75
B43: 780-799 | C43: 0 | D43: 0 | E43: 0 | F43: 0.125 | G43: 0.5 | H43: 1 | I43: 1 | J43: 1 | K43: 1.125 | N43: Loan Amt $100,000 to $149,999 | T43: 0.125
B44: 760-779 | C44: 0 | D44: 0 | E44: 0.125 | F44: 0.375 | G44: 0.875 | H44: 1.375 | I44: 1.25 | J44: 1.25 | K44: 1.375 | N44: Texas 50 A (6) | T44: 0.125
B45: 740-759 | C45: 0 | D45: 0 | E45: 0.25 | F45: 0.75 | G45: 1.125 | H45: 1.75 | I45: 1.625 | J45: 1.625 | K45: 1.75 | N45: 1 year tax return >90% LTV (self-employment) | T45: 0.25
B46: 720-739 | C46: 0 | D46: 0 | E46: 0.5 | F46: 1 | G46: 1.625 | H46: 2.125 | I46: 2 | J46: 1.875 | K46: 2 | N46: 60 DAYS LOCK (based on 30 days price) | T46: 0.25
B47: 700-719 | C47: 0 | D47: 0 | E47: 0.625 | F47: 1.25 | G47: 1.875 | H47: 2.5 | I47: 2.25 | J47: 2.25 | K47: 2.375
B48: 680-699 | C48: 0 | D48: 0 | E48: 0.875 | F48: 1.625 | G48: 2.25 | H48: 2.875 | I48: 2.625 | J48: 2.375 | K48: 2.5
B49: 660-679 | C49: 0.375 | D49: 0.5 | E49: 1.5 | F49: 2.25 | G49: 2.875 | H49: 3.375 | I49: 2.875 | J49: 2.75 | K49: 2.875
B50: 640-659 | C50: 0.5 | D50: 0.75 | E50: 1.875 | F50: 2.625 | G50: 3.375 | H50: 3.875 | I50: 3.375 | J50: 3.125 | K50: 3.25 | N50: State Adjuster (FIXED Program) | S50: 30/20Y | T50: 15/10Y
B51: 620-639 | C51: 0.625 | D51: 1 | E51: 2.375 | F51: 3.125 | G51: 4.125 | H51: 4.5 | I51: 4.25 | J51: 3.125 | K51: 3.25 | N51: Group 1 | O51: TX | S51: -0.125 | T51: -0.125
B52: Rate&Term Additional (all amortization terms)
B53: LTV | C53: ≤30 | D53: 30.01-60 | E53: 60.01-70 | F53: 70.01-75 | G53: 75.01-80 | H53: 80.01-85 | I53: 85.01-90 | J53: 90.01-95 | K53: >95 | N53: FANNIE MAE & FREDDIE MAC
B54: ARMs | C54: 0 | D54: 0 | E54: 0 | F54: 0 | G54: 0 | H54: 0 | I54: 0 | J54: 0.25 | K54: N/A | N54: LLPA WAIVER
B55: Attached Condo | C55: 0 | D55: 0 | E55: 0.125 | F55: 0.125 | G55: 0.75 | H55: 0.75 | I55: 0.75 | J55: 0.75 | K55: 0.75 | N55: Must be first-time home buyer with
B56: 2-4 Units | C56: 0 | D56: 0 | E56: 0.375 | F56: 0.375 | G56: 0.625 | H56: 0.625 | I56: 0.875 | J56: 0.875 | K56: N/A | N56: Applicable AMI (Area Median Income )
B57: N/O/O | C57: 1.125 | D57: 1.125 | E57: 1.625 | F57: 2.125 | G57: 3.375 | H57: 4.125 | I57: N/A | J57: N/A | K57: N/A
B58: Second Homes | C58: 1.125 | D58: 1.125 | E58: 1.625 | F58: 2.125 | G58: 3.375 | H58: 4.125 | I58: 4.125 | J58: N/A | K58: N/A
B59: Sub Financing | C59: 0.625 | D59: 0.625 | E59: 0.625 | F59: 0.875 | G59: 1.125 | H59: 1.125 | I59: 1.125 | J59: 1.875 | K59: 1.875 | P59: FANNIE MAE ONLY
B60: HighBal Fixed | C60: 0.5 | D60: 0.5 | E60: 0.75 | F60: 0.75 | G60: 1 | H60: 1 | I60: 1 | J60: 1 | K60: N/A | P60: 2-4 Units up to 95%
B61: HighBal ARM | C61: 1.25 | D61: 1.25 | E61: 1.5 | F61: 1.5 | G61: 2.5 | H61: 2.5 | I61: 2.5 | J61: 2.75 | K61: N/A | P61: Principal residence, Purchase & R/T refinances
B62: Baltimore County-MD | C62: 0.25 | D62: 0.25 | E62: 0.25 | F62: 0.375 | G62: 0.375 | H62: 0.5 | I62: 0.5 | J62: 0.5 | K62: 0.5 | P62: High Balance is not available
B63: Cash Out (all amortization terms)
B64: FICO/LTV | C64: ≤30 | D64: 30.01-60 | E64: 60.01-70 | F64: 70.01-75 | G64: 75.01-80 | N64: Cumulative LLPA Caps
B65: ≥800 | C65: 0.375 | D65: 0.375 | E65: 0.625 | F65: 0.875 | G65: 1.375 | S65: ALL LTV's
B66: 780-799 | C66: 0.375 | D66: 0.375 | E66: 0.625 | F66: 0.875 | G66: 1.375
B67: 760-779 | C67: 0.375 | D67: 0.375 | E67: 0.875 | F67: 1.25 | G67: 1.875 | N67: AMI & FTHB | S67: 0
B68: 740-759 | C68: 0.375 | D68: 0.375 | E68: 1 | F68: 1.625 | G68: 2.375 | N68: **(Excluded from Cumulative Cap- Loan amts ,lock term, state Adj)
B69: 720-739 | C69: 0.375 | D69: 0.5 | E69: 1.375 | F69: 2 | G69: 2.75
B70: 700-719 | C70: 0.375 | D70: 0.5 | E70: 1.625 | F70: 2.625 | G70: 3.25
B71: 680-699 | C71: 0.375 | D71: 0.625 | E71: 2 | F71: 2.875 | G71: 3.75 | N71: IMPOUNDS/ ESCROW
B72: 660-679 | C72: 0.75 | D72: 1.25 | E72: 3.125 | F72: 4.375 | G72: 5.125 | N72: • Impounds/Escrows may be waived per state law
B73: 640-659 | C73: 0.875 | D73: 1.875 | E73: 3.625 | F73: 5.125 | G73: 5.625 | N73: • HPML loans must be impounded
B74: 620-639 | C74: 1 | D74: 2 | E74: 4 | F74: 5.5 | G74: 5.75 | N74: • Any loans requiring flood insurance must include flood
B75: Cash Out Additional (all amortization terms) | N75: insurance must include in the borrower(s)’ escrow account
B76: LTV | C76: ≤30 | D76: 30.01-60 | E76: 60.01-70 | F76: 70.01-75 | G76: 75.01-80 | N76: even if no other escrows are collected or escrows have been
B77: ARMs | C77: 0 | D77: 0 | E77: 0 | F77: 0 | G77: 0 | N77: waived
B78: Attached Condo | C78: 0 | D78: 0 | E78: 0.125 | F78: 0.125 | G78: 0.75
B79: 2-4 Units | C79: 0 | D79: 0 | E79: 0.375 | F79: 0.375 | G79: N/A
B80: N/O/O | C80: 1.125 | D80: 1.125 | E80: 1.625 | F80: 2.125 | G80: N/A | N80: STATE RESTRICTIONS
B81: Second Homes | C81: 0.75 | D81: 0.75 | E81: 1.625 | F81: 2.125 | G81: N/A
B82: Sub Financing | C82: 0.625 | D82: 0.625 | E82: 0.625 | F82: 0.875 | G82: 1.125 | N82: Please refer to our website for list of Eligible States:
B83: HighBal Fixed | C83: 1.25 | D83: 1.25 | E83: 1.5 | F83: 1.5 | G83: 1.75 | N83: CLICK HERE
B84: HighBal ARM | C84: 2 | D84: 2 | E84: 2.25 | F84: 2.25 | G84: 3.25
B85: Baltimore County-MD | C85: 0.25 | D85: 0.25 | E85: 0.25 | F85: 0.375 | G85: 0.375
B87: LPMI ADJUSTER's APPLIED TO FANNIE MAE & FREDDIE MAC (Fixed & Arm's) | N87: MAX LOAN AMOUNT
B88: LPMI ADJUSTMENTS FOR 30 & 25 YEAR & ALL ARMS | N88: All States Except Alaska / Hawaii
B89: LTV | C89: Coverage | D89: >=760 | E89: 740-759 | F89: 720-739 | G89: 700-719 | H89: 680-699 | I89: 660-679 | J89: 640-659 | K89: 620-639 | N89: 1 UNIT | R89: 832750
B90: 95.01-97% | C90: 0.35 | D90: 2.3 | E90: 3.32 | F90: 4.23 | G90: 5.05 | H90: 6.27 | I90: 8.42 | J90: 9.13 | K90: 10 | N90: 2 UNIT | R90: 1066250
B91: 90.01-95% | C91: 0.3 | D91: 1.89 | E91: 2.65 | F91: 3.32 | G91: 3.93 | H91: 4.85 | I91: 6.43 | J91: 6.99 | K91: 7.75 | N91: 3 UNIT | R91: 1288800
B92: 85.01-90% | C92: 0.25 | D92: 1.43 | E92: 2.04 | F92: 2.5 | G92: 3.01 | H92: 3.67 | I92: 5.05 | J92: 5.36 | K92: 5.87 | N92: 4 UNIT | R92: 1601750
B93: 80.01-85% | C93: 0.12 | D93: 0.71 | E93: 0.87 | F93: 1.02 | G93: 1.17 | H93: 1.38 | I93: 1.84 | J93: 2.04 | K93: 2.19
B94: LPMI ADJUSTMENTS FOR 20 YEAR & UNDER
B95: 90.01-95% | C95: 0.25 | D95: 1.45 | E95: 2.12 | F95: 2.68 | G95: 3.09 | H95: 3.9 | I95: 5.12 | J95: 5.63 | K95: 6.24 | N95: MORTGAGE INSURANCE
B96: 85.01-90% | C96: 0.12 | D96: 0.79 | E96: 1.04 | F96: 1.3 | G96: 1.45 | H96: 1.76 | I96: 2.31 | J96: 2.52 | K96: 2.77 | N96: LTV | R96: 10,15, 20 Year | T96: 30 Year
B97: 80.01-85% | C97: 0.06 | D97: 0.55 | E97: 0.55 | F97: 0.55 | G97: 0.55 | H97: 0.59 | I97: 0.73 | J97: 0.78 | K97: 0.89 | N97: 95.01- 97.00%* HomeReady | R97: N/A | T97: 0.25
B98: LPMI ADDITIONAL ADJUSTMENTS (FIXED & ARM'S) | N98: 95.01-97.00% *Standard | R98: N/A | T98: 0.35
B99: N/O/O | D99: 1.19 | E99: 1.19 | F99: 1.33 | G99: 1.75 | H99: 1.75 | I99: 2.63 | J99: 2.63 | K99: 2.63 | N99: 90.01-95.00% | R99: 0.25 | T99: 0.3
B100: Second Homes | D100: 0.25 | E100: 0.25 | F100: 0.49 | G100: 0.7 | H100: 0.7 | I100: 1.23 | J100: 1.23 | K100: 1.23 | N100: 85.01-90.00% | R100: 0.12 | T100: 0.25
B101: Rate&term | D101: 0 | E101: 0 | F101: 0 | G101: 0.53 | H101: 0.53 | I101: 1.05 | J101: 1.05 | K101: 1.05 | N101: 80.01-85.00% | R101: 0.06 | T101: 0.12
B102: LPMI ADDITIONAL ADJUSTMENTS (FIXED & ARM'S) >45.00% DTI | N102: All loans with LTV > 80% are subject to MI approval
B103: 95.01-97% | D103: 0.38 | E103: 0.62 | F103: 0.76 | G103: 1.06 | H103: 1.24 | I103: 1.42 | J103: 1.6 | K103: 1.82
B104: 90.01-95% | D104: 0.35 | E104: 0.44 | F104: 0.57 | G104: 0.72 | H104: 1 | I104: 1.12 | J104: 1.27 | K104: 1.53
B105: 85.01-90% | D105: 0.28 | E105: 0.39 | F105: 0.5 | G105: 0.62 | H105: 0.75 | I105: 0.89 | J105: 1.01 | K105: 1.25
B106: 80.01-85% | D106: 0.11 | E106: 0.17 | F106: 0.22 | G106: 0.3 | H106: 0.38 | I106: 0.42 | J106: 0.44 | K106: 0.49
...

Sheet HR & HP
P1: 4 of 12
B2: AmWest Corporate Office
B3: 6 Pointe Dr. Suite 300
B4: Brea, CA 92821
B5: (714) 831-3333
B6: www.amwestwholesale.com
F7: Wholesale Rate sheet - Consumer Paid | J7: Effective: | L7: =TODAY() -> 46101 | M7: =LLPAS!O7 -> 8:00 AM PST
B8: LOAN LOCK INFO
B9: Lock Desk : Email: Lockdesk@amwestfunding.com | G9: Phone: (714) 831-3299 | J9: eFax: (714) 905-5620 | M9: Lock Hours: 8:30AM-5:00 PM PST
B10: ANNOUNCEMENT
B12: HomeReady & HomePossible Enhancement programs with $2,500 credits available!!
B15: FANNIE MAE HOMEREADY CONFORMING & HIGH BALANCE- FIXED & ARM
B16: Conforming & High Balance FIXED | H16: CONFORMING ARMS | V16: LINKED
B17: (FCF30HR) 30 YR | E17: (FCF30HR HB) 30 YR | H17: (CA5/6 HR) 5YR ARM | K17: (CA7/6 HR) 7YR ARM | N17: (CA10/6 HR) 10YR ARM | V17: 45 DAY COST
B18: RATE | C18: 30 Days | D18: 45 Days | E18: RATE | F18: 30 Days | G18: 45 Days | H18: RATE | I18: 30 Days | J18: 45 Days | K18: RATE | L18: 30 Days | M18: 45 Days | N18: RATE | O18: 30 Days | P18: 45 Days | V18: -0.125
B19: 5.375 | C19: =100-VLOOKUP(B19,'[1]Pricing '!$A$140:$K$164,11,FALSE) -> 3.5787035 | D19: =C19-$V$18 -> 3.7037035 | E19: 5.375 | F19: =100-VLOOKUP(E19,'[1]Pricing '!$A$2034:$K$2059,11,FALSE) -> 3.6732835 | G19: =F19-$V$18 -> 3.7982835 | H19: 5.125 | I19: =100-VLOOKUP(H19,'[1]Pricing '!$A$353:$K$372,11,FALSE) -> 0.90085543 | J19: =I19-$V$18 -> 1.0258554 | K19: 5.125 | L19: =100-VLOOKUP(K19,'[1]Pricing '!$A$375:$K$394,11,FALSE) -> 1.2179367 | M19: =L19-$V$18 -> 1.3429367 | N19: 5.125 | O19: =100-VLOOKUP(N19,'[1]Pricing '!$A$397:$K$416,11,FALSE) -> 1.9186049 | P19: =O19-$V$18 -> 2.0436049
B20: =B19+0.125 -> 5.5 | C20: =100-VLOOKUP(B20,'[1]Pricing '!$A$140:$K$164,11,FALSE) -> 2.9310002 | D20: =C20-$V$18 -> 3.0560002 | E20: =E19+0.125 -> 5.5 | F20: =100-VLOOKUP(E20,'[1]Pricing '!$A$2034:$K$2059,11,FALSE) -> 3.0628427 | G20: =F20-$V$18 -> 3.1878427 | H20: =H19+0.125 -> 5.25 | I20: =100-VLOOKUP(H20,'[1]Pricing '!$A$353:$K$372,11,FALSE) -> 0.66179644 | J20: =I20-$V$18 -> 0.78679644 | K20: =K19+0.125 -> 5.25 | L20: =100-VLOOKUP(K20,'[1]Pricing '!$A$375:$K$394,11,FALSE) -> 0.93232517 | M20: =L20-$V$18 -> 1.0573252 | N20: =N19+0.125 -> 5.25 | O20: =100-VLOOKUP(N20,'[1]Pricing '!$A$397:$K$416,11,FALSE) -> 1.5031459 | P20: =O20-$V$18 -> 1.6281459
B21: =B20+0.125 -> 5.625 | C21: =100-VLOOKUP(B21,'[1]Pricing '!$A$140:$K$164,11,FALSE) -> 2.3090477 | D21: =C21-$V$18 -> 2.4340477 | E21: =E20+0.125 -> 5.625 | F21: =100-VLOOKUP(E21,'[1]Pricing '!$A$2034:$K$2059,11,FALSE) -> 2.4840853 | G21: =F21-$V$18 -> 2.6090853 | H21: =H20+0.125 -> 5.375 | I21: =100-VLOOKUP(H21,'[1]Pricing '!$A$353:$K$372,11,FALSE) -> 0.4461309 | J21: =I21-$V$18 -> 0.5711309 | K21: =K20+0.125 -> 5.375 | L21: =100-VLOOKUP(K21,'[1]Pricing '!$A$375:$K$394,11,FALSE) -> 0.65604786 | M21: =L21-$V$18 -> 0.78104786 | N21: =N20+0.125 -> 5.375 | O21: =100-VLOOKUP(N21,'[1]Pricing '!$A$397:$K$416,11,FALSE) -> 1.1581668 | P21: =O21-$V$18 -> 1.2831668
B22: =B21+0.125 -> 5.75 | C22: =100-VLOOKUP(B22,'[1]Pricing '!$A$140:$K$164,11,FALSE) -> 1.7066396 | D22: =C22-$V$18 -> 1.8316396 | E22: =E21+0.125 -> 5.75 | F22: =100-VLOOKUP(E22,'[1]Pricing '!$A$2034:$K$2059,11,FALSE) -> 1.9879593 | G22: =F22-$V$18 -> 2.1129593 | H22: =H21+0.125 -> 5.5 | I22: =100-VLOOKUP(H22,'[1]Pricing '!$A$353:$K$372,11,FALSE) -> 0.22122219 | J22: =I22-$V$18 -> 0.34622219 | K22: =K21+0.125 -> 5.5 | L22: =100-VLOOKUP(K22,'[1]Pricing '!$A$375:$K$394,11,FALSE) -> 0.4173028 | M22: =L22-$V$18 -> 0.5423028 | N22: =N21+0.125 -> 5.5 | O22: =100-VLOOKUP(N22,'[1]Pricing '!$A$397:$K$416,11,FALSE) -> 0.84129533 | P22: =O22-$V$18 -> 0.96629533
B23: =B22+0.125 -> 5.875 | C23: =100-VLOOKUP(B23,'[1]Pricing '!$A$140:$K$164,11,FALSE) -> 1.0933457 | D23: =C23-$V$18 -> 1.2183457 | E23: =E22+0.125 -> 5.875 | F23: =100-VLOOKUP(E23,'[1]Pricing '!$A$2034:$K$2059,11,FALSE) -> 1.4903091 | G23: =F23-$V$18 -> 1.6153091 | H23: =H22+0.125 -> 5.625 | I23: =100-VLOOKUP(H23,'[1]Pricing '!$A$353:$K$372,11,FALSE) -> -0.01757126 | J23: =I23-$V$18 -> 0.10742874 | K23: =K22+0.125 -> 5.625 | L23: =100-VLOOKUP(K23,'[1]Pricing '!$A$375:$K$394,11,FALSE) -> 0.23646566 | M23: =L23-$V$18 -> 0.36146566 | N23: =N22+0.125 -> 5.625 | O23: =100-VLOOKUP(N23,'[1]Pricing '!$A$397:$K$416,11,FALSE) -> 0.57159726 | P23: =O23-$V$18 -> 0.69659726
B24: =B23+0.125 -> 6 | C24: =100-VLOOKUP(B24,'[1]Pricing '!$A$140:$K$164,11,FALSE) -> 0.5054967 | D24: =C24-$V$18 -> 0.6304967 | E24: =E23+0.125 -> 6 | F24: =100-VLOOKUP(E24,'[1]Pricing '!$A$2034:$K$2059,11,FALSE) -> 1.0406448 | G24: =F24-$V$18 -> 1.1656448 | H24: =H23+0.125 -> 5.75 | I24: =100-VLOOKUP(H24,'[1]Pricing '!$A$353:$K$372,11,FALSE) -> -0.22346296 | J24: =I24-$V$18 -> -0.098462962 | K24: =K23+0.125 -> 5.75 | L24: =100-VLOOKUP(K24,'[1]Pricing '!$A$375:$K$394,11,FALSE) -> 0.017665656 | M24: =L24-$V$18 -> 0.14266566 | N24: =N23+0.125 -> 5.75 | O24: =100-VLOOKUP(N24,'[1]Pricing '!$A$397:$K$416,11,FALSE) -> 0.29982665 | P24: =O24-$V$18 -> 0.42482665
B25: =B24+0.125 -> 6.125 | C25: =100-VLOOKUP(B25,'[1]Pricing '!$A$140:$K$164,11,FALSE) -> -0.16116194 | D25: =C25-$V$18 -> -0.036161938 | E25: =E24+0.125 -> 6.125 | F25: =100-VLOOKUP(E25,'[1]Pricing '!$A$2034:$K$2059,11,FALSE) -> 0.6612071 | G25: =F25-$V$18 -> 0.7862071 | H25: =H24+0.125 -> 5.875 | I25: =100-VLOOKUP(H25,'[1]Pricing '!$A$353:$K$372,11,FALSE) -> -0.37795447 | J25: =I25-$V$18 -> -0.25295447 | K25: =K24+0.125 -> 5.875 | L25: =100-VLOOKUP(K25,'[1]Pricing '!$A$375:$K$394,11,FALSE) -> -0.24152908 | M25: =L25-$V$18 -> -0.11652908 | N25: =N24+0.125 -> 5.875 | O25: =100-VLOOKUP(N25,'[1]Pricing '!$A$397:$K$416,11,FALSE) -> 0.010726647 | P25: =O25-$V$18 -> 0.13572665
B26: =B25+0.125 -> 6.25 | C26: =100-VLOOKUP(B26,'[1]Pricing '!$A$140:$K$164,11,FALSE) -> -0.59983415 | D26: =C26-$V$18 -> -0.47483415 | E26: =E25+0.125 -> 6.25 | F26: =100-VLOOKUP(E26,'[1]Pricing '!$A$2034:$K$2059,11,FALSE) -> 0.078201697 | G26: =F26-$V$18 -> 0.2032017 | H26: =H25+0.125 -> 6 | I26: =100-VLOOKUP(H26,'[1]Pricing '!$A$353:$K$372,11,FALSE) -> -0.53523005 | J26: =I26-$V$18 -> -0.41023005 | K26: =K25+0.125 -> 6 | L26: =100-VLOOKUP(K26,'[1]Pricing '!$A$375:$K$394,11,FALSE) -> -0.41935656 | M26: =L26-$V$18 -> -0.29435656 | N26: =N25+0.125 -> 6 | O26: =100-VLOOKUP(N26,'[1]Pricing '!$A$397:$K$416,11,FALSE) -> -0.21250463 | P26: =O26-$V$18 -> -0.087504633
B27: =B26+0.125 -> 6.375 | C27: =100-VLOOKUP(B27,'[1]Pricing '!$A$140:$K$164,11,FALSE) -> -1.0909731 | D27: =C27-$V$18 -> -0.96597311 | E27: =E26+0.125 -> 6.375 | F27: =100-VLOOKUP(E27,'[1]Pricing '!$A$2034:$K$2059,11,FALSE) -> -0.27984573 | G27: =F27-$V$18 -> -0.15484573 | H27: =H26+0.125 -> 6.125 | I27: =100-VLOOKUP(H27,'[1]Pricing '!$A$353:$K$372,11,FALSE) -> -0.6954631 | J27: =I27-$V$18 -> -0.5704631 | K27: =K26+0.125 -> 6.125 | L27: =100-VLOOKUP(K27,'[1]Pricing '!$A$375:$K$394,11,FALSE) -> -0.46690183 | M27: =L27-$V$18 -> -0.34190183 | N27: =N26+0.125 -> 6.125 | O27: =100-VLOOKUP(N27,'[1]Pricing '!$A$397:$K$416,11,FALSE) -> -0.34107427 | P27: =O27-$V$18 -> -0.21607427
B28: =B27+0.125 -> 6.5 | C28: =100-VLOOKUP(B28,'[1]Pricing '!$A$140:$K$164,11,FALSE) -> -1.539458 | D28: =C28-$V$18 -> -1.414458 | E28: =E27+0.125 -> 6.5 | F28: =100-VLOOKUP(E28,'[1]Pricing '!$A$2034:$K$2059,11,FALSE) -> -0.57351537 | G28: =F28-$V$18 -> -0.44851537 | H28: =H27+0.125 -> 6.25 | I28: =100-VLOOKUP(H28,'[1]Pricing '!$A$353:$K$372,11,FALSE) -> -0.83675803 | J28: =I28-$V$18 -> -0.71175803 | K28: =K27+0.125 -> 6.25 | L28: =100-VLOOKUP(K28,'[1]Pricing '!$A$375:$K$394,11,FALSE) -> -0.52818396 | M28: =L28-$V$18 -> -0.40318396 | N28: =N27+0.125 -> 6.25 | O28: =100-VLOOKUP(N28,'[1]Pricing '!$A$397:$K$416,11,FALSE) -> -0.49634108 | P28: =O28-$V$18 -> -0.37134108
B29: =B28+0.125 -> 6.625 | C29: =100-VLOOKUP(B29,'[1]Pricing '!$A$140:$K$164,11,FALSE) -> -1.9353419 | D29: =C29-$V$18 -> -1.8103419 | E29: =E28+0.125 -> 6.625 | F29: =100-VLOOKUP(E29,'[1]Pricing '!$A$2034:$K$2059,11,FALSE) -> -0.76095543 | G29: =F29-$V$18 -> -0.63595543 | H29: =H28+0.125 -> 6.375 | I29: =100-VLOOKUP(H29,'[1]Pricing '!$A$353:$K$372,11,FALSE) -> -0.94885407 | J29: =I29-$V$18 -> -0.82385407 | K29: =K28+0.125 -> 6.375 | L29: =100-VLOOKUP(K29,'[1]Pricing '!$A$375:$K$394,11,FALSE) -> -0.60669182 | M29: =L29-$V$18 -> -0.48169182 | N29: =N28+0.125 -> 6.375 | O29: =100-VLOOKUP(N29,'[1]Pricing '!$A$397:$K$416,11,FALSE) -> -0.68405185 | P29: =O29-$V$18 -> -0.55905185
B30: =B29+0.125 -> 6.75 | C30: =100-VLOOKUP(B30,'[1]Pricing '!$A$140:$K$164,11,FALSE) -> -2.3352354 | D30: =C30-$V$18 -> -2.2102354 | E30: =E29+0.125 -> 6.75 | F30: =100-VLOOKUP(E30,'[1]Pricing '!$A$2034:$K$2059,11,FALSE) -> -1.1418148 | G30: =F30-$V$18 -> -1.0168148 | H30: =H29+0.125 -> 6.5 | I30: =100-VLOOKUP(H30,'[1]Pricing '!$A$353:$K$372,11,FALSE) -> -1.0470811 | J30: =I30-$V$18 -> -0.92208113 | K30: =K29+0.125 -> 6.5 | L30: =100-VLOOKUP(K30,'[1]Pricing '!$A$375:$K$394,11,FALSE) -> -0.70866036 | M30: =L30-$V$18 -> -0.58366036 | N30: =N29+0.125 -> 6.5 | O30: =100-VLOOKUP(N30,'[1]Pricing '!$A$397:$K$416,11,FALSE) -> -0.86185261 | P30: =O30-$V$18 -> -0.73685261
B31: =B30+0.125 -> 6.875 | C31: =100-VLOOKUP(B31,'[1]Pricing '!$A$140:$K$164,11,FALSE) -> -2.7594371 | D31: =C31-$V$18 -> -2.6344371 | E31: =E30+0.125 -> 6.875 | F31: =100-VLOOKUP(E31,'[1]Pricing '!$A$2034:$K$2059,11,FALSE) -> -1.4371035 | G31: =F31-$V$18 -> -1.3121035 | H31: =H30+0.125 -> 6.625 | I31: =100-VLOOKUP(H31,'[1]Pricing '!$A$353:$K$372,11,FALSE) -> -1.1167035 | J31: =I31-$V$18 -> -0.99170348 | K31: =K30+0.125 -> 6.625 | L31: =100-VLOOKUP(K31,'[1]Pricing '!$A$375:$K$394,11,FALSE) -> -0.83545899 | M31: =L31-$V$18 -> -0.71045899 | N31: =N30+0.125 -> 6.625 | O31: =100-VLOOKUP(N31,'[1]Pricing '!$A$397:$K$416,11,FALSE) -> -1.0164158 | P31: =O31-$V$18 -> -0.89141584
... B38: =B37+0.125 -> 7.75 | C38: =100-VLOOKUP(B38,'[1]Pricing '!$A$140:$K$164,11,FALSE) -> -3.9932265 | D38: =C38-$V$18 -> -3.8682265 | E38: =E37+0.125 -> 7.75 | F38: =100-VLOOKUP(E38,'[1]Pricing '!$A$2034:$K$2059,11,FALSE) -> -2.3888092 | G38: =F38-$V$18 -> -2.2638092 | H38: =H37+0.125 -> 7.5 | I38: =100-VLOOKUP(H38,'[1]Pricing '!$A$353:$K$372,11,FALSE) -> -1.1193032 | J38: =I38-$V$18 -> -0.99430315 | K38: =K37+0.125 -> 7.5 | L38: =100-VLOOKUP(K38,'[1]Pricing '!$A$375:$K$394,11,FALSE) -> -1.623018 | M38: =L38-$V$18 -> -1.498018 | N38: =N37+0.125 -> 7.5 | O38: =100-VLOOKUP(N38,'[1]Pricing '!$A$397:$K$416,11,FALSE) -> -1.2078674 | P38: =O38-$V$18 -> -1.0828674
B39: FREDDIE MAC HOMEPOSSIBLE CONFORMING & HIGH BALANCE- FIXED & ARM
B40: Conforming & High Balance FIXED | H40: CONFORMING ARMS
B41: (FM30HP) 30 YR | E41: (FMSC30HP) 30 YR | H41: (FM5/6 HP) 5YR ARM | K41: (FM7/6 HP) 7YR ARM | N41: (FM10/6 HP) 10YR ARM
B42: RATE | C42: 30 Days | D42: 45 Days | E42: RATE | F42: 30 Days | G42: 45 Days | H42: RATE | I42: 30 Days | J42: 45 Days | K42: RATE | L42: 30 Days | M42: 45 Days | N42: RATE | O42: 30 Days | P42: 45 Days
B43: 5.375 | C43: =100-VLOOKUP(B43,'[1]Pricing '!$A$2005:$K$2030,11,FALSE) -> 3.5436035 | D43: =C43-$V$18 -> 3.6686035 | E43: 5.375 | F43: =100-VLOOKUP(E43,'[1]Pricing '!$A$2211:$K$2235,11,FALSE) -> 3.8367835 | G43: =F43-$V$18 -> 3.9617835 | H43: 5.25 | I43: =100-VLOOKUP(H43,'[1]Pricing '!$A$485:$K$504,11,FALSE) -> 1.0787222 | J43: =I43-$V$18 -> 1.2037222 | K43: 5.25 | L43: =100-VLOOKUP(K43,'[1]Pricing '!$A$507:$K$526,11,FALSE) -> 1.0283479 | M43: =L43-$V$18 -> 1.1533479 | N43: 5.25 | O43: =100-VLOOKUP(N43,'[1]Pricing '!$A$529:$K$548,11,FALSE) -> 1.9070668 | P43: =O43-$V$18 -> 2.0320668
B44: =B43+0.125 -> 5.5 | C44: =100-VLOOKUP(B44,'[1]Pricing '!$A$2005:$K$2030,11,FALSE) -> 2.9679002 | D44: =C44-$V$18 -> 3.0929002 | E44: =E43+0.125 -> 5.5 | F44: =100-VLOOKUP(E44,'[1]Pricing '!$A$2211:$K$2235,11,FALSE) -> 3.2648427 | G44: =F44-$V$18 -> 3.3898427 | H44: =H43+0.125 -> 5.375 | I44: =100-VLOOKUP(H44,'[1]Pricing '!$A$485:$K$504,11,FALSE) -> 0.74712874 | J44: =I44-$V$18 -> 0.87212874 | K44: =K43+0.125 -> 5.375 | L44: =100-VLOOKUP(K44,'[1]Pricing '!$A$507:$K$526,11,FALSE) -> 0.6773028 | M44: =L44-$V$18 -> 0.8023028 | N44: =N43+0.125 -> 5.375 | O44: =100-VLOOKUP(N44,'[1]Pricing '!$A$529:$K$548,11,FALSE) -> 1.5196953 | P44: =O44-$V$18 -> 1.6446953
B45: =B44+0.125 -> 5.625 | C45: =100-VLOOKUP(B45,'[1]Pricing '!$A$2005:$K$2030,11,FALSE) -> 2.3826477 | D45: =C45-$V$18 -> 2.5076477 | E45: =E44+0.125 -> 5.625 | F45: =100-VLOOKUP(E45,'[1]Pricing '!$A$2211:$K$2235,11,FALSE) -> 2.6735853 | G45: =F45-$V$18 -> 2.7985853 | H45: =H44+0.125 -> 5.5 | I45: =100-VLOOKUP(H45,'[1]Pricing '!$A$485:$K$504,11,FALSE) -> 0.41303704 | J45: =I45-$V$18 -> 0.53803704 | K45: =K44+0.125 -> 5.5 | L45: =100-VLOOKUP(K45,'[1]Pricing '!$A$507:$K$526,11,FALSE) -> 0.46196566 | M45: =L45-$V$18 -> 0.58696566 | N45: =N44+0.125 -> 5.5 | O45: =100-VLOOKUP(N45,'[1]Pricing '!$A$529:$K$548,11,FALSE) -> 1.1371973 | P45: =O45-$V$18 -> 1.2621973
B46: =B45+0.125 -> 5.75 | C46: =100-VLOOKUP(B46,'[1]Pricing '!$A$2005:$K$2030,11,FALSE) -> 1.7095396 | D46: =C46-$V$18 -> 1.8345396 | E46: =E45+0.125 -> 5.75 | F46: =100-VLOOKUP(E46,'[1]Pricing '!$A$2211:$K$2235,11,FALSE) -> 2.0689593 | G46: =F46-$V$18 -> 2.1939593 | H46: =H45+0.125 -> 5.625 | I46: =100-VLOOKUP(H46,'[1]Pricing '!$A$485:$K$504,11,FALSE) -> 0.078845525 | J46: =I46-$V$18 -> 0.20384553 | K46: =K45+0.125 -> 5.625 | L46: =100-VLOOKUP(K46,'[1]Pricing '!$A$507:$K$526,11,FALSE) -> 0.20596566 | M46: =L46-$V$18 -> 0.33096566 | N46: =N45+0.125 -> 5.625 | O46: =100-VLOOKUP(N46,'[1]Pricing '!$A$529:$K$548,11,FALSE) -> 0.75682665 | P46: =O46-$V$18 -> 0.88182665
B47: =B46+0.125 -> 5.875 | C47: =100-VLOOKUP(B47,'[1]Pricing '!$A$2005:$K$2030,11,FALSE) -> 1.1567457 | D47: =C47-$V$18 -> 1.2817457 | E47: =E46+0.125 -> 5.875 | F47: =100-VLOOKUP(E47,'[1]Pricing '!$A$2211:$K$2235,11,FALSE) -> 1.5278091 | G47: =F47-$V$18 -> 1.6528091 | H47: =H46+0.125 -> 5.75 | I47: =100-VLOOKUP(H47,'[1]Pricing '!$A$485:$K$504,11,FALSE) -> -0.24113005 | J47: =I47-$V$18 -> -0.11613005 | K47: =K46+0.125 -> 5.75 | L47: =100-VLOOKUP(K47,'[1]Pricing '!$A$507:$K$526,11,FALSE) -> -0.068629076 | M47: =L47-$V$18 -> 0.056370924 | N47: =N46+0.125 -> 5.75 | O47: =100-VLOOKUP(N47,'[1]Pricing '!$A$529:$K$548,11,FALSE) -> 0.36582665 | P47: =O47-$V$18 -> 0.49082665
B48: =B47+0.125 -> 6 | C48: =100-VLOOKUP(B48,'[1]Pricing '!$A$2005:$K$2030,11,FALSE) -> 0.6788967 | D48: =C48-$V$18 -> 0.8038967 | E48: =E47+0.125 -> 6 | F48: =100-VLOOKUP(E48,'[1]Pricing '!$A$2211:$K$2235,11,FALSE) -> 1.0731448 | G48: =F48-$V$18 -> 1.1981448 | H48: =H47+0.125 -> 5.875 | I48: =100-VLOOKUP(H48,'[1]Pricing '!$A$485:$K$504,11,FALSE) -> -0.5362631 | J48: =I48-$V$18 -> -0.4112631 | K48: =K47+0.125 -> 5.875 | L48: =100-VLOOKUP(K48,'[1]Pricing '!$A$507:$K$526,11,FALSE) -> -0.35225656 | M48: =L48-$V$18 -> -0.22725656 | N48: =N47+0.125 -> 5.875 | O48: =100-VLOOKUP(N48,'[1]Pricing '!$A$529:$K$548,11,FALSE) -> -0.012704633 | P48: =O48-$V$18 -> 0.11229537
B49: =B48+0.125 -> 6.125 | C49: =100-VLOOKUP(B49,'[1]Pricing '!$A$2005:$K$2030,11,FALSE) -> 0.026538062 | D49: =C49-$V$18 -> 0.15153806 | E49: =E48+0.125 -> 6.125 | F49: =100-VLOOKUP(E49,'[1]Pricing '!$A$2211:$K$2235,11,FALSE) -> 0.6617071 | G49: =F49-$V$18 -> 0.7867071 | H49: =H48+0.125 -> 6 | I49: =100-VLOOKUP(H49,'[1]Pricing '!$A$485:$K$504,11,FALSE) -> -0.83025803 | J49: =I49-$V$18 -> -0.70525803 | K49: =K48+0.125 -> 6 | L49: =100-VLOOKUP(K49,'[1]Pricing '!$A$507:$K$526,11,FALSE) -> -0.61010183 | M49: =L49-$V$18 -> -0.48510183 | N49: =N48+0.125 -> 6 | O49: =100-VLOOKUP(N49,'[1]Pricing '!$A$529:$K$548,11,FALSE) -> -0.38567427 | P49: =O49-$V$18 -> -0.26067427
B50: =B49+0.125 -> 6.25 | C50: =100-VLOOKUP(B50,'[1]Pricing '!$A$2005:$K$2030,11,FALSE) -> -0.36293415 | D50: =C50-$V$18 -> -0.23793415 | E50: =E49+0.125 -> 6.25 | F50: =100-VLOOKUP(E50,'[1]Pricing '!$A$2211:$K$2235,11,FALSE) -> 0.1976017 | G50: =F50-$V$18 -> 0.3226017 | H50: =H49+0.125 -> 6.125 | I50: =100-VLOOKUP(H50,'[1]Pricing '!$A$485:$K$504,11,FALSE) -> -1.1231541 | J50: =I50-$V$18 -> -0.99815407 | K50: =K49+0.125 -> 6.125 | L50: =100-VLOOKUP(K50,'[1]Pricing '!$A$507:$K$526,11,FALSE) -> -0.89618396 | M50: =L50-$V$18 -> -0.77118396 | N50: =N49+0.125 -> 6.125 | O50: =100-VLOOKUP(N50,'[1]Pricing '!$A$529:$K$548,11,FALSE) -> -0.76344108 | P50: =O50-$V$18 -> -0.63844108
B51: =B50+0.125 -> 6.375 | C51: =100-VLOOKUP(B51,'[1]Pricing '!$A$2005:$K$2030,11,FALSE) -> -0.91057311 | D51: =C51-$V$18 -> -0.78557311 | E51: =E50+0.125 -> 6.375 | F51: =100-VLOOKUP(E51,'[1]Pricing '!$A$2211:$K$2235,11,FALSE) -> -0.19264573 | G51: =F51-$V$18 -> -0.067645734 | H51: =H50+0.125 -> 6.25 | I51: =100-VLOOKUP(H51,'[1]Pricing '!$A$485:$K$504,11,FALSE) -> -1.3236811 | J51: =I51-$V$18 -> -1.1986811 | K51: =K50+0.125 -> 6.25 | L51: =100-VLOOKUP(K51,'[1]Pricing '!$A$507:$K$526,11,FALSE) -> -1.1207918 | M51: =L51-$V$18 -> -0.99579182 | N51: =N50+0.125 -> 6.25 | O51: =100-VLOOKUP(N51,'[1]Pricing '!$A$529:$K$548,11,FALSE) -> -1.0438519 | P51: =O51-$V$18 -> -0.91885185
B52: =B51+0.125 -> 6.5 | C52: =100-VLOOKUP(B52,'[1]Pricing '!$A$2005:$K$2030,11,FALSE) -> -1.400558 | D52: =C52-$V$18 -> -1.275558 | E52: =E51+0.125 -> 6.5 | F52: =100-VLOOKUP(E52,'[1]Pricing '!$A$2211:$K$2235,11,FALSE) -> -0.44611537 | G52: =F52-$V$18 -> -0.32111537 | H52: =H51+0.125 -> 6.375 | I52: =100-VLOOKUP(H52,'[1]Pricing '!$A$485:$K$504,11,FALSE) -> -1.3524035 | J52: =I52-$V$18 -> -1.2274035 | K52: =K51+0.125 -> 6.375 | L52: =100-VLOOKUP(K52,'[1]Pricing '!$A$507:$K$526,11,FALSE) -> -1.3117604 | M52: =L52-$V$18 -> -1.1867604 | N52: =N51+0.125 -> 6.375 | O52: =100-VLOOKUP(N52,'[1]Pricing '!$A$529:$K$548,11,FALSE) -> -1.1527526 | P52: =O52-$V$18 -> -1.0277526
B53: =B52+0.125 -> 6.625 | C53: =100-VLOOKUP(B53,'[1]Pricing '!$A$2005:$K$2030,11,FALSE) -> -1.7441419 | D53: =C53-$V$18 -> -1.6191419 | E53: =E52+0.125 -> 6.625 | F53: =100-VLOOKUP(E53,'[1]Pricing '!$A$2211:$K$2235,11,FALSE) -> -0.71325543 | G53: =F53-$V$18 -> -0.58825543 | H53: =H52+0.125 -> 6.5 | I53: =100-VLOOKUP(H53,'[1]Pricing '!$A$485:$K$504,11,FALSE) -> -1.388735 | J53: =I53-$V$18 -> -1.263735 | K53: =K52+0.125 -> 6.5 | L53: =100-VLOOKUP(K53,'[1]Pricing '!$A$507:$K$526,11,FALSE) -> -1.475159 | M53: =L53-$V$18 -> -1.350159 | N53: =N52+0.125 -> 6.5 | O53: =100-VLOOKUP(N53,'[1]Pricing '!$A$529:$K$548,11,FALSE) -> -1.2524158 | P53: =O53-$V$18 -> -1.1274158
B54: =B53+0.125 -> 6.75 | C54: =100-VLOOKUP(B54,'[1]Pricing '!$A$2005:$K$2030,11,FALSE) -> -2.1060354 | D54: =C54-$V$18 -> -1.9810354 | E54: =E53+0.125 -> 6.75 | F54: =100-VLOOKUP(E54,'[1]Pricing '!$A$2211:$K$2235,11,FALSE) -> -0.70061475 | G54: =F54-$V$18 -> -0.57561475 | H54: =H53+0.125 -> 6.625 | I54: =100-VLOOKUP(H54,'[1]Pricing '!$A$485:$K$504,11,FALSE) -> -1.4244903 | J54: =I54-$V$18 -> -1.2994903 | K54: =K53+0.125 -> 6.625 | L54: =100-VLOOKUP(K54,'[1]Pricing '!$A$507:$K$526,11,FALSE) -> -1.6410748 | M54: =L54-$V$18 -> -1.5160748 | N54: =N53+0.125 -> 6.625 | O54: =100-VLOOKUP(N54,'[1]Pricing '!$A$529:$K$548,11,FALSE) -> -1.3603509 | P54: =O54-$V$18 -> -1.2353509
B55: =B54+0.125 -> 6.875 | C55: =100-VLOOKUP(B55,'[1]Pricing '!$A$2005:$K$2030,11,FALSE) -> -2.6096371 | D55: =C55-$V$18 -> -2.4846371 | E55: =E54+0.125 -> 6.875 | F55: =100-VLOOKUP(E55,'[1]Pricing '!$A$2211:$K$2235,11,FALSE) -> -1.2537035 | G55: =F55-$V$18 -> -1.1287035 | H55: =H54+0.125 -> 6.75 | I55: =100-VLOOKUP(H55,'[1]Pricing '!$A$485:$K$504,11,FALSE) -> -1.424609 | J55: =I55-$V$18 -> -1.299609 | K55: =K54+0.125 -> 6.75 | L55: =100-VLOOKUP(K55,'[1]Pricing '!$A$507:$K$526,11,FALSE) -> -1.7943 | M55: =L55-$V$18 -> -1.6693 | N55: =N54+0.125 -> 6.75 | O55: =100-VLOOKUP(N55,'[1]Pricing '!$A$529:$K$548,11,FALSE) -> -1.284147 | P55: =O55-$V$18 -> -1.159147
... B61: =B60+0.125 -> 7.625 | C61: =100-VLOOKUP(B61,'[1]Pricing '!$A$2005:$K$2030,11,FALSE) -> -4.8987203 | D61: =C61-$V$18 -> -4.7737203 | E61: =E60+0.125 -> 7.625 | F61: =100-VLOOKUP(E61,'[1]Pricing '!$A$2211:$K$2235,11,FALSE) -> -2.5238846 | G61: =F61-$V$18 -> -2.3988846 | H61: =H60+0.125 -> 7.5 | I61: =100-VLOOKUP(H61,'[1]Pricing '!$A$485:$K$504,11,FALSE) -> -1.6271161 | J61: =I61-$V$18 -> -1.5021161 | K61: =K60+0.125 -> 7.5 | L61: =100-VLOOKUP(K61,'[1]Pricing '!$A$507:$K$526,11,FALSE) -> -1.171829 | M61: =L61-$V$18 -> -1.046829 | N61: =N60+0.125 -> 7.5 | O61: =100-VLOOKUP(N61,'[1]Pricing '!$A$529:$K$548,11,FALSE) -> 0.14907129 | P61: =O61-$V$18 -> 0.27407129
B62: =B61+0.125 -> 7.75 | C62: =100-VLOOKUP(B62,'[1]Pricing '!$A$2005:$K$2030,11,FALSE) -> -4.0991265 | D62: =C62-$V$18 -> -3.9741265 | E62: =E61+0.125 -> 7.75 | F62: =100-VLOOKUP(E62,'[1]Pricing '!$A$2211:$K$2235,11,FALSE) -> -2.0817092 | G62: =F62-$V$18 -> -1.9567092
B63: Purchase(Loan terms > 15 YR) | L63: HomeReady product codes:
B64: FICO/LTV | C64: ≤30 | D64: 30.01-60 | E64: 60.01-70 | F64: 70.01-75 | G64: 75.01-80 | H64: 80.01-85 | I64: 85.01-90 | J64: 90.01-95 | K64: >95 | L64: (LPMI) Product Codes:
B65: ≥800 | C65: 0 | D65: 0 | E65: 0 | F65: 0 | G65: 0.375 | H65: 0.375 | I65: 0.25 | J65: 0.25 | K65: 0.125 | L65: FCF30HRLPMI
B66: 780-799 | C66: 0 | D66: 0 | E66: 0 | F66: 0 | G66: 0.375 | H66: 0.375 | I66: 0.25 | J66: 0.25 | K66: 0.125 | L66: FCF30HRHB LPMI
B67: 760-779 | C67: 0 | D67: 0 | E67: 0 | F67: 0.25 | G67: 0.625 | H67: 0.625 | I67: 0.5 | J67: 0.5 | K67: 0.25 | L67: (BPMI) Product code:
B68: 740-759 | C68: 0 | D68: 0 | E68: 0.125 | F68: 0.375 | G68: 0.875 | H68: 1 | I68: 0.75 | J68: 0.625 | K68: 0.5 | L68: FCF30HR
B69: 720-739 | C69: 0 | D69: 0 | E69: 0.25 | F69: 0.75 | G69: 1.25 | H69: 1.25 | I69: 1 | J69: 0.875 | K69: 0.75 | L69: (HomeReady Enhancement) Product code:
B70: 700-719 | C70: 0 | D70: 0 | E70: 0.375 | F70: 0.875 | G70: 1.375 | H70: 1.5 | I70: 1.25 | J70: 1.125 | K70: 0.875 | L70: CA5/6HR-E CA7/6HR-E CA10/6HR-E
B71: 680-699 | C71: 0 | D71: 0 | E71: 0.625 | F71: 1.125 | G71: 1.75 | H71: 1.875 | I71: 1.5 | J71: 1.375 | K71: 1.125 | L71: FCF30HRHB-E
B72: 660-679 | C72: 0 | D72: 0 | E72: 0.75 | F72: 1.375 | G72: 1.875 | H72: 2.125 | I72: 1.75 | J72: 1.625 | K72: 1.25 | L72: FCF30HR-E
B73: 640-659 | C73: 0 | D73: 0 | E73: 1.125 | F73: 1.5 | G73: 2.25 | H73: 2.5 | I73: 2 | J73: 1.875 | K73: 1.5
B74: 620-639 | C74: 0 | D74: 0.125 | E74: 1.5 | F74: 2.125 | G74: 2.75 | H74: 2.875 | I74: 2.625 | J74: 2.25 | K74: 1.75 | L74: HomePossible product codes:
B75: Purchase Loan Additional (all amortization terms) | L75: (HomePossible Enhancement) Product code:
B76: LTV | C76: ≤30 | D76: 30.01-60 | E76: 60.01-70 | F76: 70.01-75 | G76: 75.01-80 | H76: 80.01-85 | I76: 85.01-90 | J76: 90.01-95 | K76: >95 | L76: FM5/6HP-E FM7/6HP-E FM10/6HP-E
B77: ARMs | C77: 0 | D77: 0 | E77: 0 | F77: 0 | G77: 0 | H77: 0 | I77: 0 | J77: 0.25 | K77: N/A | L77: FM30HP-E
B78: Attached Condo | C78: 0 | D78: 0 | E78: 0.125 | F78: 0.125 | G78: 0.75 | H78: 0.75 | I78: 0.75 | J78: 0.75 | K78: 0.75 | L78: FMSC30 HP-E
B79: 2-4 Units | C79: 0 | D79: 0 | E79: 0.375 | F79: 0.375 | G79: 0.625 | H79: 0.625 | I79: 0.875 | J79: 0.875 | K79: N/A | L79: (LPMI) Product Codes:
B80: N/O/O | C80: 1.125 | D80: 1.125 | E80: 1.625 | F80: 2.125 | G80: 3.375 | H80: 4.125 | I80: N/A | J80: N/A | K80: N/A | L80: FM30HPLPMI
B81: Second Homes | C81: 1.125 | D81: 1.125 | E81: 1.625 | F81: 2.125 | G81: 3.375 | H81: 4.125 | I81: 4.125 | J81: N/A | K81: N/A | L81: FMSC30HPLPMI
B82: Sub Financing | C82: 0.625 | D82: 0.625 | E82: 0.625 | F82: 0.875 | G82: 1.125 | H82: 1.125 | I82: 1.125 | J82: 1.875 | K82: 1.875 | L82: (BPMI) Product Codes:
B83: HighBal Fixed | C83: 0.5 | D83: 0.5 | E83: 0.75 | F83: 0.75 | G83: 1 | H83: 1 | I83: 1 | J83: 1 | K83: 1 | L83: FM30HP
B84: HighBal ARM | C84: 1.25 | D84: 1.25 | E84: 1.5 | F84: 1.5 | G84: 2.5 | H84: 2.5 | I84: 2.5 | J84: 2.75 | K84: N/A | L84: FMSC30HP
B85: Baltimore County-MD | C85: 0.25 | D85: 0.25 | E85: 0.25 | F85: 0.375 | G85: 0.375 | H85: 0.5 | I85: 0.5 | J85: 0.5 | K85: 0.5
B86: Rate&Term (Loan terms > 15 YR) | L86: MAX PRICE ON FIXED PROG
B87: FICO/LTV | C87: ≤30 | D87: 30.01-60 | E87: 60.01-70 | F87: 70.01-75 | G87: 75.01-80 | H87: 80.01-85 | I87: 85.01-90 | J87: 90.01-95 | K87: >95 | L87: 0.04
B88: ≥800 | C88: 0 | D88: 0 | E88: 0 | F88: 0.125 | G88: 0.5 | H88: 0.625 | I88: 0.5 | J88: 0.375 | K88: 0.375 | L88: MAX PRICE ON ARM PROG
B89: 780-799 | C89: 0 | D89: 0 | E89: 0 | F89: 0.125 | G89: 0.5 | H89: 0.625 | I89: 0.5 | J89: 0.375 | K89: 0.375 | L89: 0.03
B90: 760-779 | C90: 0 | D90: 0 | E90: 0.125 | F90: 0.375 | G90: 0.875 | H90: 1 | I90: 0.75 | J90: 0.625 | K90: 0.625 | L90: ARM INFORMATION
B91: 740-759 | C91: 0 | D91: 0 | E91: 0.25 | F91: 0.75 | G91: 1.125 | H91: 1.375 | I91: 1.125 | J91: 1 | K91: 1 | L91: LOAN TERM- 30YR AMORTIZATION
B92: 720-739 | C92: 0 | D92: 0 | E92: 0.5 | F92: 1 | G92: 1.625 | H92: 1.75 | I92: 1.5 | J92: 1.25 | K92: 1.25 | L92: FIXED PERIOD- 5/6,7/6 & 10/6
B93: 700-719 | C93: 0 | D93: 0 | E93: 0.625 | F93: 1.25 | G93: 1.875 | H93: 2.125 | I93: 1.75 | J93: 1.625 | K93: 1.625 | L93: MARGIN- 3.00%
B94: 680-699 | C94: 0 | D94: 0 | E94: 0.875 | F94: 1.625 | G94: 2.25 | H94: 2.5 | I94: 2.125 | J94: 1.75 | K94: 1.75 | L94: INDEX- SOFR 30-DAY AVG
B95: 660-679 | C95: 0 | D95: 0.125 | E95: 1.125 | F95: 1.875 | G95: 2.5 | H95: 3 | I95: 2.375 | J95: 2.125 | K95: 2.125 | L95: CAPS: 5/6 = 2/1/5
B96: 640-659 | C96: 0 | D96: 0.25 | E96: 1.375 | F96: 2.125 | G96: 2.875 | H96: 3.375 | I96: 2.875 | J96: 2.5 | K96: 2.5 | L96: 7/6= 5/1/5
B97: 620-639 | C97: 0 | D97: 0.375 | E97: 1.75 | F97: 2.5 | G97: 3.5 | H97: 3.875 | I97: 3.625 | J97: 2.5 | K97: 2.5 | L97: 10/6= 5/1/5
B98: Rate&Term Additional (all amortization terms) | L98: Cumulative LLPA Caps
B99: LTV | C99: ≤30 | D99: 30.01-60 | E99: 60.01-70 | F99: 70.01-75 | G99: 75.01-80 | H99: 80.01-85 | I99: 85.01-90 | J99: 90.01-95 | K99: >95 | L99: HomeReady & HomePossible | O99: ALL LTV's
B100: ARMs | C100: 0 | D100: 0 | E100: 0 | F100: 0 | G100: 0 | H100: 0 | I100: 0 | J100: 0.25 | K100: N/A
B101: Attached Condo | C101: 0 | D101: 0 | E101: 0.125 | F101: 0.125 | G101: 0.75 | H101: 0.75 | I101: 0.75 | J101: 0.75 | K101: 0.75 | O101: 0
B102: 2-4 Units | C102: 0 | D102: 0 | E102: 0.375 | F102: 0.375 | G102: 0.625 | H102: 0.625 | I102: 0.875 | J102: 0.875 | K102: N/A | L102: **(Excluded from Cumulative Cap- Loan amts ,lock term
B103: N/O/O | C103: 1.125 | D103: 1.125 | E103: 1.625 | F103: 2.125 | G103: 3.375 | H103: 4.125 | I103: N/A | J103: N/A | K103: N/A | L103: & State Adjuster)
B104: Second Homes | C104: 1.125 | D104: 1.125 | E104: 1.625 | F104: 2.125 | G104: 3.375 | H104: 4.125 | I104: 4.125 | J104: N/A | K104: N/A
B105: Sub Financing | C105: 0.625 | D105: 0.625 | E105: 0.625 | F105: 0.875 | G105: 1.125 | H105: 1.125 | I105: 1.125 | J105: 1.875 | K105: 1.875 | L105: State Adjuster (FIXED Program)
B106: HighBal Fixed | C106: 0.5 | D106: 0.5 | E106: 0.75 | F106: 0.75 | G106: 1 | H106: 1 | I106: 1 | J106: 1 | K106: N/A | L106: Group 1 | O106: 30/20Y | P106: 15/10Y
B107: HighBal ARM | C107: 1.25 | D107: 1.25 | E107: 1.5 | F107: 1.5 | G107: 2.5 | H107: 2.5 | I107: 2.5 | J107: 2.75 | K107: N/A | L107: TX | O107: -0.125 | P107: -0.125
B108: Baltimore County-MD | C108: 0.25 | D108: 0.25 | E108: 0.25 | F108: 0.375 | G108: 0.375 | H108: 0.5 | I108: 0.5 | J108: 0.5 | K108: 0.5
B109: ADDITIONAL ADJUSTMENTS | L109: IMPOUNDS/ ESCROW
B110: Loan Amt $50,000- $74,999 | K110: 1.5 | L110: • Impounds/Escrows may be waived per state law
B111: Loan Amt $75,000 to $99,999 | K111: 0.75 | L111: • HPML loans must be impounded
B112: Loan Amt $100,000 to $149,999 | K112: 0.125 | L112: • Any loans requiring flood insurance must include flood
B113: Texas 50 A (6) | K113: 0.125 | L113: insurance must include in the borrower(s)’ escrow account
B114: 1 YR tax return >90% LTV (self-employment) | K114: 0.25 | L114: even if no other escrows are collected or escrows have been
...

Sheet CES
P1: 6 of 11
B2: AmWest Corporate Office | N2: Lock Expiration Dates
B3: 6 Pointe Dr. Suite 300
B4: Brea, CA 92821 | N4: 30 Day Lock | P4: =[2]FNMA!P4 -> 45980
B5: (714) 831-3333 | N5: 45 Day Lock | P5: =[2]FNMA!P5 -> 45995
B6: www.amwestwholesale.com | N6: 60 Day Lock | P6: =[2]FNMA!P6 -> 46010
F7: Wholesale Rate sheet - Consumer Paid | J7: Effective: | L7: =[2]FNMA!L7 -> 45950 | M7: =[2]FNMA!M7 -> 8:00 AM PST
B9: LOAN LOCK INFO:
B11: Lock Desk : | D11: Email: Lockdesk@amwestfunding.com | H11: Phone: (714) 831-3299 | K11: eFax: (714) 421-4032 | M11: Lock Hours: 8:30AM-5:00 PM PST
B12: ANNOUNCEMENT | T12: 45 DAY LOCK
T13: 0.25
B16: CLOSED-END SECOND- (FULL DOC)
B19: Click For Guideline | E19: HCLTV | F19: 0.00-55 | G19: 55.01-60 | H19: 60.01-65 | I19: 65.01-70 | J19: 70.01-75 | K19: 75.01-80 | L19: 80.01-85 | M19: 85.01-89.99 | N19: CES - FULL DOC
B20: FULL DOC | E20: FICO/CLTV Price Adjustments | N20: HIGHLIGHTS
B21: (CES30) 30 YR | E21: 780-850 | F21: -2.5 | G21: -2 | H21: -2 | I21: -1.5 | J21: -0.5 | K21: 0 | L21: 3.5 | M21: 4.5
B22: RATE | C22: 30 Days | D22: 45 Days | E22: 760-779 | F22: -1.5 | G22: -1.5 | H22: -1.5 | I22: -1 | J22: 0 | K22: 1 | L22: 5 | M22: 6 | N22: • Fixed Rate Closed Ended
B23: 6.875 | C23: =100-VLOOKUP(B23,'[1]Pricing '!$A$4302:$K$4337,11,FALSE) -> 2.898666 | D23: =C23+$T$13 -> 3.148666 | E23: 740-759 | F23: -1 | G23: -1 | H23: -1 | I23: 0 | J23: 0 | K23: 2 | L23: 6 | M23: 8 | N23: 2nd Mortgage
B24: =B23+0.125 -> 7 | C24: =100-VLOOKUP(B24,'[1]Pricing '!$A$4302:$K$4337,11,FALSE) -> 2.425665 | D24: =C24+$T$13 -> 2.675665 | E24: 720-739 | F24: 0 | G24: 0 | H24: 0 | I24: 0 | J24: 1 | K24: 3 | L24: 7.5 | M24: N/A
B25: =B24+0.125 -> 7.125 | C25: =100-VLOOKUP(B25,'[1]Pricing '!$A$4302:$K$4337,11,FALSE) -> 1.943602 | D25: =C25+$T$13 -> 2.193602 | E25: 700-719 | F25: 0.5 | G25: 0.5 | H25: 1 | I25: 1.5 | J25: 2 | K25: 5.5 | L25: 8.5 | M25: N/A
B26: =B25+0.125 -> 7.25 | C26: =100-VLOOKUP(B26,'[1]Pricing '!$A$4302:$K$4337,11,FALSE) -> 1.452262 | D26: =C26+$T$13 -> 1.702262 | E26: 680-699 | F26: 0.75 | G26: 1 | H26: 1.5 | I26: 2 | J26: 3 | K26: N/A | L26: N/A | M26: N/A | N26: • Stand-alone
B27: =B26+0.125 -> 7.375 | C27: =100-VLOOKUP(B27,'[1]Pricing '!$A$4302:$K$4337,11,FALSE) -> 0.961637 | D27: =C27+$T$13 -> 1.211637 | E27: PROPERTY TYPE
B28: =B27+0.125 -> 7.5 | C28: =100-VLOOKUP(B28,'[1]Pricing '!$A$4302:$K$4337,11,FALSE) -> 0.462246 | D28: =C28+$T$13 -> 0.712246 | E28: 2-4 UNIT | F28: 0.5 | G28: 0.5 | H28: 0.5 | I28: 0.5 | J28: 0.5 | K28: N/A | L28: N/A | M28: N/A | N28: • No Prepayment Penalty
B29: =B28+0.125 -> 7.625 | C29: =100-VLOOKUP(B29,'[1]Pricing '!$A$4302:$K$4337,11,FALSE) -> -0.034567 | D29: =C29+$T$13 -> 0.215433 | E29: CONDO | F29: 0.25 | G29: 0.25 | H29: 0.25 | I29: 0.25 | J29: 0.25 | K29: 0.25 | L29: N/A | M29: N/A
B30: =B29+0.125 -> 7.75 | C30: =100-VLOOKUP(B30,'[1]Pricing '!$A$4302:$K$4337,11,FALSE) -> -0.536898 | D30: =C30+$T$13 -> -0.286898 | E30: OCCUPANCY | N30: • Primary, 2nd Home
B31: =B30+0.125 -> 7.875 | C31: =100-VLOOKUP(B31,'[1]Pricing '!$A$4302:$K$4337,11,FALSE) -> -1.029894 | D31: =C31+$T$13 -> -0.779894 | E31: NOO | F31: 2 | G31: 2.5 | H31: 3 | I31: 3.5 | J31: 4 | K31: N/A | L31: N/A | M31: N/A | N31: & Investment Properties
B32: =B31+0.125 -> 8 | C32: =100-VLOOKUP(B32,'[1]Pricing '!$A$4302:$K$4337,11,FALSE) -> -1.487166 | D32: =C32+$T$13 -> -1.237166 | E32: 2ND HOME | F32: 1 | G32: 1 | H32: 1 | I32: 1 | J32: 1 | K32: N/A | L32: N/A | M32: N/A
B33: =B32+0.125 -> 8.125 | C33: =100-VLOOKUP(B33,'[1]Pricing '!$A$4302:$K$4337,11,FALSE) -> -1.983175 | D33: =C33+$T$13 -> -1.733175 | E33: Baltimore County-MD | F33: 0.25 | G33: 0.25 | H33: 0.25 | I33: 0.25 | J33: 0.375 | K33: 0.375 | L33: 0.5 | M33: 0.5 | N33: • Up to 89.99% CLTVs
B34: =B33+0.125 -> 8.25 | C34: =100-VLOOKUP(B34,'[1]Pricing '!$A$4302:$K$4337,11,FALSE) -> -2.4905 | D34: =C34+$T$13 -> -2.2405
B35: =B34+0.125 -> 8.375 | C35: =100-VLOOKUP(B35,'[1]Pricing '!$A$4302:$K$4337,11,FALSE) -> -2.988193 | D35: =C35+$T$13 -> -2.738193 | E35: TERM | N35: • Min. 680 Fico
B36: =B35+0.125 -> 8.5 | C36: =100-VLOOKUP(B36,'[1]Pricing '!$A$4302:$K$4337,11,FALSE) -> -3.48673 | D36: =C36+$T$13 -> -3.23673 | E36: 20YR | G36: 0
B37: =B36+0.125 -> 8.625 | C37: =100-VLOOKUP(B37,'[1]Pricing '!$A$4302:$K$4337,11,FALSE) -> -3.975477 | D37: =C37+$T$13 -> -3.725477 | E37: 10YR | G37: 0 | N37: • Min. Loan Amount of $75,000
B38: =B37+0.125 -> 8.75 | C38: =100-VLOOKUP(B38,'[1]Pricing '!$A$4302:$K$4337,11,FALSE) -> -4.465118 | D38: =C38+$T$13 -> -4.215118 | J38: MAX PRICE
B39: =B38+0.125 -> 8.875 | C39: =100-VLOOKUP(B39,'[1]Pricing '!$A$4302:$K$4337,11,FALSE) -> -4.949543 | D39: =C39+$T$13 -> -4.699543 | J39: -2.5 | N39: • Max. DTI 50%
B40: =B39+0.125 -> 9 | C40: =100-VLOOKUP(B40,'[1]Pricing '!$A$4302:$K$4337,11,FALSE) -> -5.404691 | D40: =C40+$T$13 -> -5.154691 | E40: PRODUCT CODES
B41: =B40+0.125 -> 9.125 | C41: =100-VLOOKUP(B41,'[1]Pricing '!$A$4302:$K$4337,11,FALSE) -> -5.850573 | D41: =C41+$T$13 -> -5.600573 | E41: 30YR | G41: CES30 | N41: • Property Type
B42: =B41+0.125 -> 9.25 | C42: =100-VLOOKUP(B42,'[1]Pricing '!$A$4302:$K$4337,11,FALSE) -> -6.302466 | D42: =C42+$T$13 -> -6.052466 | E42: 20YR | G42: CES20
B43: =B42+0.125 -> 9.375 | C43: =100-VLOOKUP(B43,'[1]Pricing '!$A$4302:$K$4337,11,FALSE) -> -6.747828 | D43: =C43+$T$13 -> -6.497828 | E43: 10YR | G43: CES10
B44: =B43+0.125 -> 9.5 | C44: =100-VLOOKUP(B44,'[1]Pricing '!$A$4302:$K$4337,11,FALSE) -> -7.197737 | D44: =C44+$T$13 -> -6.947737
B45: =B44+0.125 -> 9.625 | C45: =100-VLOOKUP(B45,'[1]Pricing '!$A$4302:$K$4337,11,FALSE) -> -7.640587 | D45: =C45+$T$13 -> -7.390587 | N45: 1-4 Units
B46: =B45+0.125 -> 9.75 | C46: =100-VLOOKUP(B46,'[1]Pricing '!$A$4302:$K$4337,11,FALSE) -> -8.07608 | D46: =C46+$T$13 -> -7.82608 | N46: SFR
B47: =B46+0.125 -> 9.875 | C47: =100-VLOOKUP(B47,'[1]Pricing '!$A$4302:$K$4337,11,FALSE) -> -8.513392 | D47: =C47+$T$13 -> -8.263392 | N47: PUDS
B48: =B47+0.125 -> 10 | C48: =100-VLOOKUP(B48,'[1]Pricing '!$A$4302:$K$4337,11,FALSE) -> -8.952749 | D48: =C48+$T$13 -> -8.702749 | N48: CONDOS
B51: **Lender Paid Compensation and Borrower Paid Compensation Allowed**
B52: CLOSED-END SECOND- (ALT DOC)
B54: Click For Guideline
B55: (CES20) 20 YR | E55: CLTV | G55: 0.00-50 | H55: 50.01-55 | I55: 55.01-60 | J55: 60.01-65 | K55: 65.01-70 | L55: 70.01-75 | M55: 75.01-80
B56: RATE | C56: 30 Days | D56: 45 Days | E56: Bank Statement FICO/CLTV Price Adjustments
B57: 7.375 | C57: =100-VLOOKUP(B57,'[1]Pricing '!$A$4521:$K$4553,11,FALSE) -> 4.84 | D57: =C57+0.25 -> 5.09 | E57: 780+ | G57: -1.75 | H57: -1.75 | I57: -1.75 | J57: -1.75 | K57: -1.625 | L57: -0.5 | M57: 0.375 | N57: CES - ALT DOC
B58: =B57+0.125 -> 7.5 | C58: =100-VLOOKUP(B58,'[1]Pricing '!$A$4521:$K$4553,11,FALSE) -> 4.215 | D58: =C58+0.25 -> 4.465 | E58: 760-779 | G58: -1.625 | H58: -1.625 | I58: -1.625 | J58: -1.625 | K58: -1.5 | L58: -0.25 | M58: 0.625 | N58: HIGHLIGHTS
B59: =B58+0.125 -> 7.625 | C59: =100-VLOOKUP(B59,'[1]Pricing '!$A$4521:$K$4553,11,FALSE) -> 3.59 | D59: =C59+0.25 -> 3.84 | E59: 740-759 | G59: -1.5 | H59: -1.375 | I59: -1.375 | J59: -1.375 | K59: -1.25 | L59: 0.75 | M59: 1.875
B60: =B59+0.125 -> 7.75 | C60: =100-VLOOKUP(B60,'[1]Pricing '!$A$4521:$K$4553,11,FALSE) -> 2.965 | D60: =C60+0.25 -> 3.215 | E60: 720-739 | G60: -1 | H60: -0.875 | I60: -0.75 | J60: -0.75 | K60: -0.625 | L60: 1.25 | M60: 2.5 | N60: • Fixed Rate Closed
B61: =B60+0.125 -> 7.875 | C61: =100-VLOOKUP(B61,'[1]Pricing '!$A$4521:$K$4553,11,FALSE) -> 2.465 | D61: =C61+0.25 -> 2.715 | E61: 700-719 | G61: 0 | H61: 0.125 | I61: 0.5 | J61: 1 | K61: 1.75 | L61: 2 | M61: 2.75 | N61: Ended 2nd Mortgage
B62: =B61+0.125 -> 8 | C62: =100-VLOOKUP(B62,'[1]Pricing '!$A$4521:$K$4553,11,FALSE) -> 1.965 | D62: =C62+0.25 -> 2.215 | E62: 680-699 | G62: 0.625 | H62: 1.125 | I62: 1.5 | J62: 2.125 | K62: 2.875 | L62: N/A | M62: N/A
B63: =B62+0.125 -> 8.125 | C63: =100-VLOOKUP(B63,'[1]Pricing '!$A$4521:$K$4553,11,FALSE) -> 1.59 | D63: =C63+0.25 -> 1.84 | E63: 660-679 | G63: 1.375 | H63: 1.875 | I63: 2.375 | J63: 2.875 | K63: N/A | L63: N/A | M63: N/A | N63: • Stand-alone
B64: =B63+0.125 -> 8.25 | C64: =100-VLOOKUP(B64,'[1]Pricing '!$A$4521:$K$4553,11,FALSE) -> 1.215 | D64: =C64+0.25 -> 1.465 | E64: Other Alt Doc FICO/CLTV Price Adjustments
B65: =B64+0.125 -> 8.375 | C65: =100-VLOOKUP(B65,'[1]Pricing '!$A$4521:$K$4553,11,FALSE) -> 0.84 | D65: =C65+0.25 -> 1.09 | E65: 780+ | G65: -1.25 | H65: -1.125 | I65: -1 | J65: -0.875 | K65: -0.75 | L65: -0.125 | M65: N/A | N65: • Primary, 2nd Home
B66: =B65+0.125 -> 8.5 | C66: =100-VLOOKUP(B66,'[1]Pricing '!$A$4521:$K$4553,11,FALSE) -> 0.465 | D66: =C66+0.25 -> 0.715 | E66: 760-779 | G66: -1.125 | H66: -1 | I66: -0.875 | J66: -0.75 | K66: -0.625 | L66: 0.125 | M66: N/A | N66: & Investment Properties
B67: =B66+0.125 -> 8.625 | C67: =100-VLOOKUP(B67,'[1]Pricing '!$A$4521:$K$4553,11,FALSE) -> 0.09 | D67: =C67+0.25 -> 0.34 | E67: 740-759 | G67: -1 | H67: -0.875 | I67: -0.75 | J67: -0.625 | K67: -0.375 | L67: 0.625 | M67: N/A
B68: =B67+0.125 -> 8.75 | C68: =100-VLOOKUP(B68,'[1]Pricing '!$A$4521:$K$4553,11,FALSE) -> -0.16 | D68: =C68+0.25 -> 0.09 | E68: 720-739 | G68: -0.5 | H68: -0.375 | I68: -0.25 | J68: 0 | K68: 0.25 | L68: 1.125 | M68: N/A | N68: • Up to 75.00% CLTVs
B69: =B68+0.125 -> 8.875 | C69: =100-VLOOKUP(B69,'[1]Pricing '!$A$4521:$K$4553,11,FALSE) -> -0.41 | D69: =C69+0.25 -> -0.16 | E69: 700-719 | G69: 0 | H69: 0.125 | I69: 0.5 | J69: 1 | K69: 1.875 | L69: 1.75 | M69: N/A
B70: =B69+0.125 -> 9 | C70: =100-VLOOKUP(B70,'[1]Pricing '!$A$4521:$K$4553,11,FALSE) -> -0.66 | D70: =C70+0.25 -> -0.41 | E70: 680-699 | G70: 0.625 | H70: 1.125 | I70: 1.5 | J70: 2.125 | K70: 2.875 | L70: N/A | M70: N/A | N70: • Income Type Available
B71: =B70+0.125 -> 9.125 | C71: =100-VLOOKUP(B71,'[1]Pricing '!$A$4521:$K$4553,11,FALSE) -> -0.91 | D71: =C71+0.25 -> -0.66 | E71: 660-679 | G71: 1.375 | H71: 1.875 | I71: 2.375 | J71: 2.875 | K71: N/A | L71: N/A | M71: N/A | N71: WVOE
B72: =B71+0.125 -> 9.25 | C72: =100-VLOOKUP(B72,'[1]Pricing '!$A$4521:$K$4553,11,FALSE) -> -1.16 | D72: =C72+0.25 -> -0.91 | E72: Additional Price Adjustments | N72: P&L
B73: =B72+0.125 -> 9.375 | C73: =100-VLOOKUP(B73,'[1]Pricing '!$A$4521:$K$4553,11,FALSE) -> -1.41 | D73: =C73+0.25 -> -1.16 | E73: L.A <=$100K | G73: 0.25 | H73: 0.25 | I73: 0.5 | J73: 0.5 | K73: 0.5 | L73: 0.5 | M73: 0.75 | N73: 12 Mo bank statement
B74: =B73+0.125 -> 9.5 | C74: =100-VLOOKUP(B74,'[1]Pricing '!$A$4521:$K$4553,11,FALSE) -> -1.66 | D74: =C74+0.25 -> -1.41 | E74: L.A >$100K-$150K | G74: 0.125 | H74: 0.125 | I74: 0.25 | J74: 0.25 | K74: 0.25 | L74: 0.25 | M74: 0.5 | N74: DSCR
B75: =B74+0.125 -> 9.625 | C75: =100-VLOOKUP(B75,'[1]Pricing '!$A$4521:$K$4553,11,FALSE) -> -1.91 | D75: =C75+0.25 -> -1.66 | E75: DTI 43.01-45.00 | G75: 0 | H75: 0 | I75: 0.125 | J75: 0.125 | K75: 0.375 | L75: 0.75 | M75: 1 | U75: -0.25
B76: =B75+0.125 -> 9.75 | C76: =100-VLOOKUP(B76,'[1]Pricing '!$A$4521:$K$4553,11,FALSE) -> -2.16 | D76: =C76+0.25 -> -1.91 | E76: DTI 45.01-50.00 | G76: 0.375 | H76: 0.375 | I76: 0.375 | J76: 0.5 | K76: 0.75 | L76: 1.25 | M76: 1.5 | N76: • Min. 660 Fico
B77: =B76+0.125 -> 9.875 | C77: =100-VLOOKUP(B77,'[1]Pricing '!$A$4521:$K$4553,11,FALSE) -> -2.41 | D77: =C77+0.25 -> -2.16 | E77: Non Owner Occ | G77: 1.75 | H77: 1.875 | I77: 2 | J77: 2.25 | K77: 3 | L77: N/A | M77: N/A
B78: =B77+0.125 -> 10 | C78: =100-VLOOKUP(B78,'[1]Pricing '!$A$4521:$K$4553,11,FALSE) -> -2.66 | D78: =C78+0.25 -> -2.41 | E78: Second Home | G78: 0.5 | H78: 0.5 | I78: 0.625 | J78: 0.75 | K78: 1 | L78: 1 | M78: N/A | N78: • Min. Loan Amount of $75,000
B79: =B78+0.125 -> 10.125 | C79: =100-VLOOKUP(B79,'[1]Pricing '!$A$4521:$K$4553,11,FALSE) -> -2.91 | D79: =C79+0.25 -> -2.66 | E79: 2-4 Units | G79: 0.5 | H79: 0.625 | I79: 0.75 | J79: 0.75 | K79: 1 | L79: 1 | M79: N/A | N79: Max. Loan Amount of $500,000
B80: =B79+0.125 -> 10.25 | C80: =100-VLOOKUP(B80,'[1]Pricing '!$A$4521:$K$4553,11,FALSE) -> -3.035 | D80: =C80+0.25 -> -2.785 | E80: 12 mth Bank Statement | G80: -2.125 | H80: -2.125 | I80: -2.125 | J80: -2 | K80: -1.75 | L80: -1.125 | M80: -0.875
B81: =B80+0.125 -> 10.375 | C81: =100-VLOOKUP(B81,'[1]Pricing '!$A$4521:$K$4553,11,FALSE) -> -3.16 | D81: =C81+0.25 -> -2.91 | E81: 24 mth Bank Statement | G81: -2.5 | H81: -2.5 | I81: -2.5 | J81: -2.375 | K81: -2.25 | L81: -1.75 | M81: -1.5 | N81: • Max. DTI 50%
B82: =B81+0.125 -> 10.5 | C82: =100-VLOOKUP(B82,'[1]Pricing '!$A$4521:$K$4553,11,FALSE) -> -3.285 | D82: =C82+0.25 -> -3.035 | E82: CPA P&L | G82: -1.375 | H82: -1.25 | I82: -0.875 | J82: -0.875 | K82: -0.875 | L82: -0.375 | M82: N/A
B83: =B82+0.125 -> 10.625 | C83: =100-VLOOKUP(B83,'[1]Pricing '!$A$4521:$K$4553,11,FALSE) -> -3.41 | D83: =C83+0.25 -> -3.16 | E83: WVOE | G83: -1.75 | H83: -1.625 | I83: -1.25 | J83: -1.25 | K83: -1.25 | L83: -0.5 | M83: N/A | N83: • Property Type
B84: =B83+0.125 -> 10.75 | C84: =100-VLOOKUP(B84,'[1]Pricing '!$A$4521:$K$4553,11,FALSE) -> -3.535 | D84: =C84+0.25 -> -3.285 | E84: DSCR >=1.25 | G84: -0.875 | H84: -0.75 | I84: -0.375 | J84: -0.25 | K84: -0.125 | L84: N/A | M84: N/A | N84: 1-4 Units
B85: MICHIGAN PREPAY ADJUSTMENTS | E85: DSCR<1.25 | G85: -0.375 | H85: -0.25 | I85: 0.125 | J85: 0.375 | K85: 0.375 | L85: N/A | M85: N/A | N85: SFR
B86: 1YR PPP | D86: 0.75 | E86: Foreign National | G86: 0.5 | H86: 0.5 | I86: 0.75 | J86: N/A | K86: N/A | L86: N/A | M86: N/A | N86: PUD/CONDO
B87: 2YR PPP | D87: 1 | E87: For Nat'l + 2nd Home | G87: 2.25 | H87: 2.375 | I87: 2.75 | J87: N/A | K87: N/A | L87: N/A | M87: N/A
B88: 3YR PPP | D88: 1.5 | E88: Non-Perm Resident | G88: 0.125 | H88: 0.125 | I88: 0.125 | J88: 0.125 | K88: 0.375 | L88: 0.375 | M88: 0.5
B89: MISC PRICE ADJUSTMENTS | E89: Interest Only | G89: 0.25 | H89: 0.375 | I89: 0.375 | J89: 0.375 | K89: 0.5 | L89: 0.625 | M89: N/A | N89: MAX PRICE
B90: 30-Years Fixed | D90: 0.125 | E90: Short-Term Rental | G90: 0.5 | H90: 0.5 | I90: 0.5 | J90: 0.5 | K90: 0.75 | L90: 1 | M90: 1.25 | N90: No Prepay | P90: 100.5
B91: No Prepay | D91: 0.75 | E91: CONDO | G91: 0.25 | H91: 0.25 | I91: 0.25 | J91: 0.25 | K91: 0.25 | L91: 0.25 | M91: 0.5 | N91: 1yr Prepay | P91: 101
B92: 1yr Prepay | D92: 0.375 | E92: Florida Condo | G92: 0.125 | H92: 0.125 | I92: 0.125 | J92: 0.25 | K92: 0.25 | L92: 0.375 | M92: N/A | N92: 2yr Prepay or Primary Residence | P92: 102.5
B93: 2yr Prepay | D93: 0 | E93: Baltimore County-MD | G93: 0.25 | H93: 0.25 | I93: 0.25 | J93: 0.25 | K93: 0.25 | L93: 0.375 | M93: 0.375
B95: **Lender Paid Compensation and Borrower Paid Compensation Allowed**
B97: Lender Fees: QM-CES $1,195 /NQM-CES $1,395 Lock Extensions: 2 bps per Day (Max of 30 Days) Redraw Fee $150.00
B98: Lock Hours until 5:00 PM PST
B99: Rates and fees are subject to change without notice.

Sheet HELOC
P1: 6 of 12
B2: AmWest Corporate Office
B3: 6 Pointe Dr. Suite 300
B4: Brea, CA 92821
B5: (714) 831-3333
B6: www.amwestwholesale.com
F7: Wholesale Rate sheet - Consumer Paid | J7: Effective: | L7: =CES!L7 -> 45950 | M7: =CES!M7 -> 8:00 AM PST
B9: LOAN LOCK INFO:
B11: Lock Desk : | D11: Email: Lockdesk@amwestfunding.com | H11: Phone: (714) 831-3299 | K11: eFax: (714) 421-4032 | M11: Lock Hours: 8:30AM-5:00 PM PST
B12: ANNOUNCEMENT
B16: HELOC
B17: Click For Guideline - FULL doc | I17: Click For Guideline - Alt Doc
B18: PRIME | D18: *Full doc | E18: Alt Doc | F18: 30 Days | G18: CLTV | I18: <=55.00% | J18: 55.01-60 | K18: 60.01-65 | L18: 65.01-70 | M18: 70.01-75 | N18: 75.01-80 | O18: 80.01-85 | P18: 85.01-90
B19: Index | D19: Margin | E19: Margin | F19: Price | G19: Full Doc FICO/CLTV Price Adjustments
B20: 6.75 | D20: =MIN('[1]Pricing '!$C$4558:$C$4590) -> 1.25 | E20: =MIN('[1]Pricing '!$C$4686:$C$4718) -> 2.375 | F20: =VLOOKUP(D20,'[1]Pricing '!$C$4558:$H$4594,6,FALSE)*-1+100 -> 1.725 | G20: 780-850 | I20: -2.5 | J20: -2.5 | K20: -2 | L20: -1.5 | M20: -1 | N20: -1 | O20: 1.5 | P20: 3
D21: =D20+0.125 -> 1.375 | E21: =E20+0.125 -> 2.5 | F21: =VLOOKUP(D21,'[1]Pricing '!$C$4558:$H$4594,6,FALSE)*-1+100 -> 1.225 | G21: 760-779 | I21: -2 | J21: -2 | K21: -2 | L21: -1.5 | M21: -1 | N21: 0 | O21: 3 | P21: 4.5
D22: =D21+0.125 -> 1.5 | E22: =E21+0.125 -> 2.625 | F22: =VLOOKUP(D22,'[1]Pricing '!$C$4558:$H$4594,6,FALSE)*-1+100 -> 0.725 | G22: 740-759 | I22: -1.5 | J22: -1.5 | K22: -1.5 | L22: -1 | M22: -1 | N22: 1 | O22: 4.5 | P22: 6.5
D23: =D22+0.125 -> 1.625 | E23: =E22+0.125 -> 2.75 | F23: =VLOOKUP(D23,'[1]Pricing '!$C$4558:$H$4594,6,FALSE)*-1+100 -> 0.225 | G23: 720-739 | I23: -0.5 | J23: -0.5 | K23: -0.5 | L23: -0.5 | M23: 0 | N23: 2.5 | O23: 6 | P23: N/A
D24: =D23+0.125 -> 1.75 | E24: =E23+0.125 -> 2.875 | F24: =VLOOKUP(D24,'[1]Pricing '!$C$4558:$H$4594,6,FALSE)*-1+100 -> -0.15 | G24: 700-719 | I24: 0 | J24: 0 | K24: 0.5 | L24: 1 | M24: 1.5 | N24: 5 | O24: 7 | P24: N/A
D25: =D24+0.125 -> 1.875 | E25: =E24+0.125 -> 3 | F25: =VLOOKUP(D25,'[1]Pricing '!$C$4558:$H$4594,6,FALSE)*-1+100 -> -0.525 | G25: 680-699 | I25: 0.5 | J25: 1 | K25: 2 | L25: 2.5 | M25: 3 | N25: N/A | O25: N/A | P25: N/A
D26: =D25+0.125 -> 2 | E26: =E25+0.125 -> 3.125 | F26: =VLOOKUP(D26,'[1]Pricing '!$C$4558:$H$4594,6,FALSE)*-1+100 -> -0.9 | G26: Bank Statement FICO/CLTV Price Adjustments
D27: =D26+0.125 -> 2.125 | E27: =E26+0.125 -> 3.25 | F27: =VLOOKUP(D27,'[1]Pricing '!$C$4558:$H$4594,6,FALSE)*-1+100 -> -1.275
D28: =D27+0.125 -> 2.25 | E28: =E27+0.125 -> 3.375 | F28: =VLOOKUP(D28,'[1]Pricing '!$C$4558:$H$4594,6,FALSE)*-1+100 -> -1.65 | G28: 780-850 | I28: -1.375 | J28: -1.375 | K28: -1.125 | L28: -0.875 | M28: -0.875 | N28: -0.625 | O28: N/A | P28: N/A
D29: =D28+0.125 -> 2.375 | E29: =E28+0.125 -> 3.5 | F29: =VLOOKUP(D29,'[1]Pricing '!$C$4558:$H$4594,6,FALSE)*-1+100 -> -2.025 | G29: 760-779 | I29: -1.125 | J29: -1.125 | K29: -0.875 | L29: -0.625 | M29: -0.625 | N29: -0.375 | O29: N/A | P29: N/A
D30: =D29+0.125 -> 2.5 | E30: =E29+0.125 -> 3.625 | F30: =VLOOKUP(D30,'[1]Pricing '!$C$4558:$H$4594,6,FALSE)*-1+100 -> -2.4 | G30: 740-759 | I30: -0.875 | J30: -0.875 | K30: -0.625 | L30: -0.375 | M30: -0.375 | N30: 0.375 | O30: N/A | P30: N/A
D31: =D30+0.125 -> 2.625 | E31: =E30+0.125 -> 3.75 | F31: =VLOOKUP(D31,'[1]Pricing '!$C$4558:$H$4594,6,FALSE)*-1+100 -> -2.713 | G31: 720-739 | I31: -0.25 | J31: -0.25 | K31: 0 | L31: 0.25 | M31: 0.375 | N31: 1.125 | O31: N/A | P31: N/A
D32: =D31+0.125 -> 2.75 | E32: =E31+0.125 -> 3.875 | F32: =VLOOKUP(D32,'[1]Pricing '!$C$4558:$H$4594,6,FALSE)*-1+100 -> -3.025 | G32: 700-719 | I32: 0 | J32: 0 | K32: 0.25 | L32: 0.625 | M32: 1.25 | N32: 1.5 | O32: N/A | P32: N/A
D33: =D32+0.125 -> 2.875 | E33: =E32+0.125 -> 4 | F33: =VLOOKUP(D33,'[1]Pricing '!$C$4558:$H$4594,6,FALSE)*-1+100 -> -3.338 | G33: 680-699 | I33: 0.5 | J33: 0.5 | K33: 0.875 | L33: 1.375 | M33: N/A | N33: N/A | O33: N/A | P33: N/A
D34: =D33+0.125 -> 3 | E34: =E33+0.125 -> 4.125 | F34: =VLOOKUP(D34,'[1]Pricing '!$C$4558:$H$4594,6,FALSE)*-1+100 -> -3.65 | G34: Other Alt Doc FICO/CLTV Price Adjustments
D35: =D34+0.125 -> 3.125 | E35: =E34+0.125 -> 4.25 | F35: =VLOOKUP(D35,'[1]Pricing '!$C$4558:$H$4594,6,FALSE)*-1+100 -> -3.963
D36: =D35+0.125 -> 3.25 | E36: =E35+0.125 -> 4.375 | F36: =VLOOKUP(D36,'[1]Pricing '!$C$4558:$H$4594,6,FALSE)*-1+100 -> -4.275 | G36: 780-850 | I36: -1.25 | J36: -1.25 | K36: -1 | L36: -0.75 | M36: -0.25 | N36: 0 | O36: N/A | P36: N/A
D37: =D36+0.125 -> 3.375 | E37: =E36+0.125 -> 4.5 | F37: =VLOOKUP(D37,'[1]Pricing '!$C$4558:$H$4594,6,FALSE)*-1+100 -> -4.525 | G37: 760-779 | I37: -1 | J37: -1 | K37: -0.75 | L37: -0.5 | M37: 0 | N37: 0.25 | O37: N/A | P37: N/A
D38: =D37+0.125 -> 3.5 | E38: =E37+0.125 -> 4.625 | F38: =VLOOKUP(D38,'[1]Pricing '!$C$4558:$H$4594,6,FALSE)*-1+100 -> -4.775 | G38: 740-759 | I38: -0.75 | J38: -0.75 | K38: -0.5 | L38: -0.25 | M38: 0.25 | N38: 0.5 | O38: N/A | P38: N/A
D39: =D38+0.125 -> 3.625 | E39: =E38+0.125 -> 4.75 | F39: =VLOOKUP(D39,'[1]Pricing '!$C$4558:$H$4594,6,FALSE)*-1+100 -> -5.025 | G39: 720-739 | I39: -0.125 | J39: -0.125 | K39: 0.125 | L39: 0.375 | M39: 1 | N39: 1.25 | O39: N/A | P39: N/A
D40: =D39+0.125 -> 3.75 | E40: =E39+0.125 -> 4.875 | F40: =VLOOKUP(D40,'[1]Pricing '!$C$4558:$H$4594,6,FALSE)*-1+100 -> -5.275 | G40: 700-719 | I40: 0.125 | J40: 0.125 | K40: 0.375 | L40: 0.75 | M40: 1.375 | N40: 1.625 | O40: N/A | P40: N/A
D41: =D40+0.125 -> 3.875 | E41: =E40+0.125 -> 5 | F41: =VLOOKUP(D41,'[1]Pricing '!$C$4558:$H$4594,6,FALSE)*-1+100 -> -5.525 | G41: 680-699 | I41: 0.5 | J41: 0.5 | K41: 0.875 | L41: 1.375 | M41: 2.125 | N41: 2.375 | O41: N/A | P41: N/A
D42: =D41+0.125 -> 4 | E42: =E41+0.125 -> 5.125 | F42: =VLOOKUP(D42,'[1]Pricing '!$C$4558:$H$4594,6,FALSE)*-1+100 -> -5.775 | G42: Additional Alt Doc Price Adjustments
D43: =D42+0.125 -> 4.125 | E43: =E42+0.125 -> 5.25 | F43: =VLOOKUP(D43,'[1]Pricing '!$C$4558:$H$4594,6,FALSE)*-1+100 -> -6.025 | G43: CPA P&L | I43: 1.25 | J43: 1.25 | K43: 1.25 | L43: 1.25 | M43: 1.5 | N43: N/A | O43: N/A | P43: N/A
D44: =D43+0.125 -> 4.25 | E44: =E43+0.125 -> 5.375 | F44: =VLOOKUP(D44,'[1]Pricing '!$C$4558:$H$4594,6,FALSE)*-1+100 -> -6.275 | G44: WVOE | I44: 1 | J44: 1 | K44: 1 | L44: 1 | M44: 1.25 | N44: N/A | O44: N/A | P44: N/A
D45: =D44+0.125 -> 4.375 | E45: =E44+0.125 -> 5.5 | F45: =VLOOKUP(D45,'[1]Pricing '!$C$4558:$H$4594,6,FALSE)*-1+100 -> -6.525 | G45: DSCR >=1.25 | I45: 1.5 | J45: 2.125 | K45: 2.75 | L45: 3.375 | M45: N/A | N45: N/A | O45: N/A | P45: N/A
D46: =D45+0.125 -> 4.5 | E46: =E45+0.125 -> 5.625 | F46: =VLOOKUP(D46,'[1]Pricing '!$C$4558:$H$4594,6,FALSE)*-1+100 -> -6.775 | G46: DSCR<1.25 | I46: 2.125 | J46: 2.75 | K46: 3.375 | L46: 4 | M46: N/A | N46: N/A | O46: N/A | P46: N/A
D47: =D46+0.125 -> 4.625 | E47: =E46+0.125 -> 5.75 | F47: =VLOOKUP(D47,'[1]Pricing '!$C$4558:$H$4594,6,FALSE)*-1+100 -> -7.025 | G47: 12 mth Bank Statement | I47: -1.625 | J47: -1.625 | K47: -1.625 | L47: -1.625 | M47: -1.625 | N47: -0.875 | O47: N/A | P47: N/A
D48: =D47+0.125 -> 4.75 | E48: =E47+0.125 -> 5.875 | F48: =VLOOKUP(D48,'[1]Pricing '!$C$4558:$H$4594,6,FALSE)*-1+100 -> -7.275 | G48: 24 mth Bank Statement | I48: -2.125 | J48: -2.125 | K48: -2.125 | L48: -2.125 | M48: -2.125 | N48: -1.5 | O48: N/A | P48: N/A
D49: =D48+0.125 -> 4.875 | E49: =E48+0.125 -> 6 | F49: =VLOOKUP(D49,'[1]Pricing '!$C$4558:$H$4594,6,FALSE)*-1+100 -> -7.525 | G49: Alt Doc Rate Adjustments
D50: =D49+0.125 -> 5 | E50: =E49+0.125 -> 6.125 | F50: =VLOOKUP(D50,'[1]Pricing '!$C$4558:$H$4594,6,FALSE)*-1+100 -> -7.775 | G50: NO RATIO | I50: 3 | J50: 3.5 | K50: 4.25 | L50: N/A | M50: N/A | N50: N/A | O50: N/A | P50: N/A
D51: =D50+0.125 -> 5.125 | E51: =E50+0.125 -> 6.25 | F51: =VLOOKUP(D51,'[1]Pricing '!$C$4558:$H$4594,6,FALSE)*-1+100 -> -8.025 | G51: ***NO INCOME | I51: 4 | J51: 4.25 | K51: N/A | L51: N/A | M51: N/A | N51: N/A | O51: N/A | P51: N/A
D52: =D51+0.125 -> 5.25 | E52: =E51+0.125 -> 6.375 | F52: =VLOOKUP(D52,'[1]Pricing '!$C$4558:$H$4594,6,FALSE)*-1+100 -> -8.275 | G52: Full + Alt Price Adjustments
G53: 2-4 UNIT | I53: 0.5 | J53: 0.5 | K53: 0.5 | L53: 0.5 | M53: 0.75 | N53: N/A | O53: N/A | P53: N/A
G54: CONDO | I54: 0 | J54: 0 | K54: 0.125 | L54: 0.25 | M54: 0.375 | N54: 0.375 | O54: N/A | P54: N/A
G55: NOO (DSCR/NoRatio Excluded) | I55: 2 | J55: 2.5 | K55: 3 | L55: 3.5 | M55: N/A | N55: N/A | O55: N/A | P55: N/A
G56: 2ND HOME | I56: 1 | J56: 1 | K56: 1 | L56: 1 | M56: 1 | N56: 1 | O56: N/A | P56: N/A
B57: NOTE RATE: Prime Rate + Margin | G57: DTI > 43 | I57: 0 | J57: 0 | K57: 0.125 | L57: 0.125 | M57: 0.25 | N57: 0.25 | O57: 0.375 | P57: 0.375
B58: Qualifying Rate: Note Rate + 2.00% | G58: STATE: NJ | I58: 0 | J58: 0 | K58: 0.25 | L58: 0.25 | M58: 0.25 | N58: 0.25 | O58: 0.25 | P58: 0.25
G59: L.A <=$100K | I59: 0.25 | J59: 0.25 | K59: 0.5 | L59: 0.5 | M59: 0.5 | N59: 0.5 | O59: 0.5 | P59: 0.5
B60: Qualifying payment: Qualifying rate over | G60: L.A >$100K-$150K | I60: 0.125 | J60: 0.125 | K60: 0.25 | L60: 0.25 | M60: 0.25 | N60: 0.25 | O60: 0.25 | P60: 0.25
B61: amortizing repayment period | G61: Lock Term 45 dys | I61: 0.25 | J61: 0.25 | K61: 0.25 | L61: 0.25 | M61: 0.25 | N61: 0.25 | O61: 0.25 | P61: 0.25
G62: Florida Condo | I62: 0.125 | J62: 0.125 | K62: 0.25 | L62: 0.25 | M62: 0.375 | N62: 0.5 | O62: N/A | P62: N/A
B63: Qualify using the fully amortized | G63: Baltimore County-MD | I63: 0.25 | J63: 0.25 | K63: 0.25 | L63: 0.25 | M63: 0.375 | N63: 0.375 | O63: 0.5 | P63: 0.5
B64: payment calculated over the 20-year | G64: Draw Terms (Full + Alt Price Adjustments)
B65: fully amortization period. | G65: 24 | I65: -2 | J65: -2 | K65: -2 | L65: -2 | M65: -2 | N65: -2 | O65: -2 | P65: -2
G66: 36 | I66: -1.5 | J66: -1.5 | K66: -1.5 | L66: -1.5 | M66: -1.5 | N66: -1.5 | O66: -1.5 | P66: -1.5
G67: 60 | I67: 0 | J67: 0 | K67: 0 | L67: 0 | M67: 0 | N67: 0 | O67: 0 | P67: 0
G68: ***Excludes Maryland | I68: *MAX PRICE | N68: **MAX PRICE
I69: -2 | N69: PAR
I71: *Includes Full Doc ,WVOE, P&L | N71: **Includes No Income , No Ratio
I72: Bank Statement , DSCR
B77: HIGHLIGHTS
B80: INCOME DOC TYPES | I80: *OCCUPANCY | K80: MAX LTV/CLTV | M80: FOOTNOTES
C82: • WVOE | D82: • | E82: 12 M Bank Statements | H82: • DSCR | I82: Primary | L82: 0.9 | M82: • 1-Unit only for Second Homes
C83: • P&L | D83: • | E83: 24 M Bank Statements | H83: • No Ratio | I83: Second Homes | L83: 0.75 | M83: • Second Homes: Max CLTV of 75%
H84: • No Income | I84: Investment | L84: 0.7 | M84: • For Bank Statement income doc type, min
M85: FICO is 700 with Max CLTV of 80.00%
M86: • The Maximum Repay Period of 30 Years
M87: refers to the total length of the Loan
B92: **Lender Paid Compensation and Borrower Paid Compensation Allowed**
B98: Lender Fees: Full doc HELOC $1,195 & NQM HELOC: $1,695 Lock Extensions: 2 bps per Day (Max of 30 Days) Redraw Fee $150.00
B99: Lock Hours until 5:00 PM PST
B100: Rates and fees are subject to change without notice.

Sheet AAA_AAI_AAQ_AAO
R1: 8 of 11
B2: AmWest Corporate Office | P2: Lock Expiration Dates
B3: 6 Pointe Dr. Suite 300
B4: Brea, CA 92821 | P4: 30 Day Lock | R4: =[2]FNMA!$P$4 -> 45980
B5: (714) 831-3333 | P5: 45 Day Lock | R5: =[2]FNMA!$P$5 -> 45995
B6: www.amwestwholesale.com | P6: 60 Day Lock | R6: =[2]FNMA!$P$6 -> 46010
F7: Wholesale Rate sheet - Consumer Paid | K7: Effective: | M7: =[2]FNMA!L7 -> 45950 | N7: =[2]FNMA!M7 -> 8:00 AM PST
B9: LOAN LOCK INFO:
B11: Lock Desk : Email: Lockdesk@amwestfunding.com | G11: Phone: (714) 831-3299 | K11: eFax: (714) 905-5620 | O11: Lock Hours: 8:30AM-5:00 PM PST
B13: ANNOUNCEMENT
B17: AMWEST ADVANTAGE FIXED & ARM PROGRAMS
B19: ADVANTAGE | E19: Click For Guideline | I19: Click for Guideline | M19: ADVANTAGE BANK STMT | O19: BANK STATEMENT HIGHLIGHTS
B20: (AAF30) 30YR FIXED | E20: ADVANTAGE | I20: ADVANTAGE BANK STMT | M20: (AAB30)
B21: ASSET QUALIFIER | E21: (AAF30) 30YR FIXED | I21: (AAB30) | M21: ADVANTAGE ONE | O21: • 12 or 24 Months allowed
B22: (AAQ30) 30YR FIXED | E22: Products available | I22: Product Code: | M22: (AAO30)
B23: ADVANTAGE ITIN | E23: 30YR FIXED- AAF30 | I23: 30YR FIXED-AAB30 | M23: RATE | N23: 30 Days | O23: • MAX LTV: 85% (O/O and 2nd home only)
B24: (AAI30) 30YR FIXED | E24: 20YR FIXED - AAF20 | I24: 15YR FIXED -AAB15 | O24: • W-2 income allowed
B25: RATE | C25: 30 Days | E25: 7/6 ARM- AAA7/6 | I25: 7/6 ARM- AAB7/6 | M25: =MIN('[1]Pricing '!$A$3000:$A$3028) -> 5.75 | N25: =100-VLOOKUP(M25,'[1]Pricing '!$A$3000:$K$3028,11,FALSE) -> 5.34 | O25: • Documents for business expense:
E26: 7/6 ARM (I/O)- AAA7/6IO | I26: 7/6 ARM (I/O)- AAB7/6 | M26: =M25+0.125 -> 5.875 | N26: =100-VLOOKUP(M26,'[1]Pricing '!$A$3000:$K$3028,11,FALSE) -> 4.715 | O26: A letter prepared by a licensed tax preparer
B27: 5.875 | C27: =100-VLOOKUP(B27,'[1]Pricing '!$A$1619:$K$1646,11,FALSE) -> 5.715 | E27: Buydown Option will end in B1 or B2 | I27: Buydown Option will end in B1 or B2 | M27: =M26+0.125 -> 6 | N27: =100-VLOOKUP(M27,'[1]Pricing '!$A$3000:$K$3028,11,FALSE) -> 4.09 | O27: stating the expense ratio
B28: =B27+0.125 -> 6 | C28: =100-VLOOKUP(B28,'[1]Pricing '!$A$1619:$K$1646,11,FALSE) -> 5.09 | E28: B1=12 Months / B2=24 months | I28: B1=12 Months / B2=24 months | M28: =M27+0.125 -> 6.125 | N28: =100-VLOOKUP(M28,'[1]Pricing '!$A$3000:$K$3028,11,FALSE) -> 3.59 | O28: • Max DTI at 50%
B29: =B28+0.125 -> 6.125 | C29: =100-VLOOKUP(B29,'[1]Pricing '!$A$1619:$K$1646,11,FALSE) -> 4.465 | F29: Click For Guideline | J29: Click for Guideline | M29: =M28+0.125 -> 6.25 | N29: =100-VLOOKUP(M29,'[1]Pricing '!$A$3000:$K$3028,11,FALSE) -> 3.09 | O29: • Reserves
B30: =B29+0.125 -> 6.25 | C30: =100-VLOOKUP(B30,'[1]Pricing '!$A$1619:$K$1646,11,FALSE) -> 3.965 | E30: ASSET QUALIFIER | I30: ADVANTAGE ONE | M30: =M29+0.125 -> 6.375 | N30: =100-VLOOKUP(M30,'[1]Pricing '!$A$3000:$K$3028,11,FALSE) -> 2.59 | O30: ≤ $1M: 6 mo. PITIA
B31: =B30+0.125 -> 6.375 | C31: =100-VLOOKUP(B31,'[1]Pricing '!$A$1619:$K$1646,11,FALSE) -> 3.465 | E31: (AAQ30) 30YR FIXED | I31: (AAO30) | M31: =M30+0.125 -> 6.5 | N31: =100-VLOOKUP(M31,'[1]Pricing '!$A$3000:$K$3028,11,FALSE) -> 2.09 | O31: ≤ $2M: 9 mo. PITIA
B32: =B31+0.125 -> 6.5 | C32: =100-VLOOKUP(B32,'[1]Pricing '!$A$1619:$K$1646,11,FALSE) -> 2.965 | E32: Producs available: | I32: Product Code: | M32: =M31+0.125 -> 6.625 | N32: =100-VLOOKUP(M32,'[1]Pricing '!$A$3000:$K$3028,11,FALSE) -> 1.715 | O32: ≤ $3M: 12 mo. PITIA
B33: =B32+0.125 -> 6.625 | C33: =100-VLOOKUP(B33,'[1]Pricing '!$A$1619:$K$1646,11,FALSE) -> 2.59 | E33: 30YR FIXED- AAQ30 | I33: 30YR FIXED- AAO30 | M33: =M32+0.125 -> 6.75 | N33: =100-VLOOKUP(M33,'[1]Pricing '!$A$3000:$K$3028,11,FALSE) -> 1.34 | O33: • Business expense between 30% and 50%
B34: =B33+0.125 -> 6.75 | C34: =100-VLOOKUP(B34,'[1]Pricing '!$A$1619:$K$1646,11,FALSE) -> 2.215 | E34: 7/6 ARM- AAQ7/6 | I34: 7/6 ARM- AAO7/6 | M34: =M33+0.125 -> 6.875 | N34: =100-VLOOKUP(M34,'[1]Pricing '!$A$3000:$K$3028,11,FALSE) -> 0.965 | O34: from qualified income
B35: =B34+0.125 -> 6.875 | C35: =100-VLOOKUP(B35,'[1]Pricing '!$A$1619:$K$1646,11,FALSE) -> 1.84 | E35: 7/6 ARM (I/O)- AAQ7/6IO | M35: =M34+0.125 -> 7 | N35: =100-VLOOKUP(M35,'[1]Pricing '!$A$3000:$K$3028,11,FALSE) -> 0.615 | O35: • Closing funds can be verified with 1 month
B36: =B35+0.125 -> 7 | C36: =100-VLOOKUP(B36,'[1]Pricing '!$A$1619:$K$1646,11,FALSE) -> 1.465 | E36: Buydown Option will end in B1 or B2 | I36: Buydown Option will end in B1 or B2 | M36: =M35+0.125 -> 7.125 | N36: =100-VLOOKUP(M36,'[1]Pricing '!$A$3000:$K$3028,11,FALSE) -> 0.29 | O36: VOD or Bank Certification
B37: =B36+0.125 -> 7.125 | C37: =100-VLOOKUP(B37,'[1]Pricing '!$A$1619:$K$1646,11,FALSE) -> 1.09 | E37: B1=12 Months / B2=24 months | I37: B1=12 Months / B2=24 months | M37: =M36+0.125 -> 7.25 | N37: =100-VLOOKUP(M37,'[1]Pricing '!$A$3000:$K$3028,11,FALSE) -> -0.01 | O37: • Allowed on Non-Warrantable Condos
B38: =B37+0.125 -> 7.25 | C38: =100-VLOOKUP(B38,'[1]Pricing '!$A$1619:$K$1646,11,FALSE) -> 0.715 | E38: Click For Guideline | M38: =M37+0.125 -> 7.375 | N38: =100-VLOOKUP(M38,'[1]Pricing '!$A$3000:$K$3028,11,FALSE) -> -0.285
B39: =B38+0.125 -> 7.375 | C39: =100-VLOOKUP(B39,'[1]Pricing '!$A$1619:$K$1646,11,FALSE) -> 0.36777778 | E39: ADVANTAGE ITIN | M39: =M38+0.125 -> 7.5 | N39: =100-VLOOKUP(M39,'[1]Pricing '!$A$3000:$K$3028,11,FALSE) -> -0.535 | O39: 1099 INCOME HIGHLIGHTS
B40: =B39+0.125 -> 7.5 | C40: =100-VLOOKUP(B40,'[1]Pricing '!$A$1619:$K$1646,11,FALSE) -> 0.048333333 | E40: (AAI30) 30YR FIXED | M40: =M39+0.125 -> 7.625 | N40: =100-VLOOKUP(M40,'[1]Pricing '!$A$3000:$K$3028,11,FALSE) -> -0.76
B41: =B40+0.125 -> 7.625 | C41: =100-VLOOKUP(B41,'[1]Pricing '!$A$1619:$K$1646,11,FALSE) -> -0.24333333 | E41: Producs available: | M41: =M40+0.125 -> 7.75 | N41: =100-VLOOKUP(M41,'[1]Pricing '!$A$3000:$K$3028,11,FALSE) -> -0.96 | O41: • 1-year 1099
B42: =B41+0.125 -> 7.75 | C42: =100-VLOOKUP(B42,'[1]Pricing '!$A$1619:$K$1646,11,FALSE) -> -0.50722222 | E42: 30YR FIXED- AAI30 | M42: =M41+0.125 -> 7.875 | N42: =100-VLOOKUP(M42,'[1]Pricing '!$A$3000:$K$3028,11,FALSE) -> -1.135
B43: =B42+0.125 -> 7.875 | C43: =100-VLOOKUP(B43,'[1]Pricing '!$A$1619:$K$1646,11,FALSE) -> -0.74333333 | E43: 15YR FIXED - AAI15 | H43: MINIMUM PRICE | M43: =M42+0.125 -> 8 | N43: =100-VLOOKUP(M43,'[1]Pricing '!$A$3000:$K$3028,11,FALSE) -> -1.285 | O43: • 10% expense factor
B44: =B43+0.125 -> 8 | C44: =100-VLOOKUP(B44,'[1]Pricing '!$A$1619:$K$1646,11,FALSE) -> -0.95166667 | E44: 7/6 ARM- AAI7/6 | H44: 3YR PREPAY | J44: PAR | M44: =M43+0.125 -> 8.125 | N44: =100-VLOOKUP(M44,'[1]Pricing '!$A$3000:$K$3028,11,FALSE) -> -1.41 | O44: • 1099 income from multiple contract
B45: =B44+0.125 -> 8.125 | C45: =100-VLOOKUP(B45,'[1]Pricing '!$A$1619:$K$1646,11,FALSE) -> -1.1322222 | E45: 7/6 ARM (I/O)- AAI7/6IO | H45: 4YR PREPAY | J45: -0.25 | O45: employers allowed
B46: =B45+0.125 -> 8.25 | C46: =100-VLOOKUP(B46,'[1]Pricing '!$A$1619:$K$1646,11,FALSE) -> -1.285 | E46: Buydown Option will end in B1 or B2 | H46: 5YR PREPAY | J46: -0.5
B47: =B46+0.125 -> 8.375 | C47: =100-VLOOKUP(B47,'[1]Pricing '!$A$1619:$K$1646,11,FALSE) -> -1.41 | E47: B1=12 Months / B2=24 months | O47: • CPA letter to evidence 2 years of
J48: TERM | K48: MAX PRICE | O48: 1099 income
B49: ARM INFO | H49: PREPAY PENALTY (NOO ONLY) | J49: NO PENALTY | K49: -0.5
B50: MARGIN | D50: 0.04 | J50: 1YR PREPAY | K50: -1.75
J51: 2YR PREPAY | K51: -2.25 | O51: ITIN HIGHLIGHTS
B52: SOFR | D52: 0.036719 | J52: 3YR PREPAY | K52: -2.5
J53: 4YR PREPAY | K53: -2.75 | O53: • 12 or 24 Months Allowed - Bank Statements
B54: CAPS | D54: 5/1/5 | J54: 5YR PREPAY | K54: -2.75
H55: OWNER OCC & 2nd Home | K55: -2.25 | O55: • W-2 Income allowed
B56: FLOOR = START RATE
O57: • A letter prepared by a Licensed Tax Preparer
B58: **Lender Paid Compensation and Borrower Paid Compensation Allowed** | O58: stating the Expense Ratio
B60: PRICE ADJUSTMENTS | L60: -2 | M60: -2 | O60: • Second Homes: 1 Unit Properties Only
E61: <=55 | F61: 55.01-60 | G61: 60.01-65 | H61: 65.01-70 | I61: 70.01-75 | J61: 75.01-80 | K61: 80.01-85
B62: 780+ | E62: -1.375 | F62: -1.25 | G62: -1.125 | H62: -1 | I62: -0.875 | J62: -0.625 | K62: 0.25 | O62: • Texas Cash-Out Section 50(a)(6) not permitted
B63: 760-779 | E63: -1.25 | F63: -1.125 | G63: -1 | H63: -0.875 | I63: -0.75 | J63: -0.5 | K63: 0.375
B64: 740-759 | E64: -1.125 | F64: -1 | G64: -0.875 | H64: -0.75 | I64: -0.625 | J64: -0.375 | K64: 1 | O64: •Investment Properties: Prepayment Penalty may
B65: 720-739 | E65: -0.875 | F65: -0.875 | G65: -0.75 | H65: -0.625 | I65: -0.25 | J65: 0.375 | K65: 2.25 | O65: apply (refer to guidelines and State restrictions)
B66: 700-719 | E66: -0.625 | F66: -0.5 | G66: -0.375 | H66: 0 | I66: 0.75 | J66: 1.5 | K66: 3
B67: 680-699 | E67: -0.25 | F67: 0 | G67: 0.375 | H67: 0.875 | I67: 2 | J67: 3.5 | K67: N/A | O67: • Borrowers with No Credit Score must assume
B68: 660-679 | E68: 0 | F68: 0.25 | G68: 0.625 | H68: 1.5 | I68: 3.75 | J68: N/A | K68: N/A | O68: credit score of 620 (Purchase/R&T) and 660
B69: 640-659 | E69: 0.25 | F69: 0.5 | G69: 1 | H69: 2.5 | I69: N/A | J69: N/A | K69: N/A | O69: (Cash-Out)
B70: 620-639 | E70: 0.5 | F70: 0.875 | G70: 1.5 | H70: N/A | I70: N/A | J70: N/A | K70: N/A
B71: Baltimore County-MD | E71: 0.25 | F71: 0.25 | G71: 0.25 | H71: 0.25 | I71: 0.375 | J71: 0.375 | K71: 0.5 | O71: • Limited to 70% LTV (Purchase & R/T)
B72: For Nat'l (No FICO) | E72: 0.125 | F72: 0.25 | G72: 0.5 | H72: 1 | I72: N/A | J72: N/A | K72: N/A
B73: Non-Perm Res (+FICO) | E73: 0.125 | F73: 0.25 | G73: 0.25 | H73: 0.375 | I73: 0.375 | J73: 0.625 | K73: 0.75 | O73: 75% LTV (Cash-Out)
B74: For Nat'l & 2nd Home | E74: 0.25 | F74: 0.375 | G74: 0.75 | H74: 1.5 | I74: N/A | J74: N/A | K74: N/A | O74: 1-Unit Properties Only
B75: Interest Only | E75: 0.25 | F75: 0.25 | G75: 0.25 | H75: 0.375 | I75: 0.5 | J75: N/A | K75: N/A
B76: 2-4 Units | E76: 0.375 | F76: 0.375 | G76: 0.5 | H76: 0.75 | I76: 1 | J76: 1 | K76: N/A | O76: • Interest Only: Max LTV: 70% Min FICO: 700
B77: Cash-Out | E77: 0.25 | F77: 0.25 | G77: 0.375 | H77: 0.5 | I77: 0.75 | J77: N/A | K77: N/A
B78: Non Owner | E78: 0.25 | F78: 0.25 | G78: 0.375 | H78: 0.75 | I78: 1 | J78: 1.5 | K78: N/A | O78: ADVATANGE ONE HIGHLIGHTS
B79: Second Home | E79: 0.125 | F79: 0.125 | G79: 0.25 | H79: 0.375 | I79: 0.75 | J79: 1 | K79: 1.25
B80: Florida Condo | E80: 0.125 | F80: 0.125 | G80: 0.25 | H80: 0.25 | I80: 0.375 | J80: 0.5 | K80: 0.5
B81: 12 mth Bank Statement | E81: -1.875 | F81: -1.875 | G81: -1.75 | H81: -1.625 | I81: -1.5 | J81: -1.25 | K81: 0.15 | O81: •Loan Amount up to $3M
B82: 24 mth Bank Statement | E82: -2.25 | F82: -2.25 | G82: -2.125 | H82: -2.125 | I82: -2 | J82: -1.75 | K82: -0.35
B83: 1 Year Tax Return | E83: -2.375 | F83: -2.375 | G83: -2.25 | H83: -2 | I83: -1.75 | J83: -1.625 | K83: N/A | O83: • Reserves/Assets required per DU
B84: P&L | E84: -1.625 | F84: -1.5 | G84: -1.5 | H84: -1.375 | I84: -1 | J84: -0.625 | K84: 2.25 | O84: • 1 yr Income documents
B85: WVOE | E85: -2.25 | F85: -2.25 | G85: -2.125 | H85: -2.125 | I85: -2 | J85: -1.75 | K85: 1.75 | O85: (both Self-Employed & Salaried borrowers)
B86: 1099 | E86: -1.1 | F86: -0.975 | G86: -0.975 | H86: -0.875 | I86: -0.5 | J86: 0 | K86: N/A | O86: • Findings per DU
B87: Asset Qualifier | E87: 0.5 | F87: 0.75 | G87: 0.75 | H87: 1 | I87: 1.25 | J87: 1.5 | K87: N/A
B88: ITIN Full Doc | E88: 1 | F88: 1.125 | G88: 1.25 | H88: 1.625 | I88: 2 | J88: 2.5 | K88: N/A | O88: (Approved/Ineligible due to loan amount)
B89: ITIN 24 mth Bank Stmt/1099 | E89: 1.75 | F89: 2 | G89: 2.25 | H89: 2.5 | I89: 3 | J89: 3.5 | K89: N/A | O89: • No Tradeline requirements
B90: ITIN 12 mth Bank Stmt | E90: 2.125 | F90: 2.375 | G90: 2.75 | H90: 3 | I90: 3.5 | J90: 4.25 | K90: N/A | O90: with DU approval
B91: ADDITIONAL PRICE ADJUSTMENTS
B92: CLTV | I92: 0.25 | O92: • First Time Homebuyers Allowed
B93: Non Warrantable - CONDO | I93: 1
B94: 15yr Fixed AAB, AAI | I94: -0.125 | O94: >4 Owned properties including Financed LLPA
B95: <$100k | I95: 0.75 | Q95: 20 MAX owned properties on PORTFOLIO
B96: >$1.50mm-$2.50mm | I96: 0.25 | O96: 5-7 properties | R96: 0
B97: >$2.50mm -$3.00mm | I97: 0.375 | O97: 8-10 properties | R97: 0.125
B98: 45 Days Lock | I98: 0.125 | O98: 11-15 properties | R98: 0.25
B99: 5YR PREPAY | I99: -1.5 | O99: 16-20 properties | R99: 0.375
B100: 4YR PREPAY | I100: -1
B101: 3YR PREPAY | I101: -0.5 | O101: State Adjuster
B102: 1YR PREPAY | I102: 0.5 | O102: NY | R102: 0.25
B103: No PREPAY | I103: 1
B104: 7/6 ARM AAB, AAA, AAQ, AAI, AAO | I104: 0
B105: ADDITIONAL RATE ADJUSTMENTS
B106: 7/6 ARM AAB, AAA, AAQ, AAI, AAO | I106: 0
B107: Group 1 | C107: STANDARD PREPAYMENT ALLOWED | N107: MICHIGAN PREPAY ADJUSTMENTS
B108: States | C108: AL,AZ,AK,CA,CT,CO,DC,DE,FL,GA,HI,ID, IA,LA,ME,MD,MA,MO,MT,NE,NV,NH,NY,NC,ND,OK,OR,SC,SD,TN,UT,VA,WA,WV,WI,WY | N108: 1YR PPP | R108: 0.75
...

Sheet AIA_AIP
P1: 8 of 12
B2: AmWest Corporate Office
B3: 6 Pointe Dr. Suite 300
B4: Brea, CA 92821
B5: (714) 831-3333
B6: www.amwestwholesale.com
F7: Wholesale Rate sheet - Consumer Paid | J7: Effective: | K7: =AAA_AAI_AAQ_AAO!M7 -> 45950 | L7: =AAA_AAI_AAQ_AAO!N7 -> 8:00 AM PST
B8: LOAN LOCK INFO:
B10: Lock Desk : | D10: Email: Lockdesk@amwestfunding.com | H10: Phone: (714) 831-3299 | J10: eFax: (714) 905-5620 | L10: Lock Hours: 8:30AM-5:00 PM PST
B12: ANNOUNCEMENT
B13: =AAA_AAI_AAQ_AAO!B14 -> 0
B16: AMWEST INVESTOR FIXED & ARM PROGRAMS
B19: Click For Guideline
B20: AMWEST INVESTOR ADVANTAGE
B21: (AIA 7/6) 7 YR ARM | E21: (AIA30) 30 YR | H21: MAX PRICE | K21: PROGRAM CODE: AIA
B22: 30 DAYS | E22: 30 DAYS
B23: RATE | C23: PRICE | E23: RATE | F23: PRICE | H23: 5YR PREPAY | J23: -3 | K23: 5YR PPP | L23: AIA7/6P5, AIA7/6P5 IO, AIA30P5
B24: =MIN('[1]Pricing '!$A$1943:$A$1972) -> 5.75 | C24: =100-VLOOKUP(B24,'[1]Pricing '!$A$1943:$K$1972,11,FALSE) -> 6.315 | E24: =B24 -> 5.75 | F24: =100-VLOOKUP(E24,'[1]Pricing '!$A$1943:$K$1972,11,FALSE) -> 6.315 | H24: 4YR PREPAY | J24: -2.75 | K24: 4YR PPP | L24: AIA7/6P4, AIA7/6P4 IO, AIA30P4
B25: =B24+0.125 -> 5.875 | C25: =100-VLOOKUP(B25,'[1]Pricing '!$A$1943:$K$1972,11,FALSE) -> 5.69 | E25: =B25 -> 5.875 | F25: =100-VLOOKUP(E25,'[1]Pricing '!$A$1943:$K$1972,11,FALSE) -> 5.69 | H25: 3YR PREPAY | J25: -2.75 | K25: 3YR PPP | L25: AIA7/6P3, AIA7/6P3 IO, AIA30P3
B26: =B25+0.125 -> 6 | C26: =100-VLOOKUP(B26,'[1]Pricing '!$A$1943:$K$1972,11,FALSE) -> 5.065 | E26: =B26 -> 6 | F26: =100-VLOOKUP(E26,'[1]Pricing '!$A$1943:$K$1972,11,FALSE) -> 5.065 | H26: 2YR PREPAY | J26: -2.25 | K26: 2YR PPP | L26: AIA7/6P2, AIA7/6P2 IO, AIA30P2
B27: =B26+0.125 -> 6.125 | C27: =100-VLOOKUP(B27,'[1]Pricing '!$A$1943:$K$1972,11,FALSE) -> 4.565 | E27: =B27 -> 6.125 | F27: =100-VLOOKUP(E27,'[1]Pricing '!$A$1943:$K$1972,11,FALSE) -> 4.565 | H27: 1YR PREPAY | J27: -1.75 | K27: 1YR PPP | L27: AIA7/6P1, AIA7/6P1 IO, AIA30P1
B28: =B27+0.125 -> 6.25 | C28: =100-VLOOKUP(B28,'[1]Pricing '!$A$1943:$K$1972,11,FALSE) -> 4.065 | E28: =B28 -> 6.25 | F28: =100-VLOOKUP(E28,'[1]Pricing '!$A$1943:$K$1972,11,FALSE) -> 4.065 | H28: *NO PREPAY | J28: -1 | K28: *NO PPP | L28: AIA7/6, AIA30
B29: =B28+0.125 -> 6.375 | C29: =100-VLOOKUP(B29,'[1]Pricing '!$A$1943:$K$1972,11,FALSE) -> 3.565 | E29: =B29 -> 6.375 | F29: =100-VLOOKUP(E29,'[1]Pricing '!$A$1943:$K$1972,11,FALSE) -> 3.565
B30: =B29+0.125 -> 6.5 | C30: =100-VLOOKUP(B30,'[1]Pricing '!$A$1943:$K$1972,11,FALSE) -> 3.19 | E30: =B30 -> 6.5 | F30: =100-VLOOKUP(E30,'[1]Pricing '!$A$1943:$K$1972,11,FALSE) -> 3.19 | H30: MINIMUM PRICE | K30: ARM INFO
B31: =B30+0.125 -> 6.625 | C31: =100-VLOOKUP(B31,'[1]Pricing '!$A$1943:$K$1972,11,FALSE) -> 2.815 | E31: =B31 -> 6.625 | F31: =100-VLOOKUP(E31,'[1]Pricing '!$A$1943:$K$1972,11,FALSE) -> 2.815
B32: =B31+0.125 -> 6.75 | C32: =100-VLOOKUP(B32,'[1]Pricing '!$A$1943:$K$1972,11,FALSE) -> 2.44 | E32: =B32 -> 6.75 | F32: =100-VLOOKUP(E32,'[1]Pricing '!$A$1943:$K$1972,11,FALSE) -> 2.44 | H32: 3YR PREPAY | J32: PAR | K32: MARGIN | N32: 0.04
B33: =B32+0.125 -> 6.875 | C33: =100-VLOOKUP(B33,'[1]Pricing '!$A$1943:$K$1972,11,FALSE) -> 2.065 | E33: =B33 -> 6.875 | F33: =100-VLOOKUP(E33,'[1]Pricing '!$A$1943:$K$1972,11,FALSE) -> 2.065 | H33: 4YR PREPAY | J33: -0.25 | K33: SOFR
B34: =B33+0.125 -> 7 | C34: =100-VLOOKUP(B34,'[1]Pricing '!$A$1943:$K$1972,11,FALSE) -> 1.69 | E34: =B34 -> 7 | F34: =100-VLOOKUP(E34,'[1]Pricing '!$A$1943:$K$1972,11,FALSE) -> 1.69 | H34: 5YR PREPAY | J34: -0.5 | K34: CAPS 5/1/5
B35: =B34+0.125 -> 7.125 | C35: =100-VLOOKUP(B35,'[1]Pricing '!$A$1943:$K$1972,11,FALSE) -> 1.315 | E35: =B35 -> 7.125 | F35: =100-VLOOKUP(E35,'[1]Pricing '!$A$1943:$K$1972,11,FALSE) -> 1.315 | K35: Floor = Start Rate
B36: =B35+0.125 -> 7.25 | C36: =100-VLOOKUP(B36,'[1]Pricing '!$A$1943:$K$1972,11,FALSE) -> 0.94 | E36: =B36 -> 7.25 | F36: =100-VLOOKUP(E36,'[1]Pricing '!$A$1943:$K$1972,11,FALSE) -> 0.94
B37: =B36+0.125 -> 7.375 | C37: =100-VLOOKUP(B37,'[1]Pricing '!$A$1943:$K$1972,11,FALSE) -> 0.565 | E37: =B37 -> 7.375 | F37: =100-VLOOKUP(E37,'[1]Pricing '!$A$1943:$K$1972,11,FALSE) -> 0.565 | K37: AMWEST INVESTOR HIGHLIGHTS - AIA/AIP
B38: =B37+0.125 -> 7.5 | C38: =100-VLOOKUP(B38,'[1]Pricing '!$A$1943:$K$1972,11,FALSE) -> 0.213 | E38: =B38 -> 7.5 | F38: =100-VLOOKUP(E38,'[1]Pricing '!$A$1943:$K$1972,11,FALSE) -> 0.213 | K38: • Loan amount up to $2.5M
B39: =B38+0.125 -> 7.625 | C39: =100-VLOOKUP(B39,'[1]Pricing '!$A$1943:$K$1972,11,FALSE) -> -0.115 | E39: =B39 -> 7.625 | F39: =100-VLOOKUP(E39,'[1]Pricing '!$A$1943:$K$1972,11,FALSE) -> -0.115 | K39: • Minimum FICO as low as 620
B40: =B39+0.125 -> 7.75 | C40: =100-VLOOKUP(B40,'[1]Pricing '!$A$1943:$K$1972,11,FALSE) -> -0.419 | E40: =B40 -> 7.75 | F40: =100-VLOOKUP(E40,'[1]Pricing '!$A$1943:$K$1972,11,FALSE) -> -0.419 | K40: • Loan qualification is based on Debt Coverage Ratio (DCR)
B41: =B40+0.125 -> 7.875 | C41: =100-VLOOKUP(B41,'[1]Pricing '!$A$1943:$K$1972,11,FALSE) -> -0.701 | E41: =B41 -> 7.875 | F41: =100-VLOOKUP(E41,'[1]Pricing '!$A$1943:$K$1972,11,FALSE) -> -0.701 | K41: • Foreign Nationals allowed
B42: =B41+0.125 -> 8 | C42: =100-VLOOKUP(B42,'[1]Pricing '!$A$1943:$K$1972,11,FALSE) -> -0.958 | E42: =B42 -> 8 | F42: =100-VLOOKUP(E42,'[1]Pricing '!$A$1943:$K$1972,11,FALSE) -> -0.958 | K42: • Non-warrantable condos allowed
B43: =B42+0.125 -> 8.125 | C43: =100-VLOOKUP(B43,'[1]Pricing '!$A$1943:$K$1972,11,FALSE) -> -1.193 | E43: =B43 -> 8.125 | F43: =100-VLOOKUP(E43,'[1]Pricing '!$A$1943:$K$1972,11,FALSE) -> -1.193 | K43: • First time Homebuyer/First time investor allowed (see guidelines)
B44: =B43+0.125 -> 8.25 | C44: =100-VLOOKUP(B44,'[1]Pricing '!$A$1943:$K$1972,11,FALSE) -> -1.404 | E44: =B44 -> 8.25 | F44: =100-VLOOKUP(E44,'[1]Pricing '!$A$1943:$K$1972,11,FALSE) -> -1.404 | K44: • Asset verification based on Current Balance
K45: • LLC vesting allowed
B46: PRICE ADJUSTMENTS - AIA
B49: LOAN SPECIFIC ADJUSTERS | F49: PREPAYMENT ADJUSTER | J49: FICO LTV ADJUSTMENTS
J50: FICO | K50: <=55 | L50: 55.01-60 | M50: 60.01-65 | N50: 65.01-70 | O50: 70.01-75 | P50: 75.01-80
B51: CLTV | E51: 0.25 | F51: 5YR PREPAY | I51: -1.25 | J51: 780+ | K51: -1.375 | L51: -1.25 | M51: -1.25 | N51: -1.25 | O51: -1 | P51: -0.5
B52: <$100k | E52: 0.75 | F52: 4YR PREPAY | I52: -0.875 | J52: 760-779 | K52: -1.25 | L52: -1.125 | M52: -1.125 | N52: -1.125 | O52: -0.875 | P52: -0.375
B53: >$1.0MM-$2.0MM | E53: 0.375 | F53: 3YR PREPAY | I53: -0.6 | J53: 740-759 | K53: -1.125 | L53: -1 | M53: -1 | N53: -1 | O53: -0.75 | P53: -0.25
B54: >$2.00mm-$2.50mm | E54: 0.5 | F54: 2YR PREPAY | I54: 0 | J54: 720-739 | K54: -1 | L54: -0.875 | M54: -0.75 | N54: -0.625 | O54: -0.25 | P54: 0.375
B55: Non-Warrantable - CONDO/CONDOTEL | E55: 1 | F55: 1YR PREPAY | I55: 0.5 | J55: 700-719 | K55: -0.75 | L55: -0.625 | M55: -0.25 | N55: 0.25 | O55: 0.75 | P55: 2
B56: Short-Term Rental | E56: 0.25 | F56: *NO PREPAY | I56: 1.5 | J56: 680-699 | K56: -0.375 | L56: -0.125 | M56: 0.5 | N56: 1 | O56: 1.875 | P56: N/A
B57: 45 Days Lock | E57: 0.125 | J57: 660-679 | K57: 0.125 | L57: 0.375 | M57: 1.375 | N57: 2.125 | O57: 3.375 | P57: N/A
J58: 640-659 | K58: 0.5 | L58: 1 | M58: 2.375 | N58: 2.875 | O58: N/A | P58: N/A
J59: 620-639 | K59: 1.125 | L59: 1.875 | M59: N/A | N59: N/A | O59: N/A | P59: N/A
B60: STATE ADJUSTER | F60: MICHIGAN PREPAY ADJUSTMENTS | J60: ADDITIONAL PRICE ADJUSTMENTS
B61: NY | E61: 0.25 | F61: 1YR PPP | I61: 0.75 | J61: Baltimore County-MD | K61: 0.25 | L61: 0.25 | M61: 0.25 | N61: 0.25 | O61: 0.375 | P61: 0.375
F62: 2YR PPP | I62: 1 | J62: DSCR >=1.25 | K62: -2.875 | L62: -2.875 | M62: -2.75 | N62: -2.75 | O62: -2.25 | P62: -1.375
F63: 3YR PPP | I63: 1.5 | J63: DSCR >=1.0 | K63: -2.875 | L63: -2.75 | M63: -2.375 | N63: -2.375 | O63: -2.25 | P63: -1
J64: DSCR <1.0 | K64: -2 | L64: -1.875 | M64: -1.375 | N64: 0.25 | O64: 0.75 | P64: N/A
B65: Group 1 | C65: STANDARD PREPAYMENT ALLOWED | J65: For Nat'l (No FICO) | K65: 0.25 | L65: 0.25 | M65: 0.5 | N65: 0.875 | O65: N/A | P65: N/A
B66: States | C66: AL,AZ,AK,CA,CT,CO,DC,DE,FL,GA,HI,ID, IA,LA,ME,MD,MA,MO,MT,NE,NV,NH,NY,NC,ND | J66: NonPermRes(+FICO) | K66: 0.125 | L66: 0.125 | M66: 0.25 | N66: 0.25 | O66: 0.375 | P66: 0.375
C67: OK,OR,SC,SD,TN,UT,VA,WA,WV,WI,WY | J67: Interest Only | K67: 0.25 | L67: 0.25 | M67: 0.25 | N67: 0.375 | O67: N/A | P67: N/A
B68: Group 2 | C68: NO PREPAYMENT ALLOWED | J68: 2-4 Units | K68: 0.5 | L68: 0.5 | M68: 0.5 | N68: 0.5 | O68: 0.625 | P68: 0.75
B69: States | C69: AK, KS, MN, NJ,NM,RI,VT | J69: Cash-Out | K69: 0.25 | L69: 0.25 | M69: 0.375 | N69: 0.5 | O69: 0.75 | P69: N/A
B70: Group 3 | C70: STATES with "RESTRICTED" PREPAYMENT | I70: (CLICK HERE) | J70: Florida Condo | K70: 0.125 | L70: 0.125 | M70: 0.25 | N70: 0.25 | O70: 0.375 | P70: 0.5
B71: States | C71: IL, IN, KY,OH, TX,MI,MS,PA | J71: FTHB (Excl. Foreign National) | K71: 0.5 | L71: 0.5 | M71: 0.625 | N71: 0.75 | O71: 0.75 | P71: N/A
B76: **Borrower Paid Compensation Allowed Only** AIA/AIP
B79: Click For Guideline | F79: >4 Owned properties including Financed LLPA | J79: PRICE ADJUSTMENTS - AIP
B80: AMWEST INVESTOR PLUS | F80: 5-7 properties - 0.00 | J80: FICO | K80: <=55 | L80: 55.01-60 | M80: 60.01-65 | N80: 65.01-70 | O80: 70.01-75 | P80: 75.01-80
F81: 8-10 properties- 0.125 | J81: 780+ | K81: -1.375 | L81: -0.875 | M81: -0.25 | N81: N/A | O81: N/A | P81: N/A
C82: (AIP 7/6) 7 YR ARM | D82: (AIP 15) 15 YR | E82: (AIP 30) 30 YR | F82: 11-15 properties- 0.25 | J82: 760-779 | K82: -1.125 | L82: -0.75 | M82: -0.125 | N82: N/A | O82: N/A | P82: N/A
F83: >=16 properties- 0.375 | J83: 740-759 | K83: -0.875 | L83: -0.625 | M83: 0 | N83: N/A | O83: N/A | P83: N/A
F84: ARM INFO | J84: 720-739 | K84: -0.625 | L84: -0.375 | M84: 0.375 | N84: N/A | O84: N/A | P84: N/A
B85: RATE | C85: 30 Days | D85: 30 Days | E85: 30 Days | F85: MARGIN | H85: 0.04 | J85: 700-719 | K85: -0.25 | L85: 0 | M85: 0.875 | N85: N/A | O85: N/A | P85: N/A
F86: SOFR | H86: =AAA_AAI_AAQ_AAO!D52 -> 0.036719 | J86: 680-699 | K86: 0 | L86: 0.75 | M86: 1.75 | N86: N/A | O86: N/A | P86: N/A
B87: =MIN('[1]Pricing '!$A$2919:$A$2939) -> 7.125 | C87: =-VLOOKUP($B87,[1]!AIP_71,11,FALSE)+100 -> 2.715 | D87: =-VLOOKUP($B87,[1]!AIP_15,11,FALSE)+100 -> 2.715 | E87: =-VLOOKUP($B87,[1]!AIP_30,11,FALSE)+100 -> 2.715 | F87: CAPS | H87: 5/1/5 | J87: 660-679 | K87: 1 | L87: 1.75 | M87: 2.75 | N87: N/A | O87: N/A | P87: N/A
B88: =B87+0.125 -> 7.25 | C88: =-VLOOKUP($B88,[1]!AIP_71,11,FALSE)+100 -> 2.09 | D88: =-VLOOKUP($B88,[1]!AIP_15,11,FALSE)+100 -> 2.09 | E88: =-VLOOKUP($B88,[1]!AIP_30,11,FALSE)+100 -> 2.09 | F88: Floor = | H88: Start Rate | J88: 640-659 | K88: 1.5 | L88: 2.5 | M88: N/A | N88: N/A | O88: N/A | P88: N/A
B89: =B88+0.125 -> 7.375 | C89: =-VLOOKUP($B89,[1]!AIP_71,11,FALSE)+100 -> 1.59 | D89: =-VLOOKUP($B89,[1]!AIP_15,11,FALSE)+100 -> 1.59 | E89: =-VLOOKUP($B89,[1]!AIP_30,11,FALSE)+100 -> 1.59 | F89: PROGRAM CODE: | J89: Baltimore County-MD | K89: 0.25 | L89: 0.25 | M89: 0.25 | N89: N/A | O89: N/A | P89: N/A
B90: =B89+0.125 -> 7.5 | C90: =-VLOOKUP($B90,[1]!AIP_71,11,FALSE)+100 -> 1.215 | D90: =-VLOOKUP($B90,[1]!AIP_15,11,FALSE)+100 -> 1.215 | E90: =-VLOOKUP($B90,[1]!AIP_30,11,FALSE)+100 -> 1.215 | F90: 5YR PPP Max Price of (1.500) | J90: For Nat'l (No FICO) | K90: 0.25 | L90: 0.75 | M90: 1.5 | N90: N/A | O90: N/A | P90: N/A
B91: =B90+0.125 -> 7.625 | C91: =-VLOOKUP($B91,[1]!AIP_71,11,FALSE)+100 -> 0.84 | D91: =-VLOOKUP($B91,[1]!AIP_15,11,FALSE)+100 -> 0.84 | E91: =-VLOOKUP($B91,[1]!AIP_30,11,FALSE)+100 -> 0.84 | F91: AIP7/6P5, AIP7/6P5 IO, AIP30P5, AIP15P5 | J91: NonPermRes(+FICO) | K91: 0.125 | L91: 0.25 | M91: 0.5 | N91: N/A | O91: N/A | P91: N/A
B92: =B91+0.125 -> 7.75 | C92: =-VLOOKUP($B92,[1]!AIP_71,11,FALSE)+100 -> 0.465 | D92: =-VLOOKUP($B92,[1]!AIP_15,11,FALSE)+100 -> 0.465 | E92: =-VLOOKUP($B92,[1]!AIP_30,11,FALSE)+100 -> 0.465 | F92: 4YR PPP Max Price of (1.500) | J92: Interest Only | K92: 0.25 | L92: 0.375 | M92: 0.5 | N92: N/A | O92: N/A | P92: N/A
B93: =B92+0.125 -> 7.875 | C93: =-VLOOKUP($B93,[1]!AIP_71,11,FALSE)+100 -> 0.215 | D93: =-VLOOKUP($B93,[1]!AIP_15,11,FALSE)+100 -> 0.215 | E93: =-VLOOKUP($B93,[1]!AIP_30,11,FALSE)+100 -> 0.215 | F93: AIP7/6P4, AIP7/6P4 IO, AIP30P4, AIP15P4 | J93: 2-4 Units | K93: 0.5 | L93: 0.625 | M93: 0.75 | N93: N/A | O93: N/A | P93: N/A
B94: =B93+0.125 -> 8 | C94: =-VLOOKUP($B94,[1]!AIP_71,11,FALSE)+100 -> -0.035 | D94: =-VLOOKUP($B94,[1]!AIP_15,11,FALSE)+100 -> -0.035 | E94: =-VLOOKUP($B94,[1]!AIP_30,11,FALSE)+100 -> -0.035 | F94: 3YR PPP Max Price of (1.500) | J94: Cash-Out | K94: 0.25 | L94: 0.5 | M94: 1 | N94: N/A | O94: N/A | P94: N/A
B95: =B94+0.125 -> 8.125 | C95: =-VLOOKUP($B95,[1]!AIP_71,11,FALSE)+100 -> -0.285 | D95: =-VLOOKUP($B95,[1]!AIP_15,11,FALSE)+100 -> -0.285 | E95: =-VLOOKUP($B95,[1]!AIP_30,11,FALSE)+100 -> -0.285 | F95: AIP7/6P3, AIP7/6P3 IO, AIP30P3, AIP15P3 | J95: Florida Condo | K95: 0.125 | L95: 0.125 | M95: 0.25 | N95: N/A | O95: N/A | P95: N/A
B96: =B95+0.125 -> 8.25 | C96: =-VLOOKUP($B96,[1]!AIP_71,11,FALSE)+100 -> -0.535 | D96: =-VLOOKUP($B96,[1]!AIP_15,11,FALSE)+100 -> -0.535 | E96: =-VLOOKUP($B96,[1]!AIP_30,11,FALSE)+100 -> -0.535 | F96: 2YR PPP Max Price of (1.000) | J96: First Time Homebuyer | K96: 0.75 | L96: 0.75 | M96: 0.875 | N96: N/A | O96: N/A | P96: N/A
F97: AIP7/6P2, AIP7/6P2 IO, AIP30P2 , AIP15P2 | J97: 5YR PREPAY | P97: -1.5
F98: 1YR PPP Max Price of (0.500) | J98: 4YR PREPAY | P98: -1
F99: AIP7/6P1, AIP30P1, AIP15P1 | J99: 3YR PREPAY | P99: -0.5
F100: NO PPP Max Price of (0.000) | J100: 1YR PREPAY | P100: 0.75
F101: AIP7/6 , AIP7/6IO, AIP30, AIP15 | J101: No Prepay | P101: 3
B102: NO PREPAY: | F102: Hard PPP: 3 Years (4-4-4%) | J102: CLTV | P102: 0.25
B103: Max Price (0.000) / Use 2Y PPP base price | F103: State specific restrictions may apply (AIP ONLY) | J103: <$100k | P103: 0.75
J104: >$1.0MM-$2.0MM | P104: 0.375
B105: STATE ADJUSTER | E105: MICHIGAN PREPAY ADJUSTMENTS | J105: >$2.0mm-$2.50mm | P105: 0.5
B106: NY | D106: 0.25 | E106: 1YR PPP | F106: 0.75 | H106: 2YR PPP | I106: 1 | J106: 45 Days Lock | P106: 0.125
E107: 3YR PPP | F107: 1.5 | J107: 7/6 ARM | P107: 0
J108: RATE ADJUSTMENTS - AIP
J109: 7/6 ARM - AIP | P109: 0
B110: Lender Fees: AIA/AIP $1,995 Lock Extensions: 2 bps per Day (Max of 30 Days) Redraw Fee $150.00
B111: Lock Hours until 5:00 PM PST
B112: Rates and fees are subject to change without notice.

Sheet JUMBO
P1: 9 of 12
B3: AmWest Corporate Office
B4: 6 Pointe Dr. Suite 300
B5: Brea, CA 92821
B6: (714) 831-3333
B7: www.amwestwholesale.com
F8: Wholesale Rate sheet - Consumer Paid | K8: Effective: | L8: =+TODAY() -> 46101 | M8: =AIA_AIP!L7 -> 8:00 AM PST
B10: LOAN LOCK INFO:
B12: Lock Desk : | D12: Email: LockDesk@amwestfunding.com | H12: Phone: (714) 831-3299 | K12: eFax: (714) 421-4032 | M12: Lock Hours: 8:30AM-5:00 PM PST
B14: ANNOUNCEMENT
T15: 45 DAY LOCK
T16: -0.25
B21: Click For Guideline
B22: AUS JUMBO EXPRESS
B25: (JEA30) 30 YEAR | E25: (JEA15) 15 YEAR | I25: HIGHLIGHTS
B26: RATE | C26: 30 Days | D26: 45 Days | E26: RATE | F26: 30 Days | G26: 45 Days | I26: • Loans underwritten through DU or LPA
B27: 5.875 | C27: =100-VLOOKUP(B27,'[1]Pricing '!$A$4726:$K$4752,11,FALSE) -> 2.1452 | D27: =C27-$T$16 -> 2.3952 | E27: 6.125 | F27: =100-VLOOKUP(E27,'[1]Pricing '!$A$4755:$K$4781,11,FALSE) -> 1.9757 | G27: =F27-$T$16 -> 2.2257 | I27: • Purchase , Rate-Term & Cash Out Refinance
B28: =B27+0.125 -> 6 | C28: =100-VLOOKUP(B28,'[1]Pricing '!$A$4726:$K$4752,11,FALSE) -> 1.6422 | D28: =C28-$T$16 -> 1.8922 | E28: =+E27+0.125 -> 6.25 | F28: =100-VLOOKUP(E28,'[1]Pricing '!$A$4755:$K$4781,11,FALSE) -> 1.6723 | G28: =F28-$T$16 -> 1.9223 | I28: • Loan Amounts to $3 Million
B29: =B28+0.125 -> 6.125 | C29: =100-VLOOKUP(B29,'[1]Pricing '!$A$4726:$K$4752,11,FALSE) -> 1.1823 | D29: =C29-$T$16 -> 1.4323 | E29: =E28+0.125 -> 6.375 | F29: =100-VLOOKUP(E29,'[1]Pricing '!$A$4755:$K$4781,11,FALSE) -> 1.3914 | G29: =F29-$T$16 -> 1.6414 | I29: • Primary (1-2 Units) , Second Home (1-Unit) & Investment (1-2 Units)
B30: =B29+0.125 -> 6.25 | C30: =100-VLOOKUP(B30,'[1]Pricing '!$A$4726:$K$4752,11,FALSE) -> 0.7688 | D30: =C30-$T$16 -> 1.0188 | E30: =E29+0.125 -> 6.5 | F30: =100-VLOOKUP(E30,'[1]Pricing '!$A$4755:$K$4781,11,FALSE) -> 1.1384 | G30: =F30-$T$16 -> 1.3884 | I30: • Minimum FICO: 700
B31: =B30+0.125 -> 6.375 | C31: =100-VLOOKUP(B31,'[1]Pricing '!$A$4726:$K$4752,11,FALSE) -> 0.4055 | D31: =C31-$T$16 -> 0.6555 | E31: =E30+0.125 -> 6.625 | F31: =100-VLOOKUP(E31,'[1]Pricing '!$A$4755:$K$4781,11,FALSE) -> 0.9283 | G31: =F31-$T$16 -> 1.1783 | I31: • Max DTI 50%
B32: =B31+0.125 -> 6.5 | C32: =100-VLOOKUP(B32,'[1]Pricing '!$A$4726:$K$4752,11,FALSE) -> 0.0949 | D32: =C32-$T$16 -> 0.3449 | E32: =E31+0.125 -> 6.75 | F32: =100-VLOOKUP(E32,'[1]Pricing '!$A$4755:$K$4781,11,FALSE) -> 0.6848 | G32: =F32-$T$16 -> 0.9348 | I32: • Fixed Rate with terms of 30 & 15 years
B33: =B32+0.125 -> 6.625 | C33: =100-VLOOKUP(B33,'[1]Pricing '!$A$4726:$K$4752,11,FALSE) -> -0.1896 | D33: =C33-$T$16 -> 0.0604 | E33: =E32+0.125 -> 6.875 | F33: =100-VLOOKUP(E33,'[1]Pricing '!$A$4755:$K$4781,11,FALSE) -> 0.7285 | G33: =F33-$T$16 -> 0.9785 | I33: • No Mortgage Insurance required
B34: =B33+0.125 -> 6.75 | C34: =100-VLOOKUP(B34,'[1]Pricing '!$A$4726:$K$4752,11,FALSE) -> -0.4588 | D34: =C34-$T$16 -> -0.2088 | E34: =E33+0.125 -> 7 | F34: =100-VLOOKUP(E34,'[1]Pricing '!$A$4755:$K$4781,11,FALSE) -> 0.5215 | G34: =F34-$T$16 -> 0.7715 | I34: • Minimum Loan Amount - $1 over the agency conforming loan size
B35: =B34+0.125 -> 6.875 | C35: =100-VLOOKUP(B35,'[1]Pricing '!$A$4726:$K$4752,11,FALSE) -> -0.443 | D35: =C35-$T$16 -> -0.193 | E35: =E34+0.125 -> 7.125 | F35: =100-VLOOKUP(E35,'[1]Pricing '!$A$4755:$K$4781,11,FALSE) -> 0.3311 | G35: =F35-$T$16 -> 0.5811 | I35: • LTV up to 89.99% No MI
B36: =B35+0.125 -> 7 | C36: =100-VLOOKUP(B36,'[1]Pricing '!$A$4726:$K$4752,11,FALSE) -> -0.7023 | D36: =C36-$T$16 -> -0.4523 | E36: =E35+0.125 -> 7.25 | F36: =100-VLOOKUP(E36,'[1]Pricing '!$A$4755:$K$4781,11,FALSE) -> 0.1687 | G36: =F36-$T$16 -> 0.4187 | I36: • 2:1 and 1:0 Temp Buydown Options
B37: =B36+0.125 -> 7.125 | C37: =100-VLOOKUP(B37,'[1]Pricing '!$A$4726:$K$4752,11,FALSE) -> -0.9519 | D37: =C37-$T$16 -> -0.7019 | E37: =E36+0.125 -> 7.375 | F37: =100-VLOOKUP(E37,'[1]Pricing '!$A$4755:$K$4781,11,FALSE) -> 0.0491 | G37: =F37-$T$16 -> 0.2991 | I37: Temporary Buydowns – Product codes for Buydown Option will end in
B38: =B37+0.125 -> 7.25 | C38: =100-VLOOKUP(B38,'[1]Pricing '!$A$4726:$K$4752,11,FALSE) -> -1.1896 | D38: =C38-$T$16 -> -0.9396 | E38: =E37+0.125 -> 7.5 | F38: =100-VLOOKUP(E38,'[1]Pricing '!$A$4755:$K$4781,11,FALSE) -> -0.0822 | G38: =F38-$T$16 -> 0.1678 | I38: –B1 or –B2 (B1=12 months / B2= 24 months terms).
B39: =B38+0.125 -> 7.375 | C39: =100-VLOOKUP(B39,'[1]Pricing '!$A$4726:$K$4752,11,FALSE) -> -1.4154 | D39: =C39-$T$16 -> -1.1654 | I39: 30 YEAR: | J39: JEA30-B1 / JEA30-B2
B40: =B39+0.125 -> 7.5 | C40: =100-VLOOKUP(B40,'[1]Pricing '!$A$4726:$K$4752,11,FALSE) -> -1.6298 | D40: =C40-$T$16 -> -1.3798 | I40: 15 YEAR: | J40: JEA15-B1 / JEA15-B2
D42: FICO
D43: Amort Type | F43: LTV/CLTV | H43: <=55.00 | I43: 55.01-60 | J43: 60.01-65 | K43: 65.01-70 | L43: 70.01-75 | M43: 75.01-80 | N43: 80.01-85 | O43: 85.01-90
D44: FIXED | F44: 800+ | H44: -1.115 | I44: -0.995 | J44: -0.985 | K44: -0.86 | L44: -0.485 | M44: -0.235 | N44: 0.52 | O44: 0.905
F45: 780-799 | H45: -1.115 | I45: -0.995 | J45: -0.985 | K45: -0.86 | L45: -0.485 | M45: -0.235 | N45: 0.52 | O45: 0.905
F46: 760-779 | H46: -0.995 | I46: -0.995 | J46: -0.865 | K46: -0.74 | L46: -0.355 | M46: -0.105 | N46: 0.52 | O46: 1.405
F47: 740-759 | H47: -0.865 | I47: -0.865 | J47: -0.735 | K47: -0.61 | L47: -0.105 | M47: 0.02 | N47: 0.77 | O47: 1.655
F48: 720-739 | H48: -0.735 | I48: -0.615 | J48: -0.485 | K48: -0.23 | L48: 0.02 | M48: 0.02 | N48: 1.16 | O48: 2.045
F49: 700-719 | H49: -0.485 | I49: -0.365 | J49: -0.105 | K49: -0.105 | L49: 0.02 | M49: 0.53 | N49: 2.035 | O49: 2.68
D51: OCCUPANCY
D52: Amort Type | F52: LTV/CLTV | H52: <=55.00 | I52: 55.01-60 | J52: 60.01-65 | K52: 65.01-70 | L52: 70.01-75 | M52: 75.01-80 | N52: 80.01-85 | O52: 85.01-90
D53: FIXED | F53: NOO | H53: 0.2 | I53: 0.25 | J53: 0.3 | K53: 0.45 | L53: 0.75 | M53: 1.05 | N53: N/A | O53: N/A
F54: 2nd Home | H54: 0 | I54: 0 | J54: 0.25 | K54: 0.25 | L54: 0.5 | M54: 0.75 | N54: N/A | O54: N/A
D56: LOAN PURPOSE
D57: Amort Type | F57: LTV/CLTV | H57: <=55.00 | I57: 55.01-60 | J57: 60.01-65 | K57: 65.01-70 | L57: 70.01-75 | M57: 75.01-80 | N57: 80.01-85 | O57: 85.01-90
D58: FIXED | F58: PURCHASE | H58: -0.25 | I58: -0.25 | J58: -0.25 | K58: -0.25 | L58: -0.25 | M58: -0.25 | N58: 0 | O58: 0
F59: CASH-OUT | H59: 0.125 | I59: 0.125 | J59: 0.125 | K59: 0.25 | L59: 0.375 | M59: 1 | N59: N/A | O59: N/A
D61: OTHER ADJUSTERS
D62: Amort Type | F62: LTV/CLTV | H62: <=55.00 | I62: 55.01-60 | J62: 60.01-65 | K62: 65.01-70 | L62: 70.01-75 | M62: 75.01-80 | N62: 80.01-85 | O62: 85.01-90
D63: FIXED | F63: DTI <= 30% | H63: 0 | I63: 0 | J63: 0 | K63: -0.125 | L63: -0.125 | M63: -0.25 | N63: -0.25 | O63: -0.25
F64: DTI > 45% | H64: 0.125 | I64: 0.125 | J64: 0.125 | K64: 0.25 | L64: 0.25 | M64: 0.5 | N64: N/A | O64: N/A
D67: LOAN AMOUNT ADJUSTERS | M67: MAX PRICE
D68: L.A: <=$900,000 | G68: 0 | M68: 30YR FIXED | O68: -2
D69: L.A: $900,001-$1,000,000 | G69: -0.04 | M69: 15YR FIXED | O69: -2
D70: L.A: $1,000,001-$1,100,000 | G70: -0.06
D71: L.A: $1,100,001-$1,200,000 | G71: -0.09
D72: L.A: $1,200,001-$1,300,000 | G72: -0.09
D73: L.A: $1,300,001-$1,400,000 | G73: -0.11
D74: L.A: $1,400,001-$1,500,000 | G74: -0.13
D75: L.A: $1,500,001-$1,750,000 | G75: -0.13
D76: L.A: $1,750,001-$2,000,000 | G76: -0.15
D77: L.A: $2,000,001-$2,500,000 | G77: -0.13
D78: L.A: $2,500,001-$3,000,000 | G78: -0.13
D79: L.A: $3,000,001-$3,500,000 | G79: -0.13
B87: Jumbo products must be U/W approved to lock / Investor Approval required
